Workbook
Name Vtas: Ventas_Wellpro[#All]
Name Vtas: Ventas_Wellpro4[#All]
Name Vtas: Ventas_Wellpro[#All]

Sheet Venta (2)
A1: Indica | B1: Fecha | C1: Producto | D1: Cliente | E1: Precio de Venta | F1: Cantidad Vendida | G1: IVA | H1: Total de Venta sin IVA | I1: Total de Venta con IVA | J1: Año | K1: Mes | L1: Día
B2: 45321 | C2: Inodoro Portatil con tapa y brazo | D2: Amazon | E2: 1068.94 | F2: 1 | G2: 171.03 | H2: 1068.94 | I2: 1239.97 | J2: =YEAR(Ventas_Wellpro4[[#This Row],[Fecha]]) -> 2024 | K2: =TEXT(Ventas_Wellpro4[[#This Row],[Fecha]],"MMMM") -> enero | L2: =DAY(Ventas_Wellpro4[[#This Row],[Fecha]]) -> 30
B3: 45321 | C3: Inodoro Portatil con tapa y brazo | D3: Amazon | E3: 1068.94 | F3: 3 | G3: 513.09 | H3: 3206.82 | I3: 3719.91 | J3: =YEAR(Ventas_Wellpro4[[#This Row],[Fecha]]) -> 2024 | K3: =TEXT(Ventas_Wellpro4[[#This Row],[Fecha]],"MMMM") -> enero | L3: =DAY(Ventas_Wellpro4[[#This Row],[Fecha]]) -> 30
B4: 45321 | C4: Silla de Baño con Respaldo | D4: Amazon | E4: 748.26 | F4: 1 | G4: 119.72 | H4: 748.26 | I4: 867.98 | J4: =YEAR(Ventas_Wellpro4[[#This Row],[Fecha]]) -> 2024 | K4: =TEXT(Ventas_Wellpro4[[#This Row],[Fecha]],"MMMM") -> enero | L4: =DAY(Ventas_Wellpro4[[#This Row],[Fecha]]) -> 30
B5: 45321 | C5: Silla de Baño con Respaldo | D5: Amazon | E5: 748.26 | F5: 3 | G5: 359.16 | H5: 2244.78 | I5: 2603.94 | J5: =YEAR(Ventas_Wellpro4[[#This Row],[Fecha]]) -> 2024 | K5: =TEXT(Ventas_Wellpro4[[#This Row],[Fecha]],"MMMM") -> enero | L5: =DAY(Ventas_Wellpro4[[#This Row],[Fecha]]) -> 30
B6: 45321 | C6: Silla de Ruedas STD | D6: Amazon | E6: 2419.7 | F6: 3 | G6: 1161.46 | H6: 7259.1 | I6: 8420.56 | J6: =YEAR(Ventas_Wellpro4[[#This Row],[Fecha]]) -> 2024 | K6: =TEXT(Ventas_Wellpro4[[#This Row],[Fecha]],"MMMM") -> enero | L6: =DAY(Ventas_Wellpro4[[#This Row],[Fecha]]) -> 30
B7: 45630 | C7: Nebulizador Adulto Compacto | D7: Farmacia San Pablo | E7: 505.86 | F7: 340 | G7: 27518.78 | H7: 171992.4 | I7: 199511.18 | J7: =YEAR(Ventas_Wellpro4[[#This Row],[Fecha]]) -> 2024 | K7: =TEXT(Ventas_Wellpro4[[#This Row],[Fecha]],"MMMM") -> diciembre | L7: =DAY(Ventas_Wellpro4[[#This Row],[Fecha]]) -> 4
B8: 45329 | C8: Báscula Digital de Vidrio Marmol | D8: Amazon | E8: 176.38 | F8: 6 | G8: 169.32 | H8: 1058.28 | I8: 1227.6 | J8: =YEAR(Ventas_Wellpro4[[#This Row],[Fecha]]) -> 2024 | K8: =TEXT(Ventas_Wellpro4[[#This Row],[Fecha]],"MMMM") -> febrero | L8: =DAY(Ventas_Wellpro4[[#This Row],[Fecha]]) -> 7
B9: 45329 | C9: Cojin Cuadrad Memory Foam | D9: Amazon | E9: 160.34 | F9: 5 | G9: 128.27 | H9: 801.7 | I9: 929.97 | J9: =YEAR(Ventas_Wellpro4[[#This Row],[Fecha]]) -> 2024 | K9: =TEXT(Ventas_Wellpro4[[#This Row],[Fecha]],"MMMM") -> febrero | L9: =DAY(Ventas_Wellpro4[[#This Row],[Fecha]]) -> 7
B10: 45329 | C10: Inodoro Portatil con tapa y brazo | D10: Amazon | E10: 1068.94 | F10: 1 | G10: 171.03 | H10: 1068.94 | I10: 1239.97 | J10: =YEAR(Ventas_Wellpro4[[#This Row],[Fecha]]) -> 2024 | K10: =TEXT(Ventas_Wellpro4[[#This Row],[Fecha]],"MMMM") -> febrero | L10: =DAY(Ventas_Wellpro4[[#This Row],[Fecha]]) -> 7
B11: 45329 | C11: Silla de Baño con Respaldo | D11: Amazon | E11: 748.26 | F11: 1 | G11: 119.72 | H11: 748.26 | I11: 867.98 | J11: =YEAR(Ventas_Wellpro4[[#This Row],[Fecha]]) -> 2024 | K11: =TEXT(Ventas_Wellpro4[[#This Row],[Fecha]],"MMMM") -> febrero | L11: =DAY(Ventas_Wellpro4[[#This Row],[Fecha]]) -> 7
B12: 45329 | C12: Silla de Ruedas STD | D12: Amazon | E12: 2419.7 | F12: 1 | G12: 387.15 | H12: 2419.7 | I12: 2806.85 | J12: =YEAR(Ventas_Wellpro4[[#This Row],[Fecha]]) -> 2024 | K12: =TEXT(Ventas_Wellpro4[[#This Row],[Fecha]],"MMMM") -> febrero | L12: =DAY(Ventas_Wellpro4[[#This Row],[Fecha]]) -> 7
B13: 45335 | C13: Báscula Digital de Vidrio Antideslizante | D13: Amazon | E13: 176.38 | F13: 6 | G13: 169.32 | H13: 1058.28 | I13: 1227.6 | J13: =YEAR(Ventas_Wellpro4[[#This Row],[Fecha]]) -> 2024 | K13: =TEXT(Ventas_Wellpro4[[#This Row],[Fecha]],"MMMM") -> febrero | L13: =DAY(Ventas_Wellpro4[[#This Row],[Fecha]]) -> 13
... B57: 45929 | C57: Nebulizador Adulto Compacto | D57: Farmacia Sana Sana | E57: 633.62 | F57: 4 | G57: 405.5168 | H57: 2534.48 | I57: 2939.9968 | J57: =YEAR(Ventas_Wellpro4[[#This Row],[Fecha]]) -> 2025 | K57: =TEXT(Ventas_Wellpro4[[#This Row],[Fecha]],"MMMM") -> septiembre | L57: =DAY(Ventas_Wellpro4[[#This Row],[Fecha]]) -> 29
B58: 45931 | C58: Nebulizador Adulto Walmart | D58: Walmart | E58: 498.66 | F58: 6 | G58: =+(Ventas_Wellpro4[[#This Row],[Precio de Venta]]*0.16)*Ventas_Wellpro4[[#This Row],[Cantidad Vendida]] -> 478.7136 | H58: 2991.96 | I58: =+Ventas_Wellpro4[[#This Row],[Total de Venta sin IVA]]+Ventas_Wellpro4[[#This Row],[IVA]] -> 3470.6736 | J58: =YEAR(Ventas_Wellpro4[[#This Row],[Fecha]]) -> 2025 | K58: =TEXT(Ventas_Wellpro4[[#This Row],[Fecha]],"MMMM") -> octubre | L58: =DAY(Ventas_Wellpro4[[#This Row],[Fecha]]) -> 1
B59: 45931 | C59: Nebulizador Adulto Walmart | D59: Walmart | E59: 498.66 | F59: 36 | G59: =+(Ventas_Wellpro4[[#This Row],[Precio de Venta]]*0.16)*Ventas_Wellpro4[[#This Row],[Cantidad Vendida]] -> 2872.2816 | H59: 17951.76 | I59: =+Ventas_Wellpro4[[#This Row],[Total de Venta sin IVA]]+Ventas_Wellpro4[[#This Row],[IVA]] -> 20824.042 | J59: =YEAR(Ventas_Wellpro4[[#This Row],[Fecha]]) -> 2025 | K59: =TEXT(Ventas_Wellpro4[[#This Row],[Fecha]],"MMMM") -> octubre | L59: =DAY(Ventas_Wellpro4[[#This Row],[Fecha]]) -> 1
B60: 45931 | C60: Nebulizador Adulto Walmart | D60: Walmart | E60: 498.66 | F60: 12 | G60: =+(Ventas_Wellpro4[[#This Row],[Precio de Venta]]*0.16)*Ventas_Wellpro4[[#This Row],[Cantidad Vendida]] -> 957.4272 | H60: 5983.92 | I60: =+Ventas_Wellpro4[[#This Row],[Total de Venta sin IVA]]+Ventas_Wellpro4[[#This Row],[IVA]] -> 6941.3472 | J60: =YEAR(Ventas_Wellpro4[[#This Row],[Fecha]]) -> 2025 | K60: =TEXT(Ventas_Wellpro4[[#This Row],[Fecha]],"MMMM") -> octubre | L60: =DAY(Ventas_Wellpro4[[#This Row],[Fecha]]) -> 1
B61: 45931 | C61: Nebulizador Adulto Walmart | D61: Walmart | E61: 498.66 | F61: 6 | G61: =+(Ventas_Wellpro4[[#This Row],[Precio de Venta]]*0.16)*Ventas_Wellpro4[[#This Row],[Cantidad Vendida]] -> 478.7136 | H61: 2991.96 | I61: =+Ventas_Wellpro4[[#This Row],[Total de Venta sin IVA]]+Ventas_Wellpro4[[#This Row],[IVA]] -> 3470.6736 | J61: =YEAR(Ventas_Wellpro4[[#This Row],[Fecha]]) -> 2025 | K61: =TEXT(Ventas_Wellpro4[[#This Row],[Fecha]],"MMMM") -> octubre | L61: =DAY(Ventas_Wellpro4[[#This Row],[Fecha]]) -> 1
B62: 45482 | C62: Termómetro Pediatrico Cute Animals Panda | D62: Walmart | E62: 70.05 | F62: 240 | G62: 2689.92 | H62: 16812 | I62: 19501.92 | J62: =YEAR(Ventas_Wellpro4[[#This Row],[Fecha]]) -> 2024 | K62: =TEXT(Ventas_Wellpro4[[#This Row],[Fecha]],"MMMM") -> julio | L62: =DAY(Ventas_Wellpro4[[#This Row],[Fecha]]) -> 9
B63: 45482 | C63: Termómetro Pediatrico Cute Animals Panda | D63: Walmart | E63: 70.05 | F63: 240 | G63: 2689.92 | H63: 16812 | I63: 19501.92 | J63: =YEAR(Ventas_Wellpro4[[#This Row],[Fecha]]) -> 2024 | K63: =TEXT(Ventas_Wellpro4[[#This Row],[Fecha]],"MMMM") -> julio | L63: =DAY(Ventas_Wellpro4[[#This Row],[Fecha]]) -> 9
B64: 45482 | C64: Termómetro Pediatrico Cute Animals Panda | D64: Walmart | E64: 70.05 | F64: 240 | G64: 2689.92 | H64: 16812 | I64: 19501.92 | J64: =YEAR(Ventas_Wellpro4[[#This Row],[Fecha]]) -> 2024 | K64: =TEXT(Ventas_Wellpro4[[#This Row],[Fecha]],"MMMM") -> julio | L64: =DAY(Ventas_Wellpro4[[#This Row],[Fecha]]) -> 9
B65: 45482 | C65: Termómetro Pediatrico Cute Animals Panda | D65: Walmart | E65: 70.05 | F65: 240 | G65: 2689.92 | H65: 16812 | I65: 19501.92 | J65: =YEAR(Ventas_Wellpro4[[#This Row],[Fecha]]) -> 2024 | K65: =TEXT(Ventas_Wellpro4[[#This Row],[Fecha]],"MMMM") -> julio | L65: =DAY(Ventas_Wellpro4[[#This Row],[Fecha]]) -> 9
B66: 45482 | C66: Termómetro Pediatrico Cute Animals Panda | D66: Walmart | E66: 70.05 | F66: 240 | G66: 2689.92 | H66: 16812 | I66: 19501.92 | J66: =YEAR(Ventas_Wellpro4[[#This Row],[Fecha]]) -> 2024 | K66: =TEXT(Ventas_Wellpro4[[#This Row],[Fecha]],"MMMM") -> julio | L66: =DAY(Ventas_Wellpro4[[#This Row],[Fecha]]) -> 9
B67: 45931 | C67: Nebulizador Adulto Walmart | D67: Walmart | E67: 498.66 | F67: 6 | G67: =+(Ventas_Wellpro4[[#This Row],[Precio de Venta]]*0.16)*Ventas_Wellpro4[[#This Row],[Cantidad Vendida]] -> 478.7136 | H67: 2991.96 | I67: =+Ventas_Wellpro4[[#This Row],[Total de Venta sin IVA]]+Ventas_Wellpro4[[#This Row],[IVA]] -> 3470.6736 | J67: =YEAR(Ventas_Wellpro4[[#This Row],[Fecha]]) -> 2025 | K67: =TEXT(Ventas_Wellpro4[[#This Row],[Fecha]],"MMMM") -> octubre | L67: =DAY(Ventas_Wellpro4[[#This Row],[Fecha]]) -> 1
B68: 45931 | C68: Termómetro Pediatrico Cute Animals Koala | D68: MERCADO LIBRE | E68: 137.79 | F68: 1 | G68: =+(Ventas_Wellpro4[[#This Row],[Precio de Venta]]*0.16)*Ventas_Wellpro4[[#This Row],[Cantidad Vendida]] -> 22.0464 | H68: 137.79 | I68: =+Ventas_Wellpro4[[#This Row],[Total de Venta sin IVA]]+Ventas_Wellpro4[[#This Row],[IVA]] -> 159.8364 | J68: =YEAR(Ventas_Wellpro4[[#This Row],[Fecha]]) -> 2025 | K68: =TEXT(Ventas_Wellpro4[[#This Row],[Fecha]],"MMMM") -> octubre | L68: =DAY(Ventas_Wellpro4[[#This Row],[Fecha]]) -> 1
B69: 45484 | C69: Termómetro Pediatrico Cute Animals Panda | D69: Walmart | E69: 70.05 | F69: 240 | G69: 2689.92 | H69: 16812 | I69: 19501.92 | J69: =YEAR(Ventas_Wellpro4[[#This Row],[Fecha]]) -> 2024 | K69: =TEXT(Ventas_Wellpro4[[#This Row],[Fecha]],"MMMM") -> julio | L69: =DAY(Ventas_Wellpro4[[#This Row],[Fecha]]) -> 11
B70: 45488 | C70: Termómetro Pediatrico Cute Animals Koala | D70: Amazon | E70: 93.01 | F70: 240 | G70: 3571.58 | H70: 22322.4 | I70: 25893.98 | J70: =YEAR(Ventas_Wellpro4[[#This Row],[Fecha]]) -> 2024 | K70: =TEXT(Ventas_Wellpro4[[#This Row],[Fecha]],"MMMM") -> julio | L70: =DAY(Ventas_Wellpro4[[#This Row],[Fecha]]) -> 15
B71: 45931 | C71: Termómetro Pediatrico Cute Animals Ranita | D71: MERCADO LIBRE | E71: 137.79 | F71: 1 | G71: =+(Ventas_Wellpro4[[#This Row],[Precio de Venta]]*0.16)*Ventas_Wellpro4[[#This Row],[Cantidad Vendida]] -> 22.0464 | H71: 137.79 | I71: =+Ventas_Wellpro4[[#This Row],[Total de Venta sin IVA]]+Ventas_Wellpro4[[#This Row],[IVA]] -> 159.8364 | J71: =YEAR(Ventas_Wellpro4[[#This Row],[Fecha]]) -> 2025 | K71: =TEXT(Ventas_Wellpro4[[#This Row],[Fecha]],"MMMM") -> octubre | L71: =DAY(Ventas_Wellpro4[[#This Row],[Fecha]]) -> 1
B72: 45931 | C72: Inodoro Portatil con tapa y brazo | D72: MERCADO LIBRE | E72: 1706.9 | F72: 1 | G72: =+(Ventas_Wellpro4[[#This Row],[Precio de Venta]]*0.16)*Ventas_Wellpro4[[#This Row],[Cantidad Vendida]] -> 273.104 | H72: 1706.9 | I72: =+Ventas_Wellpro4[[#This Row],[Total de Venta sin IVA]]+Ventas_Wellpro4[[#This Row],[IVA]] -> 1980.004 | J72: =YEAR(Ventas_Wellpro4[[#This Row],[Fecha]]) -> 2025 | K72: =TEXT(Ventas_Wellpro4[[#This Row],[Fecha]],"MMMM") -> octubre | L72: =DAY(Ventas_Wellpro4[[#This Row],[Fecha]]) -> 1
B73: 45931 | C73: Termómetro Pediatrico Cute Animals Cerdito | D73: MERCADO LIBRE | E73: 137.79 | F73: 1 | G73: =+(Ventas_Wellpro4[[#This Row],[Precio de Venta]]*0.16)*Ventas_Wellpro4[[#This Row],[Cantidad Vendida]] -> 22.0464 | H73: 137.79 | I73: =+Ventas_Wellpro4[[#This Row],[Total de Venta sin IVA]]+Ventas_Wellpro4[[#This Row],[IVA]] -> 159.8364 | J73: =YEAR(Ventas_Wellpro4[[#This Row],[Fecha]]) -> 2025 | K73: =TEXT(Ventas_Wellpro4[[#This Row],[Fecha]],"MMMM") -> octubre | L73: =DAY(Ventas_Wellpro4[[#This Row],[Fecha]]) -> 1
B74: 45912 | C74: Nebulizador Adulto Moderno NBA-10WA | D74: Mercado Libre | E74: 905.16 | F74: 1 | G74: 144.8256 | H74: 905.16 | I74: 1049.9856 | J74: =YEAR(Ventas_Wellpro4[[#This Row],[Fecha]]) -> 2025 | K74: =TEXT(Ventas_Wellpro4[[#This Row],[Fecha]],"MMMM") -> septiembre | L74: =DAY(Ventas_Wellpro4[[#This Row],[Fecha]]) -> 12
B75: 45931 | C75: Nebulizador Pediatrico Elefante Celeste | D75: Walmart | E75: 525.59 | F75: 24 | G75: =+(Ventas_Wellpro4[[#This Row],[Precio de Venta]]*0.16)*Ventas_Wellpro4[[#This Row],[Cantidad Vendida]] -> 2018.2656 | H75: 12614.16 | I75: =+Ventas_Wellpro4[[#This Row],[Total de Venta sin IVA]]+Ventas_Wellpro4[[#This Row],[IVA]] -> 14632.426 | J75: =YEAR(Ventas_Wellpro4[[#This Row],[Fecha]]) -> 2025 | K75: =TEXT(Ventas_Wellpro4[[#This Row],[Fecha]],"MMMM") -> octubre | L75: =DAY(Ventas_Wellpro4[[#This Row],[Fecha]]) -> 1
B76: 45931 | C76: Nebulizador Pediatrico Elefante Celeste | D76: Walmart | E76: 525.59 | F76: 102 | G76: =+(Ventas_Wellpro4[[#This Row],[Precio de Venta]]*0.16)*Ventas_Wellpro4[[#This Row],[Cantidad Vendida]] -> 8577.6288 | H76: 53610.18 | I76: =+Ventas_Wellpro4[[#This Row],[Total de Venta sin IVA]]+Ventas_Wellpro4[[#This Row],[IVA]] -> 62187.809 | J76: =YEAR(Ventas_Wellpro4[[#This Row],[Fecha]]) -> 2025 | K76: =TEXT(Ventas_Wellpro4[[#This Row],[Fecha]],"MMMM") -> octubre | L76: =DAY(Ventas_Wellpro4[[#This Row],[Fecha]]) -> 1
B77: 45931 | C77: Nebulizador Pediatrico Elefante Celeste | D77: Walmart | E77: 525.59 | F77: 54 | G77: =+(Ventas_Wellpro4[[#This Row],[Precio de Venta]]*0.16)*Ventas_Wellpro4[[#This Row],[Cantidad Vendida]] -> 4541.0976 | H77: 28381.86 | I77: =+Ventas_Wellpro4[[#This Row],[Total de Venta sin IVA]]+Ventas_Wellpro4[[#This Row],[IVA]] -> 32922.958 | J77: =YEAR(Ventas_Wellpro4[[#This Row],[Fecha]]) -> 2025 | K77: =TEXT(Ventas_Wellpro4[[#This Row],[Fecha]],"MMMM") -> octubre | L77: =DAY(Ventas_Wellpro4[[#This Row],[Fecha]]) -> 1
B78: 45931 | C78: Nebulizador Pediatrico Elefante Celeste | D78: Walmart | E78: 525.59 | F78: 66 | G78: =+(Ventas_Wellpro4[[#This Row],[Precio de Venta]]*0.16)*Ventas_Wellpro4[[#This Row],[Cantidad Vendida]] -> 5550.2304 | H78: 34688.94 | I78: =+Ventas_Wellpro4[[#This Row],[Total de Venta sin IVA]]+Ventas_Wellpro4[[#This Row],[IVA]] -> 40239.17 | J78: =YEAR(Ventas_Wellpro4[[#This Row],[Fecha]]) -> 2025 | K78: =TEXT(Ventas_Wellpro4[[#This Row],[Fecha]],"MMMM") -> octubre | L78: =DAY(Ventas_Wellpro4[[#This Row],[Fecha]]) -> 1
B79: 45931 | C79: Nebulizador Pediatrico Elefante Celeste | D79: Walmart | E79: 525.59 | F79: 60 | G79: =+(Ventas_Wellpro4[[#This Row],[Precio de Venta]]*0.16)*Ventas_Wellpro4[[#This Row],[Cantidad Vendida]] -> 5045.664 | H79: 31535.4 | I79: =+Ventas_Wellpro4[[#This Row],[Total de Venta sin IVA]]+Ventas_Wellpro4[[#This Row],[IVA]] -> 36581.064 | J79: =YEAR(Ventas_Wellpro4[[#This Row],[Fecha]]) -> 2025 | K79: =TEXT(Ventas_Wellpro4[[#This Row],[Fecha]],"MMMM") -> octubre | L79: =DAY(Ventas_Wellpro4[[#This Row],[Fecha]]) -> 1
B80: 45932 | C80: Nebulizador Adulto Walmart | D80: Walmart | E80: 498.66 | F80: 6 | G80: =+(Ventas_Wellpro4[[#This Row],[Precio de Venta]]*0.16)*Ventas_Wellpro4[[#This Row],[Cantidad Vendida]] -> 478.7136 | H80: 2991.96 | I80: =+Ventas_Wellpro4[[#This Row],[Total de Venta sin IVA]]+Ventas_Wellpro4[[#This Row],[IVA]] -> 3470.6736 | J80: =YEAR(Ventas_Wellpro4[[#This Row],[Fecha]]) -> 2025 | K80: =TEXT(Ventas_Wellpro4[[#This Row],[Fecha]],"MMMM") -> octubre | L80: =DAY(Ventas_Wellpro4[[#This Row],[Fecha]]) -> 2
B81: 45932 | C81: Nebulizador Adulto Walmart | D81: Walmart | E81: 498.66 | F81: 6 | G81: =+(Ventas_Wellpro4[[#This Row],[Precio de Venta]]*0.16)*Ventas_Wellpro4[[#This Row],[Cantidad Vendida]] -> 478.7136 | H81: 2991.96 | I81: =+Ventas_Wellpro4[[#This Row],[Total de Venta sin IVA]]+Ventas_Wellpro4[[#This Row],[IVA]] -> 3470.6736 | J81: =YEAR(Ventas_Wellpro4[[#This Row],[Fecha]]) -> 2025 | K81: =TEXT(Ventas_Wellpro4[[#This Row],[Fecha]],"MMMM") -> octubre | L81: =DAY(Ventas_Wellpro4[[#This Row],[Fecha]]) -> 2
B82: 45932 | C82: Nebulizador Adulto Walmart | D82: Walmart | E82: 498.66 | F82: 6 | G82: =+(Ventas_Wellpro4[[#This Row],[Precio de Venta]]*0.16)*Ventas_Wellpro4[[#This Row],[Cantidad Vendida]] -> 478.7136 | H82: 2991.96 | I82: =+Ventas_Wellpro4[[#This Row],[Total de Venta sin IVA]]+Ventas_Wellpro4[[#This Row],[IVA]] -> 3470.6736 | J82: =YEAR(Ventas_Wellpro4[[#This Row],[Fecha]]) -> 2025 | K82: =TEXT(Ventas_Wellpro4[[#This Row],[Fecha]],"MMMM") -> octubre | L82: =DAY(Ventas_Wellpro4[[#This Row],[Fecha]]) -> 2
B83: 45932 | C83: Nebulizador Adulto Walmart | D83: Walmart | E83: 498.66 | F83: 12 | G83: =+(Ventas_Wellpro4[[#This Row],[Precio de Venta]]*0.16)*Ventas_Wellpro4[[#This Row],[Cantidad Vendida]] -> 957.4272 | H83: 5983.92 | I83: =+Ventas_Wellpro4[[#This Row],[Total de Venta sin IVA]]+Ventas_Wellpro4[[#This Row],[IVA]] -> 6941.3472 | J83: =YEAR(Ventas_Wellpro4[[#This Row],[Fecha]]) -> 2025 | K83: =TEXT(Ventas_Wellpro4[[#This Row],[Fecha]],"MMMM") -> octubre | L83: =DAY(Ventas_Wellpro4[[#This Row],[Fecha]]) -> 2
B84: 45932 | C84: Nebulizador Adulto Walmart | D84: Walmart | E84: 498.66 | F84: 12 | G84: =+(Ventas_Wellpro4[[#This Row],[Precio de Venta]]*0.16)*Ventas_Wellpro4[[#This Row],[Cantidad Vendida]] -> 957.4272 | H84: 5983.92 | I84: =+Ventas_Wellpro4[[#This Row],[Total de Venta sin IVA]]+Ventas_Wellpro4[[#This Row],[IVA]] -> 6941.3472 | J84: =YEAR(Ventas_Wellpro4[[#This Row],[Fecha]]) -> 2025 | K84: =TEXT(Ventas_Wellpro4[[#This Row],[Fecha]],"MMMM") -> octubre | L84: =DAY(Ventas_Wellpro4[[#This Row],[Fecha]]) -> 2
B85: 45932 | C85: Nebulizador Adulto Walmart | D85: Walmart | E85: 498.66 | F85: 18 | G85: =+(Ventas_Wellpro4[[#This Row],[Precio de Venta]]*0.16)*Ventas_Wellpro4[[#This Row],[Cantidad Vendida]] -> 1436.1408 | H85: 8975.88 | I85: =+Ventas_Wellpro4[[#This Row],[Total de Venta sin IVA]]+Ventas_Wellpro4[[#This Row],[IVA]] -> 10412.021 | J85: =YEAR(Ventas_Wellpro4[[#This Row],[Fecha]]) -> 2025 | K85: =TEXT(Ventas_Wellpro4[[#This Row],[Fecha]],"MMMM") -> octubre | L85: =DAY(Ventas_Wellpro4[[#This Row],[Fecha]]) -> 2
B86: 45932 | C86: Nebulizador Adulto Walmart | D86: Walmart | E86: 498.66 | F86: 6 | G86: =+(Ventas_Wellpro4[[#This Row],[Precio de Venta]]*0.16)*Ventas_Wellpro4[[#This Row],[Cantidad Vendida]] -> 478.7136 | H86: 2991.96 | I86: =+Ventas_Wellpro4[[#This Row],[Total de Venta sin IVA]]+Ventas_Wellpro4[[#This Row],[IVA]] -> 3470.6736 | J86: =YEAR(Ventas_Wellpro4[[#This Row],[Fecha]]) -> 2025 | K86: =TEXT(Ventas_Wellpro4[[#This Row],[Fecha]],"MMMM") -> octubre | L86: =DAY(Ventas_Wellpro4[[#This Row],[Fecha]]) -> 2
B87: 45490 | C87: Termómetro Pediatrico Cute Animals Panda | D87: Walmart | E87: 70.05 | F87: 240 | G87: 2689.92 | H87: 16812 | I87: 19501.92 | J87: =YEAR(Ventas_Wellpro4[[#This Row],[Fecha]]) -> 2024 | K87: =TEXT(Ventas_Wellpro4[[#This Row],[Fecha]],"MMMM") -> julio | L87: =DAY(Ventas_Wellpro4[[#This Row],[Fecha]]) -> 17
B88: 45490 | C88: Termómetro Pediatrico Cute Animals Panda | D88: Walmart | E88: 70.05 | F88: 240 | G88: 2689.92 | H88: 16812 | I88: 19501.92 | J88: =YEAR(Ventas_Wellpro4[[#This Row],[Fecha]]) -> 2024 | K88: =TEXT(Ventas_Wellpro4[[#This Row],[Fecha]],"MMMM") -> julio | L88: =DAY(Ventas_Wellpro4[[#This Row],[Fecha]]) -> 17
B89: 45490 | C89: Termómetro Pediatrico Cute Animals Panda | D89: Walmart | E89: 70.05 | F89: 240 | G89: 2689.92 | H89: 16812 | I89: 19501.92 | J89: =YEAR(Ventas_Wellpro4[[#This Row],[Fecha]]) -> 2024 | K89: =TEXT(Ventas_Wellpro4[[#This Row],[Fecha]],"MMMM") -> julio | L89: =DAY(Ventas_Wellpro4[[#This Row],[Fecha]]) -> 17
B90: 45490 | C90: Termómetro Pediatrico Cute Animals Panda | D90: Walmart | E90: 70.05 | F90: 240 | G90: 2689.92 | H90: 16812 | I90: 19501.92 | J90: =YEAR(Ventas_Wellpro4[[#This Row],[Fecha]]) -> 2024 | K90: =TEXT(Ventas_Wellpro4[[#This Row],[Fecha]],"MMMM") -> julio | L90: =DAY(Ventas_Wellpro4[[#This Row],[Fecha]]) -> 17
B91: 45490 | C91: Termómetro Pediatrico Cute Animals Panda | D91: Walmart | E91: 70.05 | F91: 240 | G91: 2689.92 | H91: 16812 | I91: 19501.92 | J91: =YEAR(Ventas_Wellpro4[[#This Row],[Fecha]]) -> 2024 | K91: =TEXT(Ventas_Wellpro4[[#This Row],[Fecha]],"MMMM") -> julio | L91: =DAY(Ventas_Wellpro4[[#This Row],[Fecha]]) -> 17
B92: 45932 | C92: Nebulizador Adulto Walmart | D92: Walmart | E92: 498.66 | F92: 12 | G92: =+(Ventas_Wellpro4[[#This Row],[Precio de Venta]]*0.16)*Ventas_Wellpro4[[#This Row],[Cantidad Vendida]] -> 957.4272 | H92: 5983.92 | I92: =+Ventas_Wellpro4[[#This Row],[Total de Venta sin IVA]]+Ventas_Wellpro4[[#This Row],[IVA]] -> 6941.3472 | J92: =YEAR(Ventas_Wellpro4[[#This Row],[Fecha]]) -> 2025 | K92: =TEXT(Ventas_Wellpro4[[#This Row],[Fecha]],"MMMM") -> octubre | L92: =DAY(Ventas_Wellpro4[[#This Row],[Fecha]]) -> 2
B93: 45932 | C93: Termómetro Pediatrico Cute Animals Panda | D93: Walmart | E93: 70.05 | F93: 240 | G93: =+(Ventas_Wellpro4[[#This Row],[Precio de Venta]]*0.16)*Ventas_Wellpro4[[#This Row],[Cantidad Vendida]] -> 2689.92 | H93: 16812 | I93: =+Ventas_Wellpro4[[#This Row],[Total de Venta sin IVA]]+Ventas_Wellpro4[[#This Row],[IVA]] -> 19501.92 | J93: =YEAR(Ventas_Wellpro4[[#This Row],[Fecha]]) -> 2025 | K93: =TEXT(Ventas_Wellpro4[[#This Row],[Fecha]],"MMMM") -> octubre | L93: =DAY(Ventas_Wellpro4[[#This Row],[Fecha]]) -> 2
B94: 45932 | C94: Termómetro Pediatrico Cute Animals Panda | D94: Walmart | E94: 70.05 | F94: 240 | G94: =+(Ventas_Wellpro4[[#This Row],[Precio de Venta]]*0.16)*Ventas_Wellpro4[[#This Row],[Cantidad Vendida]] -> 2689.92 | H94: 16812 | I94: =+Ventas_Wellpro4[[#This Row],[Total de Venta sin IVA]]+Ventas_Wellpro4[[#This Row],[IVA]] -> 19501.92 | J94: =YEAR(Ventas_Wellpro4[[#This Row],[Fecha]]) -> 2025 | K94: =TEXT(Ventas_Wellpro4[[#This Row],[Fecha]],"MMMM") -> octubre | L94: =DAY(Ventas_Wellpro4[[#This Row],[Fecha]]) -> 2
B95: 45932 | C95: Termómetro Pediatrico Cute Animals Ranita | D95: MERCADO LIBRE | E95: 137.795 | F95: 2 | G95: =+(Ventas_Wellpro4[[#This Row],[Precio de Venta]]*0.16)*Ventas_Wellpro4[[#This Row],[Cantidad Vendida]] -> 44.0944 | H95: 275.59 | I95: =+Ventas_Wellpro4[[#This Row],[Total de Venta sin IVA]]+Ventas_Wellpro4[[#This Row],[IVA]] -> 319.6844 | J95: =YEAR(Ventas_Wellpro4[[#This Row],[Fecha]]) -> 2025 | K95: =TEXT(Ventas_Wellpro4[[#This Row],[Fecha]],"MMMM") -> octubre | L95: =DAY(Ventas_Wellpro4[[#This Row],[Fecha]]) -> 2
B96: 45932 | C96: Inodoro Portatil con tapa y brazo | D96: MERCADO LIBRE | E96: 1706.9 | F96: 1 | G96: =+(Ventas_Wellpro4[[#This Row],[Precio de Venta]]*0.16)*Ventas_Wellpro4[[#This Row],[Cantidad Vendida]] -> 273.104 | H96: 1706.9 | I96: =+Ventas_Wellpro4[[#This Row],[Total de Venta sin IVA]]+Ventas_Wellpro4[[#This Row],[IVA]] -> 1980.004 | J96: =YEAR(Ventas_Wellpro4[[#This Row],[Fecha]]) -> 2025 | K96: =TEXT(Ventas_Wellpro4[[#This Row],[Fecha]],"MMMM") -> octubre | L96: =DAY(Ventas_Wellpro4[[#This Row],[Fecha]]) -> 2
B97: 45932 | C97: Nebulizador Pediatrico Elefante Celeste | D97: Walmart | E97: 525.59 | F97: 24 | G97: =+(Ventas_Wellpro4[[#This Row],[Precio de Venta]]*0.16)*Ventas_Wellpro4[[#This Row],[Cantidad Vendida]] -> 2018.2656 | H97: 12614.16 | I97: =+Ventas_Wellpro4[[#This Row],[Total de Venta sin IVA]]+Ventas_Wellpro4[[#This Row],[IVA]] -> 14632.426 | J97: =YEAR(Ventas_Wellpro4[[#This Row],[Fecha]]) -> 2025 | K97: =TEXT(Ventas_Wellpro4[[#This Row],[Fecha]],"MMMM") -> octubre | L97: =DAY(Ventas_Wellpro4[[#This Row],[Fecha]]) -> 2
B98: 45932 | C98: Nebulizador Pediatrico Elefante Celeste | D98: Walmart | E98: 525.59 | F98: 12 | G98: =+(Ventas_Wellpro4[[#This Row],[Precio de Venta]]*0.16)*Ventas_Wellpro4[[#This Row],[Cantidad Vendida]] -> 1009.1328 | H98: 6307.08 | I98: =+Ventas_Wellpro4[[#This Row],[Total de Venta sin IVA]]+Ventas_Wellpro4[[#This Row],[IVA]] -> 7316.2128 | J98: =YEAR(Ventas_Wellpro4[[#This Row],[Fecha]]) -> 2025 | K98: =TEXT(Ventas_Wellpro4[[#This Row],[Fecha]],"MMMM") -> octubre | L98: =DAY(Ventas_Wellpro4[[#This Row],[Fecha]]) -> 2
B99: 45932 | C99: Nebulizador Pediatrico Elefante Celeste | D99: Walmart | E99: 525.59 | F99: 6 | G99: =+(Ventas_Wellpro4[[#This Row],[Precio de Venta]]*0.16)*Ventas_Wellpro4[[#This Row],[Cantidad Vendida]] -> 504.5664 | H99: 3153.54 | I99: =+Ventas_Wellpro4[[#This Row],[Total de Venta sin IVA]]+Ventas_Wellpro4[[#This Row],[IVA]] -> 3658.1064 | J99: =YEAR(Ventas_Wellpro4[[#This Row],[Fecha]]) -> 2025 | K99: =TEXT(Ventas_Wellpro4[[#This Row],[Fecha]],"MMMM") -> octubre | L99: =DAY(Ventas_Wellpro4[[#This Row],[Fecha]]) -> 2
B100: 45492 | C100: Termómetro Pediatrico Cute Animals Panda | D100: Walmart | E100: 70.05 | F100: 240 | G100: 2689.92 | H100: 16812 | I100: 19501.92 | J100: =YEAR(Ventas_Wellpro4[[#This Row],[Fecha]]) -> 2024 | K100: =TEXT(Ventas_Wellpro4[[#This Row],[Fecha]],"MMMM") -> julio | L100: =DAY(Ventas_Wellpro4[[#This Row],[Fecha]]) -> 19
B101: 45492 | C101: Termómetro Pediatrico Cute Animals Panda | D101: Walmart | E101: 70.05 | F101: 240 | G101: 2689.92 | H101: 16812 | I101: 19501.92 | J101: =YEAR(Ventas_Wellpro4[[#This Row],[Fecha]]) -> 2024 | K101: =TEXT(Ventas_Wellpro4[[#This Row],[Fecha]],"MMMM") -> julio | L101: =DAY(Ventas_Wellpro4[[#This Row],[Fecha]]) -> 19
B102: 45492 | C102: Termómetro Pediatrico Cute Animals Panda | D102: Walmart | E102: 70.05 | F102: 240 | G102: 2689.92 | H102: 16812 | I102: 19501.92 | J102: =YEAR(Ventas_Wellpro4[[#This Row],[Fecha]]) -> 2024 | K102: =TEXT(Ventas_Wellpro4[[#This Row],[Fecha]],"MMMM") -> julio | L102: =DAY(Ventas_Wellpro4[[#This Row],[Fecha]]) -> 19
B103: 45932 | C103: Nebulizador Pediatrico Elefante Celeste | D103: Walmart | E103: 525.59 | F103: 30 | G103: =+(Ventas_Wellpro4[[#This Row],[Precio de Venta]]*0.16)*Ventas_Wellpro4[[#This Row],[Cantidad Vendida]] -> 2522.832 | H103: 15767.7 | I103: =+Ventas_Wellpro4[[#This Row],[Total de Venta sin IVA]]+Ventas_Wellpro4[[#This Row],[IVA]] -> 18290.532 | J103: =YEAR(Ventas_Wellpro4[[#This Row],[Fecha]]) -> 2025 | K103: =TEXT(Ventas_Wellpro4[[#This Row],[Fecha]],"MMMM") -> octubre | L103: =DAY(Ventas_Wellpro4[[#This Row],[Fecha]]) -> 2
B104: 45932 | C104: Nebulizador Pediatrico Elefante Celeste | D104: Walmart | E104: 525.59 | F104: 6 | G104: =+(Ventas_Wellpro4[[#This Row],[Precio de Venta]]*0.16)*Ventas_Wellpro4[[#This Row],[Cantidad Vendida]] -> 504.5664 | H104: 3153.54 | I104: =+Ventas_Wellpro4[[#This Row],[Total de Venta sin IVA]]+Ventas_Wellpro4[[#This Row],[IVA]] -> 3658.1064 | J104: =YEAR(Ventas_Wellpro4[[#This Row],[Fecha]]) -> 2025 | K104: =TEXT(Ventas_Wellpro4[[#This Row],[Fecha]],"MMMM") -> octubre | L104: =DAY(Ventas_Wellpro4[[#This Row],[Fecha]]) -> 2
B105: 45932 | C105: Nebulizador Pediatrico Elefante Celeste | D105: Walmart | E105: 525.59 | F105: 36 | G105: =+(Ventas_Wellpro4[[#This Row],[Precio de Venta]]*0.16)*Ventas_Wellpro4[[#This Row],[Cantidad Vendida]] -> 3027.3984 | H105: 18921.24 | I105: =+Ventas_Wellpro4[[#This Row],[Total de Venta sin IVA]]+Ventas_Wellpro4[[#This Row],[IVA]] -> 21948.638 | J105: =YEAR(Ventas_Wellpro4[[#This Row],[Fecha]]) -> 2025 | K105: =TEXT(Ventas_Wellpro4[[#This Row],[Fecha]],"MMMM") -> octubre | L105: =DAY(Ventas_Wellpro4[[#This Row],[Fecha]]) -> 2
B106: 45932 | C106: Nebulizador Pediatrico Elefante Celeste | D106: Walmart | E106: 525.59 | F106: 42 | G106: =+(Ventas_Wellpro4[[#This Row],[Precio de Venta]]*0.16)*Ventas_Wellpro4[[#This Row],[Cantidad Vendida]] -> 3531.9648 | H106: 22074.78 | I106: =+Ventas_Wellpro4[[#This Row],[Total de Venta sin IVA]]+Ventas_Wellpro4[[#This Row],[IVA]] -> 25606.745 | J106: =YEAR(Ventas_Wellpro4[[#This Row],[Fecha]]) -> 2025 | K106: =TEXT(Ventas_Wellpro4[[#This Row],[Fecha]],"MMMM") -> octubre | L106: =DAY(Ventas_Wellpro4[[#This Row],[Fecha]]) -> 2
B107: 45324 | C107: Nebulizador Adulto Moderno Tapa Azul | D107: Amazon | E107: 566.83 | F107: 6 | G107: 544.16 | H107: 3400.98 | I107: 3945.14 | J107: =YEAR(Ventas_Wellpro4[[#This Row],[Fecha]]) -> 2024 | K107: =TEXT(Ventas_Wellpro4[[#This Row],[Fecha]],"MMMM") -> febrero | L107: =DAY(Ventas_Wellpro4[[#This Row],[Fecha]]) -> 2
B108: 45398 | C108: Nebulizador Adulto Moderno Tapa Azul | D108: Amazon | E108: 566.83 | F108: 6 | G108: 544.16 | H108: 3400.98 | I108: 3945.14 | J108: =YEAR(Ventas_Wellpro4[[#This Row],[Fecha]]) -> 2024 | K108: =TEXT(Ventas_Wellpro4[[#This Row],[Fecha]],"MMMM") -> abril | L108: =DAY(Ventas_Wellpro4[[#This Row],[Fecha]]) -> 16
B109: 45419 | C109: Nebulizador Adulto Moderno Tapa Azul | D109: Medical Life | E109: 724.07 | F109: 1 | G109: 115.85 | H109: 724.07 | I109: 839.92 | J109: =YEAR(Ventas_Wellpro4[[#This Row],[Fecha]]) -> 2024 | K109: =TEXT(Ventas_Wellpro4[[#This Row],[Fecha]],"MMMM") -> mayo | L109: =DAY(Ventas_Wellpro4[[#This Row],[Fecha]]) -> 7
B110: 45426 | C110: Nebulizador Adulto Moderno Tapa Azul | D110: Medical Life | E110: 724.07 | F110: 1 | G110: 115.85 | H110: 724.07 | I110: 839.92 | J110: =YEAR(Ventas_Wellpro4[[#This Row],[Fecha]]) -> 2024 | K110: =TEXT(Ventas_Wellpro4[[#This Row],[Fecha]],"MMMM") -> mayo | L110: =DAY(Ventas_Wellpro4[[#This Row],[Fecha]]) -> 14
B111: 45499 | C111: Termómetro Pediatrico Cute Animals Panda | D111: Walmart | E111: 70.05 | F111: 240 | G111: 2689.92 | H111: 16812 | I111: 19501.92 | J111: =YEAR(Ventas_Wellpro4[[#This Row],[Fecha]]) -> 2024 | K111: =TEXT(Ventas_Wellpro4[[#This Row],[Fecha]],"MMMM") -> julio | L111: =DAY(Ventas_Wellpro4[[#This Row],[Fecha]]) -> 26
B112: 45499 | C112: Termómetro Pediatrico Cute Animals Panda | D112: Walmart | E112: 70.05 | F112: 240 | G112: 2689.92 | H112: 16812 | I112: 19501.92 | J112: =YEAR(Ventas_Wellpro4[[#This Row],[Fecha]]) -> 2024 | K112: =TEXT(Ventas_Wellpro4[[#This Row],[Fecha]],"MMMM") -> julio | L112: =DAY(Ventas_Wellpro4[[#This Row],[Fecha]]) -> 26
B113: 45449 | C113: Nebulizador Adulto Moderno Tapa Azul | D113: Amazon | E113: 678.84 | F113: 24 | G113: 2606.75 | H113: 16292.16 | I113: 18898.91 | J113: =YEAR(Ventas_Wellpro4[[#This Row],[Fecha]]) -> 2024 | K113: =TEXT(Ventas_Wellpro4[[#This Row],[Fecha]],"MMMM") -> junio | L113: =DAY(Ventas_Wellpro4[[#This Row],[Fecha]]) -> 6
B114: 45520 | C114: Nebulizador Adulto Moderno Tapa Azul | D114: Market Place | E114: 905.16 | F114: 1 | G114: 144.83 | H114: 905.16 | I114: 1049.99 | J114: =YEAR(Ventas_Wellpro4[[#This Row],[Fecha]]) -> 2024 | K114: =TEXT(Ventas_Wellpro4[[#This Row],[Fecha]],"MMMM") -> agosto | L114: =DAY(Ventas_Wellpro4[[#This Row],[Fecha]]) -> 16
B115: 45532 | C115: Nebulizador Adulto Moderno Tapa Azul | D115: Market Place | E115: 905.16 | F115: 1 | G115: 144.83 | H115: 905.16 | I115: 1049.99 | J115: =YEAR(Ventas_Wellpro4[[#This Row],[Fecha]]) -> 2024 | K115: =TEXT(Ventas_Wellpro4[[#This Row],[Fecha]],"MMMM") -> agosto | L115: =DAY(Ventas_Wellpro4[[#This Row],[Fecha]]) -> 28
B116: 45503 | C116: Termómetro Pediatrico Cute Animals Panda | D116: Walmart | E116: 70.05 | F116: 240 | G116: 2689.92 | H116: 16812 | I116: 19501.92 | J116: =YEAR(Ventas_Wellpro4[[#This Row],[Fecha]]) -> 2024 | K116: =TEXT(Ventas_Wellpro4[[#This Row],[Fecha]],"MMMM") -> julio | L116: =DAY(Ventas_Wellpro4[[#This Row],[Fecha]]) -> 30
B117: 45560 | C117: Nebulizador Adulto Moderno Tapa Azul | D117: Market Place | E117: 905.16 | F117: 1 | G117: 144.83 | H117: 905.16 | I117: 1049.99 | J117: =YEAR(Ventas_Wellpro4[[#This Row],[Fecha]]) -> 2024 | K117: =TEXT(Ventas_Wellpro4[[#This Row],[Fecha]],"MMMM") -> septiembre | L117: =DAY(Ventas_Wellpro4[[#This Row],[Fecha]]) -> 25
B118: 45560 | C118: Nebulizador Adulto Moderno Tapa Azul | D118: Market Place | E118: 905.16 | F118: 1 | G118: 144.83 | H118: 905.16 | I118: 1049.99 | J118: =YEAR(Ventas_Wellpro4[[#This Row],[Fecha]]) -> 2024 | K118: =TEXT(Ventas_Wellpro4[[#This Row],[Fecha]],"MMMM") -> septiembre | L118: =DAY(Ventas_Wellpro4[[#This Row],[Fecha]]) -> 25
... B257: 45929 | C257: Nebulizador Adulto Moderno Tapa Azul | D257: Farmacia Sana Sana | E257: 646.55 | F257: 11 | G257: 1137.928 | H257: 7112.05 | I257: 8249.978 | J257: =YEAR(Ventas_Wellpro4[[#This Row],[Fecha]]) -> 2025 | K257: =TEXT(Ventas_Wellpro4[[#This Row],[Fecha]],"MMMM") -> septiembre | L257: =DAY(Ventas_Wellpro4[[#This Row],[Fecha]]) -> 29
B258: 45932 | C258: Nebulizador Pediatrico Elefante Celeste | D258: Walmart | E258: 525.59 | F258: 30 | G258: =+(Ventas_Wellpro4[[#This Row],[Precio de Venta]]*0.16)*Ventas_Wellpro4[[#This Row],[Cantidad Vendida]] -> 2522.832 | H258: 15767.7 | I258: =+Ventas_Wellpro4[[#This Row],[Total de Venta sin IVA]]+Ventas_Wellpro4[[#This Row],[IVA]] -> 18290.532 | J258: =YEAR(Ventas_Wellpro4[[#This Row],[Fecha]]) -> 2025 | K258: =TEXT(Ventas_Wellpro4[[#This Row],[Fecha]],"MMMM") -> octubre | L258: =DAY(Ventas_Wellpro4[[#This Row],[Fecha]]) -> 2
B259: 45932 | C259: Nebulizador Pediatrico Elefante Celeste | D259: Walmart | E259: 525.59 | F259: 30 | G259: =+(Ventas_Wellpro4[[#This Row],[Precio de Venta]]*0.16)*Ventas_Wellpro4[[#This Row],[Cantidad Vendida]] -> 2522.832 | H259: 15767.7 | I259: =+Ventas_Wellpro4[[#This Row],[Total de Venta sin IVA]]+Ventas_Wellpro4[[#This Row],[IVA]] -> 18290.532 | J259: =YEAR(Ventas_Wellpro4[[#This Row],[Fecha]]) -> 2025 | K259: =TEXT(Ventas_Wellpro4[[#This Row],[Fecha]],"MMMM") -> octubre | L259: =DAY(Ventas_Wellpro4[[#This Row],[Fecha]]) -> 2
B260: 45933 | C260: Termómetro Pediatrico Cute Animals Osito | D260: MERCADO LIBRE | E260: 137.79 | F260: 1 | G260: =+(Ventas_Wellpro4[[#This Row],[Precio de Venta]]*0.16)*Ventas_Wellpro4[[#This Row],[Cantidad Vendida]] -> 22.0464 | H260: 137.79 | I260: =+Ventas_Wellpro4[[#This Row],[Total de Venta sin IVA]]+Ventas_Wellpro4[[#This Row],[IVA]] -> 159.8364 | J260: =YEAR(Ventas_Wellpro4[[#This Row],[Fecha]]) -> 2025 | K260: =TEXT(Ventas_Wellpro4[[#This Row],[Fecha]],"MMMM") -> octubre | L260: =DAY(Ventas_Wellpro4[[#This Row],[Fecha]]) -> 3
B261: 45933 | C261: Termómetro Pediatrico Cute Animals Cerdito | D261: MERCADO LIBRE | E261: 137.79 | F261: 1 | G261: =+(Ventas_Wellpro4[[#This Row],[Precio de Venta]]*0.16)*Ventas_Wellpro4[[#This Row],[Cantidad Vendida]] -> 22.0464 | H261: 137.79 | I261: =+Ventas_Wellpro4[[#This Row],[Total de Venta sin IVA]]+Ventas_Wellpro4[[#This Row],[IVA]] -> 159.8364 | J261: =YEAR(Ventas_Wellpro4[[#This Row],[Fecha]]) -> 2025 | K261: =TEXT(Ventas_Wellpro4[[#This Row],[Fecha]],"MMMM") -> octubre | L261: =DAY(Ventas_Wellpro4[[#This Row],[Fecha]]) -> 3
B262: 45558 | C262: Termómetro Pediatrico Cute Animals Panda | D262: Walmart | E262: 70.05 | F262: 240 | G262: 2689.92 | H262: 16812 | I262: 19501.92 | J262: =YEAR(Ventas_Wellpro4[[#This Row],[Fecha]]) -> 2024 | K262: =TEXT(Ventas_Wellpro4[[#This Row],[Fecha]],"MMMM") -> septiembre | L262: =DAY(Ventas_Wellpro4[[#This Row],[Fecha]]) -> 23
B263: 45558 | C263: Termómetro Pediatrico Cute Animals Panda | D263: Walmart | E263: 70.05 | F263: 240 | G263: 2689.92 | H263: 16812 | I263: 19501.92 | J263: =YEAR(Ventas_Wellpro4[[#This Row],[Fecha]]) -> 2024 | K263: =TEXT(Ventas_Wellpro4[[#This Row],[Fecha]],"MMMM") -> septiembre | L263: =DAY(Ventas_Wellpro4[[#This Row],[Fecha]]) -> 23
B264: 45936 | C264: Termómetro Pediatrico Cute Animals Ranita | D264: MERCADO LIBRE | E264: 137.79 | F264: 1 | G264: =+(Ventas_Wellpro4[[#This Row],[Precio de Venta]]*0.16)*Ventas_Wellpro4[[#This Row],[Cantidad Vendida]] -> 22.0464 | H264: 137.79 | I264: =+Ventas_Wellpro4[[#This Row],[Total de Venta sin IVA]]+Ventas_Wellpro4[[#This Row],[IVA]] -> 159.8364 | J264: =YEAR(Ventas_Wellpro4[[#This Row],[Fecha]]) -> 2025 | K264: =TEXT(Ventas_Wellpro4[[#This Row],[Fecha]],"MMMM") -> octubre | L264: =DAY(Ventas_Wellpro4[[#This Row],[Fecha]]) -> 6
B265: 45936 | C265: Báscula Digital de Vidrio Marmol | D265: MERCADO LIBRE | E265: 343.97 | F265: 1 | G265: =+(Ventas_Wellpro4[[#This Row],[Precio de Venta]]*0.16)*Ventas_Wellpro4[[#This Row],[Cantidad Vendida]] -> 55.0352 | H265: 343.97 | I265: =+Ventas_Wellpro4[[#This Row],[Total de Venta sin IVA]]+Ventas_Wellpro4[[#This Row],[IVA]] -> 399.0052 | J265: =YEAR(Ventas_Wellpro4[[#This Row],[Fecha]]) -> 2025 | K265: =TEXT(Ventas_Wellpro4[[#This Row],[Fecha]],"MMMM") -> octubre | L265: =DAY(Ventas_Wellpro4[[#This Row],[Fecha]]) -> 6
B266: 45936 | C266: Báscula Digital de Vidrio Antideslizante | D266: MERCADO LIBRE | E266: 343.97 | F266: 1 | G266: =+(Ventas_Wellpro4[[#This Row],[Precio de Venta]]*0.16)*Ventas_Wellpro4[[#This Row],[Cantidad Vendida]] -> 55.0352 | H266: 343.97 | I266: =+Ventas_Wellpro4[[#This Row],[Total de Venta sin IVA]]+Ventas_Wellpro4[[#This Row],[IVA]] -> 399.0052 | J266: =YEAR(Ventas_Wellpro4[[#This Row],[Fecha]]) -> 2025 | K266: =TEXT(Ventas_Wellpro4[[#This Row],[Fecha]],"MMMM") -> octubre | L266: =DAY(Ventas_Wellpro4[[#This Row],[Fecha]]) -> 6
B267: 45936 | C267: Báscula Digital de Vidrio Antideslizante | D267: MERCADO LIBRE | E267: 343.97 | F267: 1 | G267: =+(Ventas_Wellpro4[[#This Row],[Precio de Venta]]*0.16)*Ventas_Wellpro4[[#This Row],[Cantidad Vendida]] -> 55.0352 | H267: 343.97 | I267: =+Ventas_Wellpro4[[#This Row],[Total de Venta sin IVA]]+Ventas_Wellpro4[[#This Row],[IVA]] -> 399.0052 | J267: =YEAR(Ventas_Wellpro4[[#This Row],[Fecha]]) -> 2025 | K267: =TEXT(Ventas_Wellpro4[[#This Row],[Fecha]],"MMMM") -> octubre | L267: =DAY(Ventas_Wellpro4[[#This Row],[Fecha]]) -> 6
B268: 45560 | C268: Termómetro Pediatrico Cute Animals Osito | D268: Market Place | E268: 131.03 | F268: 1 | G268: 20.96 | H268: 131.03 | I268: 151.99 | J268: =YEAR(Ventas_Wellpro4[[#This Row],[Fecha]]) -> 2024 | K268: =TEXT(Ventas_Wellpro4[[#This Row],[Fecha]],"MMMM") -> septiembre | L268: =DAY(Ventas_Wellpro4[[#This Row],[Fecha]]) -> 25
B269: 45562 | C269: Báscula Digital de Vidrio Antideslizante | D269: Amazon | E269: 211.23 | F269: 6 | G269: 202.78 | H269: 1267.38 | I269: 1470.16 | J269: =YEAR(Ventas_Wellpro4[[#This Row],[Fecha]]) -> 2024 | K269: =TEXT(Ventas_Wellpro4[[#This Row],[Fecha]],"MMMM") -> septiembre | L269: =DAY(Ventas_Wellpro4[[#This Row],[Fecha]]) -> 27
B270: 45562 | C270: Báscula Digital de Vidrio Antideslizante | D270: Amazon | E270: 211.23 | F270: 6 | G270: 202.78 | H270: 1267.38 | I270: 1470.16 | J270: =YEAR(Ventas_Wellpro4[[#This Row],[Fecha]]) -> 2024 | K270: =TEXT(Ventas_Wellpro4[[#This Row],[Fecha]],"MMMM") -> septiembre | L270: =DAY(Ventas_Wellpro4[[#This Row],[Fecha]]) -> 27
B271: 45936 | C271: Termómetro Pediatrico Cute Animals Cerdito | D271: MERCADO LIBRE | E271: 137.79 | F271: 1 | G271: =+(Ventas_Wellpro4[[#This Row],[Precio de Venta]]*0.16)*Ventas_Wellpro4[[#This Row],[Cantidad Vendida]] -> 22.0464 | H271: 137.79 | I271: =+Ventas_Wellpro4[[#This Row],[Total de Venta sin IVA]]+Ventas_Wellpro4[[#This Row],[IVA]] -> 159.8364 | J271: =YEAR(Ventas_Wellpro4[[#This Row],[Fecha]]) -> 2025 | K271: =TEXT(Ventas_Wellpro4[[#This Row],[Fecha]],"MMMM") -> octubre | L271: =DAY(Ventas_Wellpro4[[#This Row],[Fecha]]) -> 6
B272: 45937 | C272: Termómetro Pediatrico Cute Animals Osito | D272: MERCADO LIBRE | E272: 137.79 | F272: 1 | G272: =+(Ventas_Wellpro4[[#This Row],[Precio de Venta]]*0.16)*Ventas_Wellpro4[[#This Row],[Cantidad Vendida]] -> 22.0464 | H272: 137.79 | I272: =+Ventas_Wellpro4[[#This Row],[Total de Venta sin IVA]]+Ventas_Wellpro4[[#This Row],[IVA]] -> 159.8364 | J272: =YEAR(Ventas_Wellpro4[[#This Row],[Fecha]]) -> 2025 | K272: =TEXT(Ventas_Wellpro4[[#This Row],[Fecha]],"MMMM") -> octubre | L272: =DAY(Ventas_Wellpro4[[#This Row],[Fecha]]) -> 7
B273: 45937 | C273: Termómetro Pediatrico Cute Animals Panda | D273: MERCADO LIBRE | E273: 137.79 | F273: 1 | G273: =+(Ventas_Wellpro4[[#This Row],[Precio de Venta]]*0.16)*Ventas_Wellpro4[[#This Row],[Cantidad Vendida]] -> 22.0464 | H273: 137.79 | I273: =Venta!H2229 -> 905.16 | J273: =YEAR(Ventas_Wellpro4[[#This Row],[Fecha]]) -> 2025 | K273: =TEXT(Ventas_Wellpro4[[#This Row],[Fecha]],"MMMM") -> octubre | L273: =DAY(Ventas_Wellpro4[[#This Row],[Fecha]]) -> 7
B274: 45937 | C274: Termómetro Pediatrico Cute Animals Ranita | D274: MERCADO LIBRE | E274: 137.795 | F274: 2 | G274: =+(Ventas_Wellpro4[[#This Row],[Precio de Venta]]*0.16)*Ventas_Wellpro4[[#This Row],[Cantidad Vendida]] -> 44.0944 | H274: 275.59 | I274: =+Ventas_Wellpro4[[#This Row],[Total de Venta sin IVA]]+Ventas_Wellpro4[[#This Row],[IVA]] -> 319.6844 | J274: =YEAR(Ventas_Wellpro4[[#This Row],[Fecha]]) -> 2025 | K274: =TEXT(Ventas_Wellpro4[[#This Row],[Fecha]],"MMMM") -> octubre | L274: =DAY(Ventas_Wellpro4[[#This Row],[Fecha]]) -> 7
B275: 45937 | C275: Termómetro Pediatrico Cute Animals Ranita | D275: MERCADO LIBRE | E275: 137.79 | F275: 1 | G275: =+(Ventas_Wellpro4[[#This Row],[Precio de Venta]]*0.16)*Ventas_Wellpro4[[#This Row],[Cantidad Vendida]] -> 22.0464 | H275: 137.79 | I275: =+Ventas_Wellpro4[[#This Row],[Total de Venta sin IVA]]+Ventas_Wellpro4[[#This Row],[IVA]] -> 159.8364 | J275: =YEAR(Ventas_Wellpro4[[#This Row],[Fecha]]) -> 2025 | K275: =TEXT(Ventas_Wellpro4[[#This Row],[Fecha]],"MMMM") -> octubre | L275: =DAY(Ventas_Wellpro4[[#This Row],[Fecha]]) -> 7
B276: 45937 | C276: Báscula Digital de Vidrio Transparente | D276: Chedraui | E276: 343.97 | F276: 1 | G276: =+(Ventas_Wellpro4[[#This Row],[Precio de Venta]]*0.16)*Ventas_Wellpro4[[#This Row],[Cantidad Vendida]] -> 55.0352 | H276: 343.97 | I276: =+Ventas_Wellpro4[[#This Row],[Total de Venta sin IVA]]+Ventas_Wellpro4[[#This Row],[IVA]] -> 399.0052 | J276: =YEAR(Ventas_Wellpro4[[#This Row],[Fecha]]) -> 2025 | K276: =TEXT(Ventas_Wellpro4[[#This Row],[Fecha]],"MMMM") -> octubre | L276: =DAY(Ventas_Wellpro4[[#This Row],[Fecha]]) -> 7
B277: 45937 | C277: Báscula Digital de Vidrio Marmol | D277: MERCADO LIBRE | E277: 343.97 | F277: 1 | G277: =+(Ventas_Wellpro4[[#This Row],[Precio de Venta]]*0.16)*Ventas_Wellpro4[[#This Row],[Cantidad Vendida]] -> 55.0352 | H277: 343.97 | I277: =+Ventas_Wellpro4[[#This Row],[Total de Venta sin IVA]]+Ventas_Wellpro4[[#This Row],[IVA]] -> 399.0052 | J277: =YEAR(Ventas_Wellpro4[[#This Row],[Fecha]]) -> 2025 | K277: =TEXT(Ventas_Wellpro4[[#This Row],[Fecha]],"MMMM") -> octubre | L277: =DAY(Ventas_Wellpro4[[#This Row],[Fecha]]) -> 7
B278: 45937 | C278: Báscula Digital de Vidrio Marmol | D278: MERCADO LIBRE | E278: 343.97 | F278: 1 | G278: =+(Ventas_Wellpro4[[#This Row],[Precio de Venta]]*0.16)*Ventas_Wellpro4[[#This Row],[Cantidad Vendida]] -> 55.0352 | H278: 343.97 | I278: =+Ventas_Wellpro4[[#This Row],[Total de Venta sin IVA]]+Ventas_Wellpro4[[#This Row],[IVA]] -> 399.0052 | J278: =YEAR(Ventas_Wellpro4[[#This Row],[Fecha]]) -> 2025 | K278: =TEXT(Ventas_Wellpro4[[#This Row],[Fecha]],"MMMM") -> octubre | L278: =DAY(Ventas_Wellpro4[[#This Row],[Fecha]]) -> 7
B279: 45565 | C279: Báscula Digital de Vidrio Antideslizante | D279: Amazon | E279: 211.23 | F279: 12 | G279: 405.56 | H279: 2534.76 | I279: 2940.32 | J279: =YEAR(Ventas_Wellpro4[[#This Row],[Fecha]]) -> 2024 | K279: =TEXT(Ventas_Wellpro4[[#This Row],[Fecha]],"MMMM") -> septiembre | L279: =DAY(Ventas_Wellpro4[[#This Row],[Fecha]]) -> 30
B280: 45565 | C280: Báscula Digital de Vidrio Antideslizante | D280: Amazon | E280: 211.23 | F280: 6 | G280: 202.78 | H280: 1267.38 | I280: 1470.16 | J280: =YEAR(Ventas_Wellpro4[[#This Row],[Fecha]]) -> 2024 | K280: =TEXT(Ventas_Wellpro4[[#This Row],[Fecha]],"MMMM") -> septiembre | L280: =DAY(Ventas_Wellpro4[[#This Row],[Fecha]]) -> 30
B281: 45565 | C281: Cojin Cuadrad Memory Foam | D281: Market Place | E281: 0 | F281: 1 | G281: 0 | H281: 0 | I281: 0 | J281: =YEAR(Ventas_Wellpro4[[#This Row],[Fecha]]) -> 2024 | K281: =TEXT(Ventas_Wellpro4[[#This Row],[Fecha]],"MMMM") -> septiembre | L281: =DAY(Ventas_Wellpro4[[#This Row],[Fecha]]) -> 30
...

Sheet Catalogo Clientes
A1: Clientes | B1: Categoría 2 | C1: Pais
A2: WALMART | B2: AUTOSERVICIO | C2: MEXICO | E2: =UPPER(Catalogo_Clientes[[#This Row],[Clientes]]) -> WALMART
A3: AMAZON | B3: E-COMERCE | C3: MEXICO | E3: =UPPER(Catalogo_Clientes[[#This Row],[Clientes]]) -> AMAZON
A4: MARKET PLACE | B4: E-COMERCE | C4: MEXICO | E4: =UPPER(Catalogo_Clientes[[#This Row],[Clientes]]) -> MARKET PLACE
A5: CHEDRAUI | B5: AUTOSERVICIO | C5: MEXICO | E5: =UPPER(Catalogo_Clientes[[#This Row],[Clientes]]) -> CHEDRAUI
A6: MEDICAL LIFE | B6: FARMACIA | C6: MEXICO | E6: =UPPER(Catalogo_Clientes[[#This Row],[Clientes]]) -> MEDICAL LIFE
A7: NADRO | B7: DISTRIBUIDOR | C7: MEXICO | E7: =UPPER(Catalogo_Clientes[[#This Row],[Clientes]]) -> NADRO
A8: UNEFARM | B8: FARMACIA | C8: MEXICO | E8: =UPPER(Catalogo_Clientes[[#This Row],[Clientes]]) -> UNEFARM
A9: FARMACIA SAN PABLO | B9: FARMACIA | C9: MEXICO | E9: =UPPER(Catalogo_Clientes[[#This Row],[Clientes]]) -> FARMACIA SAN PABLO
A10: FARMACIA SANA SANA | B10: FARMACIA | C10: MEXICO | E10: =UPPER(Catalogo_Clientes[[#This Row],[Clientes]]) -> FARMACIA SANA SANA
A11: FORTUS | B11: INTERNO | C11: MEXICO | E11: =UPPER(Catalogo_Clientes[[#This Row],[Clientes]]) -> FORTUS
A12: BASILICA DE GUADALUPE | B12: AUTOSERVICIO | C12: MEXICO | E12: =UPPER(Catalogo_Clientes[[#This Row],[Clientes]]) -> BASILICA DE GUADALUPE
A13: MERCADO LIBRE | B13: E-COMERCE | C13: MEXICO | E13: =UPPER(Catalogo_Clientes[[#This Row],[Clientes]]) -> MERCADO LIBRE
... A29: FARMACIA BENAVIDES | B29: FARMACIA | C29: MEXICO | E29: =UPPER(Catalogo_Clientes[[#This Row],[Clientes]]) -> FARMACIA BENAVIDES

Sheet TblProductos (2)
A3: Suma de Cantidad Vendida | C3: Años (Fecha) | D3: Trimestres (Fecha) | E3: Meses (Fecha) | F3: Fecha
C4: <30/01/2024 | D4: 2024 | E4: 2024 | F4: 2024 | G4: 2024 | H4: 2024 | I4: 2024 | J4: 2024 | K4: 2024 | L4: 2024 | M4: 2024 | N4: 2024 | O4: 2024 | P4: 2024 | Q4: 2024 | R4: 2024 | S4: 2024 | T4: 2024 | U4: 2024 | V4: 2024 | W4: 2024 | X4: 2024 | Y4: 2024 | Z4: 2024 | AA4: 2024 | AB4: 2024 | AC4: 2024 | AD4: 2024 | AE4: 2024 | AF4: 2024 | AG4: 2024 | AH4: 2024 | AI4: 2024 | AJ4: 2024 | AK4: 2024 | AL4: 2024 | AM4: 2024 | AN4: 2024 | AO4: 2024 | AP4: 2024 | AQ4: 2024 | AR4: 2024 | AS4: 2024 | AT4: 2024 | AU4: 2024 | AV4: 2024 | AW4: 2024 | AX4: 2024 | AY4: 2024 | AZ4: 2024 | BA4: 2024 | BB4: 2024 | BC4: 2024 | BD4: 2024 | BE4: 2024 | BF4: 2024 | BG4: 2024 | BH4: 2024 | BI4: 2024 | BJ4: 2024 | BK4: 2024 | BL4: 2024 | BM4: 2024 | BN4: 2024 | BO4: 2024 | BP4: 2024 | BQ4: 2024 | BR4: 2024 | BS4: 2024 | BT4: 2024 | BU4: 2024 | BV4: 2024 | BW4: 2024 | BX4: 2024 | BY4: 2024 | BZ4: 2024 | CA4: 2024 | CB4: 2024 | CC4: 2024 | CD4: 2024 | CE4: 2024 | CF4: 2024 | CG4: 2024 | CH4: 2024 | CI4: 2025 | CJ4: 2025 | CK4: 2025 | CL4: 2025 | CM4: 2025 | CN4: 2025 | CO4: 2025 | CP4: 2025 | CQ4: 2025 | CR4: 2025 | CS4: 2025 | CT4: 2025 | CU4: 2025 | CV4: 2025 | CW4: 2025 | CX4: 2025 | CY4: 2025 | CZ4: 2025 | DA4: 2025 | DB4: 2025 | DC4: 2025 | DD4: 2025 | DE4: 2025 | DF4: 2025 | DG4: 2025 | DH4: 2025 | DI4: 2025 | DJ4: 2025 | DK4: 2025 | DL4: 2025 | DM4: 2025 | DN4: 2025 | DO4: 2025 | DP4: 2025 | DQ4: 2025 | DR4: 2025 | DS4: 2025 | DT4: 2025 | DU4: 2025 | DV4: 2025 | DW4: 2025 | DX4: 2025 | DY4: 2025 | DZ4: 2025 | EA4: 2025 | EB4: 2025 | EC4: 2025 | ED4: 2025 | EE4: 2025 | EF4: 2025 | EG4: 2025 | EH4: 2025 | EI4: 2025 | EJ4: 2025 | EK4: 2025 | EL4: 2025 | EM4: 2025 | EN4: 2025 | EO4: 2025 | EP4: 2025 | EQ4: 2025 | ER4: 2025 | ES4: 2025 | ET4: 2025 | EU4: 2025 | EV4: 2025 | EW4: 2025 | EX4: 2025 | EY4: 2025 | EZ4: 2025 | FA4: 2025 | FB4: 2025 | FC4: 2025 | FD4: 2025 | FE4: 2025 | FF4: 2025 | FG4: 2025 | FH4: 2025 | FI4: 2025 | FJ4: 2025 | FK4: 2025 | FL4: 2025 | FM4: 2025 | FN4: 2025 | FO4: 2025 | FP4: 2025 | FQ4: 2025 | FR4: 2025 | FS4: 2025 | FT4: 2025 | FU4: 2025 | FV4: 2025 | FW4: 2025 | FX4: 2025 | FY4: 2025 | FZ4: 2025 | GA4: 2025 | GB4: 2025 | GC4: 2025 | GD4: 2025 | GE4: 2025 | GF4: 2025 | GG4: 2025 | GH4: 2025 | GI4: 2025 | GJ4: 2025 | GK4: 2025 | GL4: 2025 | GM4: 2025 | GN4: 2025 | GO4: 2025 | GP4: 2025 | GQ4: 2025 | GR4: 2025 | GS4: 2025 | GT4: 2025 | GU4: 2025 | GV4: 2025 | GW4: 2025 | GX4: 2025 | GY4: 2025 | GZ4: 2025 | HA4: 2025 | HB4: 2025 | HC4: 2025 | HD4: 2025 | HE4: 2025 | HF4: 2025 | HG4: 2025 | HH4: 2025 | HI4: 2025 | HJ4: 2025 | HK4: 2025 | HL4: 2025 | HM4: 2025 | HN4: 2025 | HO4: 2025 | HP4: 2025 | HQ4: 2025 | HR4: 2025 | HS4: 2025 | HT4: 2025 | HU4: 2025 | HV4: 2025 | HW4: 2025 | HX4: 2025 | HY4: 2025 | HZ4: 2025 | IA4: 2025 | IB4: 2025 | IC4: 2025 | ID4: 2025 | IE4: 2025 | IF4: 2025 | IG4: 2025 | IH4: 2025 | II4: 2025 | IJ4: 2025 | IK4: 2025 | IL4: 2025 | IM4: 2025 | IN4: 2025 | IO4: 2025 | IP4: 2025 | IQ4: 2025 | IR4: 2025 | IS4: 2025 | IT4: 2025 | IU4: 2025 | IV4: 2025 | IW4: 2025 | IX4: 2025 | IY4: 2025 | IZ4: 2025 | JA4: 2025 | JB4: 2025 | JC4: 2025 | JD4: 2025 | JE4: 2025 | JF4: 2025 | JG4: 2025 | JH4: 2025 | JI4: 2025 | JJ4: 2025 | JK4: 2025 | JL4: 2025 | JM4: 2025 | JN4: 2025 | JO4: 2025 | JP4: 2025 | JQ4: 2025 | JR4: 2025 | JS4: 2025 | JT4: 2025 | JU4: 2025 | JV4: 2025 | JW4: 2025 | JX4: 2025 | JY4: 2025 | JZ4: 2025 | KA4: 2025 | KB4: 2025 | KC4: 2025 | KD4: 2025 | KE4: 2025 | KF4: 2025 | KG4: 2025 | KH4: 2025 | KI4: 2025 | KJ4: 2025 | KK4: 2025 | KL4: 2025 | KM4: 2025 | KN4: 2025 | KO4: 2025 | KP4: 2025 | KQ4: 2025 | KR4: 2025 | KS4: 2025 | KT4: 2025 | KU4: 2025 | KV4: 2025 | KW4: 2026 | KX4: 2026 | KY4: 2026 | KZ4: 2026 | LA4: 2026 | LB4: 2026 | LC4: 2026 | LD4: 2026 | LE4: 2026 | LF4: 2026 | LG4: 2026 | LH4: 2026 | LI4: 2026 | LJ4: 2026 | LK4: 2026 | LL4: 2026 | LM4: 2026 | LN4: 2026 | LO4: 2026 | LP4: 2026 | LQ4: 2026 | LR4: 2026 | LS4: 2026 | LT4: 2026 | LU4: 2026 | LV4: 2026 | LW4: 2026 | LX4: 2026 | LY4: 2026 | LZ4: 2026 | MA4: 2026 | MB4: 2026 | MC4: 2026 | MD4: 2026 | ME4: 2026 | MF4: 2026 | MG4: 2026 | MH4: 2026 | MI4: 2026 | MJ4: 2026 | MK4: 2026 | ML4: 2026 | MM4: 2026 | MN4: 2026 | MO4: 2026 | MP4: 2026 | MQ4: 2026 | MR4: 2026 | MS4: 2026 | MT4: 2026 | MU4: 2026 | MV4: 2026 | MW4: 2026 | MX4: 2026 | MY4: 2026 | MZ4: 2026 | NA4: 2026 | NB4: 2026 | NC4: 2026 | ND4: 2026 | NE4: 2026 | NF4: 2026 | NG4: 2026 | NH4: 2026 | NI4: 2026 | NJ4: 2026 | NK4: 2026 | NL4: 2026 | NM4: 2026 | NN4: 2026 | NO4: 2026 | NP4: 2026 | NQ4: 2026 | NR4: 2026 | NS4: 2026 | NT4: 2026 | NU4: 2026 | NV4: 2026 | NW4: 2026 | NX4: 2026 | NY4: 2026 | NZ4: 2026 | OA4: 2026 | OB4: 2026 | OC4: 2026 | OD4: 2026 | OE4: 2026 | OF4: 2026 | OG4: 2026 | OH4: 2026 | OI4: 2026 | OJ4: 2026 | OK4: 2026 | OL4: 2026 | OM4: 2026 | ON4: 2026 | OO4: 2026 | OP4: 2026 | OQ4: 2026 | OR4: 2026 | OS4: 2026 | OT4: 2026 | OU4: 2026 | OV4: 2026 | OW4: 2026 | OX4: 2026 | OY4: 2026 | OZ4: 2026 | PA4: 2026 | PB4: 2026 | PC4: 2026 | PD4: 2026 | PE4: 2026 | PF4: 2026 | PG4: 2026 | PH4: 2026 | PI4: 2026 | PJ4: 2026 | PK4: 2026 | PL4: 2026 | PM4: 2026 | PN4: 2026 | PO4: 2026 | PP4: 2026 | PQ4: 2026 | PR4: 2026 | PS4: 2026 | PT4: 2026 | PU4: 2026 | PV4: 2026 | PW4: 2026 | PX4: 2026 | PY4: 2026 | PZ4: 2026 | QA4: 2026 | QB4: 2026 | QC4: 2026 | QD4: 2026 | QE4: 2026 | QF4: 2026 | QG4: 2026 | QH4: 2026 | QI4: 2026 | QJ4: 2026 | QK4: 2026 | QL4: 2026 | QM4: 2026 | QN4: 2026 | QO4: 2026 | QP4: 2026 | QQ4: 2026 | QR4: 2026 | QS4: 2026 | QT4: 2026 | QU4: 2026 | QV4: 2026 | QW4: 2026 | QX4: 2026 | QY4: 2026 | QZ4: 2026 | RA4: 2026
C5: <30/01/2024 | D5: Trim.1 | E5: Trim.1 | F5: Trim.1 | G5: Trim.1 | H5: Trim.2 | I5: Trim.2 | J5: Trim.2 | K5: Trim.2 | L5: Trim.2 | M5: Trim.2 | N5: Trim.3 | O5: Trim.3 | P5: Trim.3 | Q5: Trim.3 | R5: Trim.3 | S5: Trim.3 | T5: Trim.3 | U5: Trim.3 | V5: Trim.3 | W5: Trim.3 | X5: Trim.3 | Y5: Trim.3 | Z5: Trim.3 | AA5: Trim.3 | AB5: Trim.3 | AC5: Trim.3 | AD5: Trim.3 | AE5: Trim.3 | AF5: Trim.3 | AG5: Trim.3 | AH5: Trim.3 | AI5: Trim.3 | AJ5: Trim.3 | AK5: Trim.3 | AL5: Trim.3 | AM5: Trim.3 | AN5: Trim.3 | AO5: Trim.3 | AP5: Trim.3 | AQ5: Trim.3 | AR5: Trim.4 | AS5: Trim.4 | AT5: Trim.4 | AU5: Trim.4 | AV5: Trim.4 | AW5: Trim.4 | AX5: Trim.4 | AY5: Trim.4 | AZ5: Trim.4 | BA5: Trim.4 | BB5: Trim.4 | BC5: Trim.4 | BD5: Trim.4 | BE5: Trim.4 | BF5: Trim.4 | BG5: Trim.4 | BH5: Trim.4 | BI5: Trim.4 | BJ5: Trim.4 | BK5: Trim.4 | BL5: Trim.4 | BM5: Trim.4 | BN5: Trim.4 | BO5: Trim.4 | BP5: Trim.4 | BQ5: Trim.4 | BR5: Trim.4 | BS5: Trim.4 | BT5: Trim.4 | BU5: Trim.4 | BV5: Trim.4 | BW5: Trim.4 | BX5: Trim.4 | BY5: Trim.4 | BZ5: Trim.4 | CA5: Trim.4 | CB5: Trim.4 | CC5: Trim.4 | CD5: Trim.4 | CE5: Trim.4 | CF5: Trim.4 | CG5: Trim.4 | CH5: Trim.4 | CI5: Trim.1 | CJ5: Trim.1 | CK5: Trim.1 | CL5: Trim.1 | CM5: Trim.1 | CN5: Trim.1 | CO5: Trim.1 | CP5: Trim.1 | CQ5: Trim.1 | CR5: Trim.1 | CS5: Trim.1 | CT5: Trim.1 | CU5: Trim.1 | CV5: Trim.1 | CW5: Trim.1 | CX5: Trim.1 | CY5: Trim.1 | CZ5: Trim.1 | DA5: Trim.1 | DB5: Trim.1 | DC5: Trim.1 | DD5: Trim.1 | DE5: Trim.1 | DF5: Trim.1 | DG5: Trim.1 | DH5: Trim.1 | DI5: Trim.1 | DJ5: Trim.1 | DK5: Trim.1 | DL5: Trim.1 | DM5: Trim.1 | DN5: Trim.1 | DO5: Trim.1 | DP5: Trim.1 | DQ5: Trim.1 | DR5: Trim.1 | DS5: Trim.1 | DT5: Trim.1 | DU5: Trim.1 | DV5: Trim.1 | DW5: Trim.1 | DX5: Trim.1 | DY5: Trim.1 | DZ5: Trim.1 | EA5: Trim.1 | EB5: Trim.1 | EC5: Trim.1 | ED5: Trim.1 | EE5: Trim.1 | EF5: Trim.1 | EG5: Trim.1 | EH5: Trim.1 | EI5: Trim.1 | EJ5: Trim.2 | EK5: Trim.2 | EL5: Trim.2 | EM5: Trim.2 | EN5: Trim.2 | EO5: Trim.2 | EP5: Trim.2 | EQ5: Trim.2 | ER5: Trim.2 | ES5: Trim.2 | ET5: Trim.2 | EU5: Trim.2 | EV5: Trim.2 | EW5: Trim.2 | EX5: Trim.2 | EY5: Trim.2 | EZ5: Trim.2 | FA5: Trim.2 | FB5: Trim.2 | FC5: Trim.2 | FD5: Trim.2 | FE5: Trim.2 | FF5: Trim.2 | FG5: Trim.2 | FH5: Trim.2 | FI5: Trim.2 | FJ5: Trim.2 | FK5: Trim.2 | FL5: Trim.2 | FM5: Trim.2 | FN5: Trim.2 | FO5: Trim.2 | FP5: Trim.2 | FQ5: Trim.2 | FR5: Trim.2 | FS5: Trim.2 | FT5: Trim.2 | FU5: Trim.2 | FV5: Trim.2 | FW5: Trim.2 | FX5: Trim.2 | FY5: Trim.2 | FZ5: Trim.2 | GA5: Trim.2 | GB5: Trim.2 | GC5: Trim.2 | GD5: Trim.2 | GE5: Trim.2 | GF5: Trim.2 | GG5: Trim.2 | GH5: Trim.3 | GI5: Trim.3 | GJ5: Trim.3 | GK5: Trim.3 | GL5: Trim.3 | GM5: Trim.3 | GN5: Trim.3 | GO5: Trim.3 | GP5: Trim.3 | GQ5: Trim.3 | GR5: Trim.3 | GS5: Trim.3 | GT5: Trim.3 | GU5: Trim.3 | GV5: Trim.3 | GW5: Trim.3 | GX5: Trim.3 | GY5: Trim.3 | GZ5: Trim.3 | HA5: Trim.3 | HB5: Trim.3 | HC5: Trim.3 | HD5: Trim.3 | HE5: Trim.3 | HF5: Trim.3 | HG5: Trim.3 | HH5: Trim.3 | HI5: Trim.3 | HJ5: Trim.3 | HK5: Trim.3 | HL5: Trim.3 | HM5: Trim.3 | HN5: Trim.3 | HO5: Trim.3 | HP5: Trim.3 | HQ5: Trim.3 | HR5: Trim.3 | HS5: Trim.3 | HT5: Trim.3 | HU5: Trim.3 | HV5: Trim.3 | HW5: Trim.3 | HX5: Trim.3 | HY5: Trim.3 | HZ5: Trim.3 | IA5: Trim.3 | IB5: Trim.3 | IC5: Trim.3 | ID5: Trim.3 | IE5: Trim.3 | IF5: Trim.3 | IG5: Trim.3 | IH5: Trim.3 | II5: Trim.3 | IJ5: Trim.3 | IK5: Trim.3 | IL5: Trim.3 | IM5: Trim.3 | IN5: Trim.4 | IO5: Trim.4 | IP5: Trim.4 | IQ5: Trim.4 | IR5: Trim.4 | IS5: Trim.4 | IT5: Trim.4 | IU5: Trim.4 | IV5: Trim.4 | IW5: Trim.4 | IX5: Trim.4 | IY5: Trim.4 | IZ5: Trim.4 | JA5: Trim.4 | JB5: Trim.4 | JC5: Trim.4 | JD5: Trim.4 | JE5: Trim.4 | JF5: Trim.4 | JG5: Trim.4 | JH5: Trim.4 | JI5: Trim.4 | JJ5: Trim.4 | JK5: Trim.4 | JL5: Trim.4 | JM5: Trim.4 | JN5: Trim.4 | JO5: Trim.4 | JP5: Trim.4 | JQ5: Trim.4 | JR5: Trim.4 | JS5: Trim.4 | JT5: Trim.4 | JU5: Trim.4 | JV5: Trim.4 | JW5: Trim.4 | JX5: Trim.4 | JY5: Trim.4 | JZ5: Trim.4 | KA5: Trim.4 | KB5: Trim.4 | KC5: Trim.4 | KD5: Trim.4 | KE5: Trim.4 | KF5: Trim.4 | KG5: Trim.4 | KH5: Trim.4 | KI5: Trim.4 | KJ5: Trim.4 | KK5: Trim.4 | KL5: Trim.4 | KM5: Trim.4 | KN5: Trim.4 | KO5: Trim.4 | KP5: Trim.4 | KQ5: Trim.4 | KR5: Trim.4 | KS5: Trim.4 | KT5: Trim.4 | KU5: Trim.4 | KV5: Trim.4 | KW5: Trim.1 | KX5: Trim.1 | KY5: Trim.1 | KZ5: Trim.1 | LA5: Trim.1 | LB5: Trim.1 | LC5: Trim.1 | LD5: Trim.1 | LE5: Trim.1 | LF5: Trim.1 | LG5: Trim.1 | LH5: Trim.1 | LI5: Trim.1 | LJ5: Trim.1 | LK5: Trim.1 | LL5: Trim.1 | LM5: Trim.1 | LN5: Trim.1 | LO5: Trim.1 | LP5: Trim.1 | LQ5: Trim.1 | LR5: Trim.1 | LS5: Trim.1 | LT5: Trim.1 | LU5: Trim.1 | LV5: Trim.1 | LW5: Trim.1 | LX5: Trim.1 | LY5: Trim.1 | LZ5: Trim.1 | MA5: Trim.1 | MB5: Trim.1 | MC5: Trim.1 | MD5: Trim.1 | ME5: Trim.1 | MF5: Trim.1 | MG5: Trim.1 | MH5: Trim.1 | MI5: Trim.1 | MJ5: Trim.1 | MK5: Trim.1 | ML5: Trim.1 | MM5: Trim.1 | MN5: Trim.1 | MO5: Trim.1 | MP5: Trim.1 | MQ5: Trim.1 | MR5: Trim.1 | MS5: Trim.1 | MT5: Trim.1 | MU5: Trim.1 | MV5: Trim.1 | MW5: Trim.1 | MX5: Trim.1 | MY5: Trim.1 | MZ5: Trim.1 | NA5: Trim.1 | NB5: Trim.1 | NC5: Trim.1 | ND5: Trim.2 | NE5: Trim.2 | NF5: Trim.2 | NG5: Trim.2 | NH5: Trim.2 | NI5: Trim.2 | NJ5: Trim.2 | NK5: Trim.2 | NL5: Trim.2 | NM5: Trim.2 | NN5: Trim.2 | NO5: Trim.2 | NP5: Trim.2 | NQ5: Trim.2 | NR5: Trim.2 | NS5: Trim.2 | NT5: Trim.2 | NU5: Trim.2 | NV5: Trim.2 | NW5: Trim.2 | NX5: Trim.2 | NY5: Trim.2 | NZ5: Trim.2 | OA5: Trim.2 | OB5: Trim.2 | OC5: Trim.2 | OD5: Trim.2 | OE5: Trim.2 | OF5: Trim.2 | OG5: Trim.2 | OH5: Trim.2 | OI5: Trim.2 | OJ5: Trim.2 | OK5: Trim.2 | OL5: Trim.2 | OM5: Trim.2 | ON5: Trim.2 | OO5: Trim.2 | OP5: Trim.2 | OQ5: Trim.2 | OR5: Trim.2 | OS5: Trim.2 | OT5: Trim.2 | OU5: Trim.2 | OV5: Trim.2 | OW5: Trim.2 | OX5: Trim.2 | OY5: Trim.2 | OZ5: Trim.2 | PA5: Trim.2 | PB5: Trim.2 | PC5: Trim.2 | PD5: Trim.2 | PE5: Trim.2 | PF5: Trim.2 | PG5: Trim.2 | PH5: Trim.2 | PI5: Trim.2 | PJ5: Trim.2 | PK5: Trim.3 | PL5: Trim.3 | PM5: Trim.3 | PN5: Trim.3 | PO5: Trim.3 | PP5: Trim.3 | PQ5: Trim.3 | PR5: Trim.3 | PS5: Trim.3 | PT5: Trim.3 | PU5: Trim.3 | PV5: Trim.3 | PW5: Trim.3 | PX5: Trim.3 | PY5: Trim.3 | PZ5: Trim.3 | QA5: Trim.3 | QB5: Trim.3 | QC5: Trim.3 | QD5: Trim.3 | QE5: Trim.3 | QF5: Trim.3 | QG5: Trim.3 | QH5: Trim.3 | QI5: Trim.3 | QJ5: Trim.3 | QK5: Trim.3 | QL5: Trim.3 | QM5: Trim.3 | QN5: Trim.3 | QO5: Trim.3 | QP5: Trim.3 | QQ5: Trim.3 | QR5: Trim.3 | QS5: Trim.3 | QT5: Trim.3 | QU5: Trim.3 | QV5: Trim.3 | QW5: Trim.3 | QX5: Trim.3 | QY5: Trim.3 | QZ5: Trim.3 | RA5: Trim.3
C6: <30/01/2024 | D6: ene | E6: feb | F6: feb | G6: feb | H6: abr | I6: may | J6: may | K6: may | L6: jun | M6: jun | N6: jul | O6: jul | P6: jul | Q6: jul | R6: jul | S6: jul | T6: jul | U6: jul | V6: jul | W6: jul | X6: ago | Y6: ago | Z6: ago | AA6: ago | AB6: ago | AC6: ago | AD6: ago | AE6: ago | AF6: ago | AG6: sept | AH6: sept | AI6: sept | AJ6: sept | AK6: sept | AL6: sept | AM6: sept | AN6: sept | AO6: sept | AP6: sept | AQ6: sept | AR6: oct | AS6: oct | AT6: oct | AU6: oct | AV6: oct | AW6: oct | AX6: oct | AY6: oct | AZ6: oct | BA6: oct | BB6: oct | BC6: oct | BD6: oct | BE6: oct | BF6: oct | BG6: nov | BH6: nov | BI6: nov | BJ6: nov | BK6: nov | BL6: nov | BM6: nov | BN6: nov | BO6: nov | BP6: nov | BQ6: nov | BR6: nov | BS6: nov | BT6: nov | BU6: dic | BV6: dic | BW6: dic | BX6: dic | BY6: dic | BZ6: dic | CA6: dic | CB6: dic | CC6: dic | CD6: dic | CE6: dic | CF6: dic | CG6: dic | CH6: dic | CI6: ene | CJ6: ene | CK6: ene | CL6: ene | CM6: ene | CN6: ene | CO6: ene | CP6: ene | CQ6: ene | CR6: ene | CS6: ene | CT6: ene | CU6: ene | CV6: ene | CW6: ene | CX6: ene | CY6: ene | CZ6: feb | DA6: feb | DB6: feb | DC6: feb | DD6: feb | DE6: feb | DF6: feb | DG6: feb | DH6: feb | DI6: feb | DJ6: feb | DK6: feb | DL6: feb | DM6: feb | DN6: feb | DO6: feb | DP6: feb | DQ6: feb | DR6: mar | DS6: mar | DT6: mar | DU6: mar | DV6: mar | DW6: mar | DX6: mar | DY6: mar | DZ6: mar | EA6: mar | EB6: mar | EC6: mar | ED6: mar | EE6: mar | EF6: mar | EG6: mar | EH6: mar | EI6: mar | EJ6: abr | EK6: abr | EL6: abr | EM6: abr | EN6: abr | EO6: abr | EP6: abr | EQ6: abr | ER6: abr | ES6: abr | ET6: abr | EU6: abr | EV6: abr | EW6: abr | EX6: may | EY6: may | EZ6: may | FA6: may | FB6: may | FC6: may | FD6: may | FE6: may | FF6: may | FG6: may | FH6: may | FI6: may | FJ6: may | FK6: may | FL6: may | FM6: may | FN6: may | FO6: jun | FP6: jun | FQ6: jun | FR6: jun | FS6: jun | FT6: jun | FU6: jun | FV6: jun | FW6: jun | FX6: jun | FY6: jun | FZ6: jun | GA6: jun | GB6: jun | GC6: jun | GD6: jun | GE6: jun | GF6: jun | GG6: jun | GH6: jul | GI6: jul | GJ6: jul | GK6: jul | GL6: jul | GM6: jul | GN6: jul | GO6: jul | GP6: jul | GQ6: jul | GR6: jul | GS6: jul | GT6: jul | GU6: jul | GV6: jul | GW6: jul | GX6: jul | GY6: jul | GZ6: jul | HA6: jul | HB6: ago | HC6: ago | HD6: ago | HE6: ago | HF6: ago | HG6: ago | HH6: ago | HI6: ago | HJ6: ago | HK6: ago | HL6: ago | HM6: ago | HN6: ago | HO6: ago | HP6: ago | HQ6: ago | HR6: ago | HS6: ago | HT6: ago | HU6: sept | HV6: sept | HW6: sept | HX6: sept | HY6: sept | HZ6: sept | IA6: sept | IB6: sept | IC6: sept | ID6: sept | IE6: sept | IF6: sept | IG6: sept | IH6: sept | II6: sept | IJ6: sept | IK6: sept | IL6: sept | IM6: sept | IN6: oct | IO6: oct | IP6: oct | IQ6: oct | IR6: oct | IS6: oct | IT6: oct | IU6: oct | IV6: oct | IW6: oct | IX6: oct | IY6: oct | IZ6: oct | JA6: oct | JB6: oct | JC6: oct | JD6: oct | JE6: oct | JF6: oct | JG6: oct | JH6: nov | JI6: nov | JJ6: nov | JK6: nov | JL6: nov | JM6: nov | JN6: nov | JO6: nov | JP6: nov | JQ6: nov | JR6: nov | JS6: nov | JT6: nov | JU6: nov | JV6: nov | JW6: nov | JX6: nov | JY6: nov | JZ6: nov | KA6: nov | KB6: dic | KC6: dic | KD6: dic | KE6: dic | KF6: dic | KG6: dic | KH6: dic | KI6: dic | KJ6: dic | KK6: dic | KL6: dic | KM6: dic | KN6: dic | KO6: dic | KP6: dic | KQ6: dic | KR6: dic | KS6: dic | KT6: dic | KU6: dic | KV6: dic | KW6: ene | KX6: ene | KY6: ene | KZ6: ene | LA6: ene | LB6: ene | LC6: ene | LD6: ene | LE6: ene | LF6: ene | LG6: ene | LH6: ene | LI6: ene | LJ6: ene | LK6: ene | LL6: ene | LM6: ene | LN6: ene | LO6: ene | LP6: ene | LQ6: feb | LR6: feb | LS6: feb | LT6: feb | LU6: feb | LV6: feb | LW6: feb | LX6: feb | LY6: feb | LZ6: feb | MA6: feb | MB6: feb | MC6: feb | MD6: feb | ME6: feb | MF6: feb | MG6: feb | MH6: feb | MI6: feb | MJ6: mar | MK6: mar | ML6: mar | MM6: mar | MN6: mar | MO6: mar | MP6: mar | MQ6: mar | MR6: mar | MS6: mar | MT6: mar | MU6: mar | MV6: mar | MW6: mar | MX6: mar | MY6: mar | MZ6: mar | NA6: mar | NB6: mar | NC6: mar | ND6: abr | NE6: abr | NF6: abr | NG6: abr | NH6: abr | NI6: abr | NJ6: abr | NK6: abr | NL6: abr | NM6: abr | NN6: abr | NO6: abr | NP6: abr | NQ6: abr | NR6: abr | NS6: abr | NT6: abr | NU6: abr | NV6: abr | NW6: abr | NX6: may | NY6: may | NZ6: may | OA6: may | OB6: may | OC6: may | OD6: may | OE6: may | OF6: may | OG6: may | OH6: may | OI6: may | OJ6: may | OK6: may | OL6: may | OM6: may | ON6: may | OO6: may | OP6: may | OQ6: jun | OR6: jun | OS6: jun | OT6: jun | OU6: jun | OV6: jun | OW6: jun | OX6: jun | OY6: jun | OZ6: jun | PA6: jun | PB6: jun | PC6: jun | PD6: jun | PE6: jun | PF6: jun | PG6: jun | PH6: jun | PI6: jun | PJ6: jun | PK6: jul | PL6: jul | PM6: jul | PN6: jul | PO6: jul | PP6: jul | PQ6: jul | PR6: jul | PS6: jul | PT6: jul | PU6: jul | PV6: jul | PW6: jul | PX6: jul | PY6: jul | PZ6: jul | QA6: jul | QB6: jul | QC6: jul | QD6: jul | QE6: jul | QF6: jul | QG6: ago | QH6: ago | QI6: ago | QJ6: ago | QK6: ago | QL6: ago | QM6: ago | QN6: ago | QO6: ago | QP6: ago | QQ6: ago | QR6: ago | QS6: ago | QT6: ago | QU6: ago | QV6: ago | QW6: ago | QX6: ago | QY6: ago | QZ6: ago | RA6: ago
A7: Cliente | B7: Producto | C7: (en blanco) | D7: 45321 | E7: 45324 | F7: 45329 | G7: 45335 | H7: 45398 | I7: 45418 | J7: 45419 | K7: 45426 | L7: 45449 | M7: 45460 | N7: 45475 | O7: 45478 | P7: 45482 | Q7: 45484 | R7: 45488 | S7: 45490 | T7: 45492 | U7: 45499 | V7: 45503 | W7: 45504 | X7: 45505 | Y7: 45511 | Z7: 45512 | AA7: 45516 | AB7: 45517 | AC7: 45520 | AD7: 45527 | AE7: 45530 | AF7: 45532 | AG7: 45537 | AH7: 45538 | AI7: 45541 | AJ7: 45546 | AK7: 45547 | AL7: 45548 | AM7: 45552 | AN7: 45558 | AO7: 45560 | AP7: 45562 | AQ7: 45565 | AR7: 45568 | AS7: 45573 | AT7: 45574 | AU7: 45575 | AV7: 45579 | AW7: 45580 | AX7: 45581 | AY7: 45582 | AZ7: 45586 | BA7: 45587 | BB7: 45590 | BC7: 45593 | BD7: 45594 | BE7: 45595 | BF7: 45596 | BG7: 45600 | BH7: 45601 | BI7: 45603 | BJ7: 45604 | BK7: 45607 | BL7: 45608 | BM7: 45610 | BN7: 45611 | BO7: 45615 | BP7: 45616 | BQ7: 45617 | BR7: 45621 | BS7: 45622 | BT7: 45624 | BU7: 45628 | BV7: 45629 | BW7: 45630 | BX7: 45631 | BY7: 45635 | BZ7: 45636 | CA7: 45637 | CB7: 45638 | CC7: 45639 | CD7: 45643 | CE7: 45645 | CF7: 45652 | CG7: 45656 | CH7: 45657 | CI7: 45659 | CJ7: 45660 | CK7: 45663 | CL7: 45664 | CM7: 45665 | CN7: 45666 | CO7: 45670 | CP7: 45671 | CQ7: 45672 | CR7: 45673 | CS7: 45674 | CT7: 45677 | CU7: 45679 | CV7: 45684 | CW7: 45685 | CX7: 45686 | CY7: 45687 | CZ7: 45692 | DA7: 45693 | DB7: 45694 | DC7: 45695 | DD7: 45698 | DE7: 45699 | DF7: 45700 | DG7: 45701 | DH7: 45702 | DI7: 45705 | DJ7: 45706 | DK7: 45707 | DL7: 45708 | DM7: 45712 | DN7: 45713 | DO7: 45714 | DP7: 45715 | DQ7: 45716 | DR7: 45719 | DS7: 45720 | DT7: 45721 | DU7: 45722 | DV7: 45726 | DW7: 45727 | DX7: 45728 | DY7: 45729 | DZ7: 45730 | EA7: 45734 | EB7: 45735 | EC7: 45736 | ED7: 45737 | EE7: 45740 | EF7: 45741 | EG7: 45742 | EH7: 45743 | EI7: 45747 | EJ7: 45749 | EK7: 45750 | EL7: 45755 | EM7: 45757 | EN7: 45758 | EO7: 45762 | EP7: 45763 | EQ7: 45768 | ER7: 45769 | ES7: 45770 | ET7: 45771 | EU7: 45775 | EV7: 45776 | EW7: 45777 | EX7: 45782 | EY7: 45785 | EZ7: 45789 | FA7: 45790 | FB7: 45792 | FC7: 45793 | FD7: 45796 | FE7: 45797 | FF7: 45798 | FG7: 45799 | FH7: 45800 | FI7: 45803 | FJ7: 45804 | FK7: 45805 | FL7: 45806 | FM7: 45807 | FN7: 45808 | FO7: 45810 | FP7: 45811 | FQ7: 45812 | FR7: 45813 | FS7: 45814 | FT7: 45817 | FU7: 45818 | FV7: 45819 | FW7: 45820 | FX7: 45821 | FY7: 45824 | FZ7: 45825 | GA7: 45826 | GB7: 45827 | GC7: 45828 | GD7: 45831 | GE7: 45834 | GF7: 45835 | GG7: 45838 | GH7: 45839 | GI7: 45840 | GJ7: 45841 | GK7: 45845 | GL7: 45846 | GM7: 45847 | GN7: 45848 | GO7: 45852 | GP7: 45853 | GQ7: 45854 | GR7: 45856 | GS7: 45859 | GT7: 45860 | GU7: 45861 | GV7: 45862 | GW7: 45863 | GX7: 45866 | GY7: 45867 | GZ7: 45868 | HA7: 45869 | HB7: 45873 | HC7: 45874 | HD7: 45875 | HE7: 45876 | HF7: 45877 | HG7: 45880 | HH7: 45881 | HI7: 45882 | HJ7: 45883 | HK7: 45884 | HL7: 45887 | HM7: 45888 | HN7: 45889 | HO7: 45890 | HP7: 45891 | HQ7: 45894 | HR7: 45896 | HS7: 45897 | HT7: 45898 | HU7: 45901 | HV7: 45902 | HW7: 45903 | HX7: 45904 | HY7: 45905 | HZ7: 45908 | IA7: 45910 | IB7: 45911 | IC7: 45912 | ID7: 45915 | IE7: 45917 | IF7: 45918 | IG7: 45919 | IH7: 45922 | II7: 45923 | IJ7: 45924 | IK7: 45925 | IL7: 45929 | IM7: 45930 | IN7: 45931 | IO7: 45932 | IP7: 45933 | IQ7: 45936 | IR7: 45937 | IS7: 45938 | IT7: 45939 | IU7: 45940 | IV7: 45943 | IW7: 45944 | IX7: 45945 | IY7: 45946 | IZ7: 45947 | JA7: 45951 | JB7: 45952 | JC7: 45953 | JD7: 45957 | JE7: 45958 | JF7: 45959 | JG7: 45960 | JH7: 45964 | JI7: 45965 | JJ7: 45966 | JK7: 45967 | JL7: 45968 | JM7: 45971 | JN7: 45972 | JO7: 45973 | JP7: 45974 | JQ7: 45975 | JR7: 45978 | JS7: 45979 | JT7: 45980 | JU7: 45981 | JV7: 45982 | JW7: 45985 | JX7: 45986 | JY7: 45987 | JZ7: 45988 | KA7: 45989 | KB7: 45992 | KC7: 45993 | KD7: 45994 | KE7: 45995 | KF7: 45996 | KG7: 45999 | KH7: 46001 | KI7: 46002 | KJ7: 46003 | KK7: 46006 | KL7: 46007 | KM7: 46008 | KN7: 46009 | KO7: 46010 | KP7: 46013 | KQ7: 46014 | KR7: 46015 | KS7: 46017 | KT7: 46020 | KU7: 46021 | KV7: 46022 | KW7: 46024 | KX7: 46027 | KY7: 46028 | KZ7: 46029 | LA7: 46030 | LB7: 46031 | LC7: 46034 | LD7: 46035 | LE7: 46036 | LF7: 46037 | LG7: 46038 | LH7: 46041 | LI7: 46043 | LJ7: 46044 | LK7: 46045 | LL7: 46048 | LM7: 46049 | LN7: 46050 | LO7: 46051 | LP7: 46052 | LQ7: 46056 | LR7: 46057 | LS7: 46058 | LT7: 46059 | LU7: 46062 | LV7: 46063 | LW7: 46064 | LX7: 46065 | LY7: 46066 | LZ7: 46069 | MA7: 46070 | MB7: 46071 | MC7: 46072 | MD7: 46073 | ME7: 46076 | MF7: 46077 | MG7: 46078 | MH7: 46079 | MI7: 46080 | MJ7: 46083 | MK7: 46084 | ML7: 46085 | MM7: 46086 | MN7: 46087 | MO7: 46090 | MP7: 46091 | MQ7: 46092 | MR7: 46093 | MS7: 46094 | MT7: 46098 | MU7: 46099 | MV7: 46100 | MW7: 46101 | MX7: 46104 | MY7: 46105 | MZ7: 46106 | NA7: 46108 | NB7: 46111 | NC7: 46112 | ND7: 46113 | NE7: 46118 | NF7: 46119 | NG7: 46120 | NH7: 46121 | NI7: 46122 | NJ7: 46125 | NK7: 46126 | NL7: 46127 | NM7: 46128 | NN7: 46129 | NO7: 46132 | NP7: 46133 | NQ7: 46134 | NR7: 46135 | NS7: 46136 | NT7: 46139 | NU7: 46140 | NV7: 46141 | NW7: 46142 | NX7: 46146 | NY7: 46147 | NZ7: 46148 | OA7: 46149 | OB7: 46150 | OC7: 46153 | OD7: 46155 | OE7: 46156 | OF7: 46157 | OG7: 46160 | OH7: 46161 | OI7: 46162 | OJ7: 46163 | OK7: 46164 | OL7: 46167 | OM7: 46168 | ON7: 46169 | OO7: 46170 | OP7: 46171 | OQ7: 46174 | OR7: 46175 | OS7: 46176 | OT7: 46177 | OU7: 46178 | OV7: 46181 | OW7: 46182 | OX7: 46183 | OY7: 46184 | OZ7: 46188 | PA7: 46189 | PB7: 46190 | PC7: 46192 | PD7: 46195 | PE7: 46196 | PF7: 46197 | PG7: 46198 | PH7: 46199 | PI7: 46202 | PJ7: 46203 | PK7: 46204 | PL7: 46205 | PM7: 46206 | PN7: 46209 | PO7: 46210 | PP7: 46211 | PQ7: 46212 | PR7: 46213 | PS7: 46216 | PT7: 46217 | PU7: 46218 | PV7: 46219 | PW7: 46220 | PX7: 46223 | PY7: 46224 | PZ7: 46225 | QA7: 46227 | QB7: 46230 | QC7: 46231 | QD7: 46232 | QE7: 46233 | QF7: 46234 | QG7: 46237 | QH7: 46238 | QI7: 46239 | QJ7: 46240 | QK7: 46241 | QL7: 46244 | QM7: 46245 | QN7: 46246 | QO7: 46247 | QP7: 46248 | QQ7: 46251 | QR7: 46252 | QS7: 46253 | QT7: 46254 | QU7: 46255 | QV7: 46258 | QW7: 46259 | QX7: 46260 | QY7: 46261 | QZ7: 46262 | RA7: 46265
A8: AMAZON | B8: Báscula Digital de Vidrio Antideslizante | G8: 12 | AF8: 12 | AJ8: 6 | AP8: 12 | AQ8: 18 | BK8: 12 | BV8: 18 | CL8: 6 | DI8: 6 | DZ8: 6 | FR8: 6 | FY8: 6 | GA8: 6 | GF8: 18 | GK8: 6 | GM8: 6 | GU8: 6 | HB8: 6 | HQ8: 6 | HZ8: 6 | IS8: 6 | JB8: 6 | KK8: 6 | KY8: 6 | KZ8: 6 | LC8: 6 | LL8: 6 | LQ8: 6 | NY8: 6 | NZ8: 6 | OJ8: 6 | OL8: 6 | OT8: 6 | OU8: 6 | OV8: 12 | OY8: 6 | OZ8: 6 | QL8: 6
A9: AMAZON | B9: Báscula Digital de Vidrio Marmol | F9: 6 | G9: 6 | BV9: 6 | DI9: 6 | DU9: 6 | EI9: 6 | FF9: 6 | FY9: 6 | GK9: 12 | JF9: 6 | KY9: 6 | LC9: 6 | LH9: 6 | LL9: 6 | MH9: 6 | MR9: 6 | OS9: 6 | OX9: 6 | QG9: 6
A10: AMAZON | B10: Báscula Digital de Vidrio Transparente | G10: 12 | CL10: 6 | DU10: 6 | EI10: 6 | GM10: 6 | GU10: 6 | GY10: 6 | JF10: 6 | KY10: 6 | LH10: 6 | LJ10: 6 | MH10: 6 | OS10: 6 | OV10: 6
A11: AMAZON | B11: Cojin Cuadrad Memory Foam | F11: 5 | G11: 1 | PY11: 2 | QG11: 2 | QQ11: 1 | QV11: 1 | QW11: 1 | QY11: 1
A12: AMAZON | B12: Inodoro Portatil con tapa y brazo | D12: 4 | F12: 1 | G12: 1
A13: AMAZON | B13: Kit de Nebulización Adulto | OS13: 100
A14: AMAZON | B14: Kit de Nebulización Pediátrico | OS14: 100 | QW14: 100
A15: AMAZON | B15: Nebulizador Adulto Moderno NBA-10WA | NY15: 6
A16: AMAZON | B16: Nebulizador Adulto Moderno Tapa Azul | E16: 6 | H16: 6 | L16: 24 | BY16: 6 | EI16: 12 | EU16: 6 | FA16: 54 | JK16: 6 | KK16: 6 | KP16: 6 | MX16: 6
A17: AMAZON | B17: Nebulizador Pediatrico Buho Celeste | JB17: 6 | KD17: 6 | KI17: 6 | LQ17: 6
A18: AMAZON | B18: Nebulizador Pediatrico Buho Rosado | JB18: 6 | LC18: 6 | LL18: 6 | LQ18: 6
A19: AMAZON | B19: Nebulizador Pediatrico Elefante Rosa | ED19: 6 | EL19: 6 | EO19: 6 | JK19: 6 | JX19: 6 | MH19: 6
A20: AMAZON | B20: Pack Tarjetas Aromatizantes con Frases Motivacionales | GR20: 30
A21: AMAZON | B21: Pack Tarjetas Aromatizantes con Frases Religiosas | GR21: 30
A22: AMAZON | B22: Pack Tarjetas Aromatizantes con Imagenes Religiosas | GR22: 30
A23: AMAZON | B23: Prueba de Embarazo Wellpro Response Tipo Lápiz | HJ23: 100 | HQ23: 100 | IS23: 100 | JR23: 100 | KY23: 100 | LQ23: 100 | LV23: 100 | LZ23: 100 | NY23: 100 | OL23: 100
A24: AMAZON | B24: Silla de Baño con Respaldo | D24: 4 | F24: 1 | G24: 1 | PS24: 1
A25: AMAZON | B25: Silla de Ruedas STD | D25: 3 | F25: 1 | GF25: 1 | GR25: 1
A26: AMAZON | B26: Tarjeta Aromatizante con Frases Motivacionales | GU26: 240 | LC26: 120 | MX26: 120 | NY26: 120
A27: AMAZON | B27: Tarjeta Aromatizante con Frases Religiosas | IW27: 120 | KB27: 120 | MX27: 120 | OM27: 120
A28: AMAZON | B28: Tarjeta Aromatizante con Imágenes Religiosas | FO28: 720
A29: AMAZON | B29: Termómetro Pediatrico Cute Animals Koala | G29: 240 | I29: 240 | R29: 240 | AF29: 240 | AQ29: 240 | BG29: 240 | BK29: 480 | BV29: 240 | DU29: 240 | EY29: 240 | FX29: 240 | HU29: 240 | IA29: 240 | JE29: 240 | JR29: 240 | LL29: 240 | LU29: 240 | NE29: 240 | NX29: 480 | QL29: 240
A30: AMAZON | B30: Termómetro Pediatrico Cute Animals Osito | G30: 240 | M30: 240 | AC30: 240 | BK30: 480 | CI30: 240 | EV30: 240 | GA30: 240 | HX30: 240 | IS30: 240 | JH30: 240 | KT30: 240 | LL30: 240 | LZ30: 240 | NZ30: 240 | OX30: 240 | QN30: 240
A31: AMAZON | B31: Termómetro Pediatrico Cute Animals Panda | G31: 240 | DU31: 240 | IS31: 240 | LL31: 240 | OJ31: 240 | PZ31: 240 | QL31: 240 | QN31: 240 | QT31: 240
A32: AMAZON | B32: Termómetro Pediatrico Cute Animals Ranita | G32: 240 | FF32: 240 | LC32: 240 | PB32: 240
A33: ANGELICA BENITEZ HERNANDEZ | JB33: 53
A34: AP DISTRIBUCION | HQ34: 21600
A35: CHEDRAUI | IR35: 1
A36: CONAFAR | LO36: 340 | PR36: 242 | RA36: 70
A37: COPPEL | IW37: 61 | KL37: 2 | KM37: 2 | KW37: 9 | LL37: 8
A38: COPPEL MARKETPLACE | HF38: 1 | HH38: 2 | HO38: 2 | HR38: 2 | HY38: 1 | KK38: 1 | LS38: 1 | MX38: 1
A39: DANIEL ZARCO SALINAS | IS39: 12 | KM39: 10
A40: FANASA | B40: Nebulizador Adulto Compacto | MK40: 50 | OA40: 6 | OD40: 11 | OJ40: 10 | OT40: 9 | OW40: 20 | PC40: 10 | PG40: 5 | PL40: 3 | PP40: 39 | QT40: 2
A41: FANASA | B41: Nebulizador Adulto Moderno Tapa Azul | MK41: 50 | NK41: 5 | OA41: 5 | OD41: 10 | OJ41: 9 | OT41: 6 | OW41: 20 | PC41: 8 | PG41: 6 | PL41: 2 | PP41: 35
A42: FANASA | B42: Nebulizador Adulto Walmart | NK42: 5
A43: FANASA | B43: Nebulizador Pediatrico Elefante Celeste | NX43: 180 | OW43: 20 | QE43: 81 | QI43: 3 | QT43: 7
A44: FANASA | B44: Nebulizador Pediatrico Elefante Rosa | NX44: 126 | OW44: 20 | PS44: 40 | QE44: 64 | QI44: 35
A45: FANASA | B45: Prueba de Embarazo Wellpro Response Tipo Lápiz | NX45: 260 | OW45: 400 | PS45: 80 | QE45: 155 | QI45: 40 | RA45: 170
A46: FANASA | B46: Termómetro Pediatrico Cute Animals Koala | LA46: 1680 | OW46: 80
A47: FANASA | B47: Termómetro Pediatrico Cute Animals Osito | LA47: 1680 | OW47: 80
A48: FARMACIA LA FE | LM48: 30 | OM48: 121
A49: FARMACIA SAN PABLO | BW49: 560 | CX49: 363 | DI49: 187 | DL49: 1 | DP49: 413 | DX49: 133 | EG49: 25 | EQ49: 94 | EW49: 185 | FJ49: 98 | FZ49: 48 | GJ49: 130 | IC49: 81 | IS49: 87 | JA49: 82 | JE49: 115
A50: FARMACIA SANA SANA | IL50: 179 | JS50: 294 | KI50: 124 | KW50: 104 | MV50: 220 | PC50: 53 | PD50: 53 | PI50: 75
A51: HOSPITALES CRUZ AZUL | OT51: 64
A52: LA GUADALUPANA | HI52: 216 | QM52: 85
A53: MARKET PLACE | AC53: 4 | AE53: 1 | AF53: 1 | AG53: 1 | AH53: 6 | AO53: 5 | AQ53: 6 | AS53: 1 | AV53: 3 | AY53: 2 | AZ53: 5 | BB53: 2 | BC53: 6 | BF53: 4 | BG53: 2 | BI53: 3 | BJ53: 1 | BL53: 1 | BM53: 4 | BO53: 3 | BP53: 3 | BQ53: 1 | BS53: 4 | BU53: 4 | BV53: 1 | BX53: 1 | BZ53: 2 | CA53: 1 | CB53: 2 | CC53: 1 | CF53: 8 | CM53: 3 | CO53: 5 | CQ53: 13 | CR53: 2 | CU53: 2 | CV53: 4 | CW53: 1 | CY53: 8 | CZ53: 4 | DB53: 1 | DD53: 1 | DE53: 7 | DF53: 1 | DG53: 6 | DH53: 1 | DI53: 3 | DJ53: 3 | DK53: 2 | DL53: 6 | DM53: 8 | DN53: 4 | DP53: 10 | DR53: 4 | DS53: 2 | DT53: 4 | DV53: 1 | DW53: 5 | DX53: 36 | DY53: 1 | DZ53: 14 | EA53: 8 | EB53: 1 | EC53: 2 | EE53: 11 | EF53: 5 | EG53: 3 | EH53: 2 | EJ53: 20 | EK53: 2 | EP53: 35 | ER53: 15 | ES53: 21 | ET53: 10 | EU53: 1 | EV53: 4 | EW53: 9 | EX53: 5 | EY53: 2 | EZ53: 4 | FA53: 3 | FB53: 4 | FC53: 5 | FG53: 3 | FH53: 16 | FI53: 5 | FJ53: 9 | FK53: 3 | FL53: 4 | FM53: 11 | FN53: 1
A54: MEDICAL LIFE | J54: 5 | K54: 48
A55: MERCADO LIBRE | FO55: 10 | FP55: 3 | FQ55: 4 | FR55: 6 | FS55: 14 | FT55: 10 | FU55: 6 | FV55: 5 | FW55: 1 | FX55: 6 | FY55: 10 | FZ55: 4 | GA55: 10 | GB55: 6 | GC55: 2 | GD55: 4 | GE55: 8 | GG55: 2 | GH55: 7 | GI55: 2 | GJ55: 3 | GK55: 5 | GL55: 2 | GN55: 5 | GO55: 6 | GP55: 1 | GQ55: 1 | GS55: 7 | GT55: 9 | GU55: 4 | GV55: 6 | GX55: 12 | GY55: 3 | GZ55: 1 | HA55: 8 | HB55: 10 | HC55: 3 | HE55: 3 | HF55: 2 | HG55: 13 | HH55: 6 | HI55: 28 | HJ55: 4 | HK55: 8 | HL55: 11 | HM55: 6 | HN55: 2 | HO55: 6 | HP55: 2 | HQ55: 3 | HR55: 6 | HS55: 4 | HT55: 3 | HU55: 9 | HV55: 5 | HW55: 3 | HX55: 6 | HZ55: 13 | IA55: 4 | IB55: 4 | IC55: 2 | ID55: 6 | IE55: 9 | IF55: 3 | IG55: 1 | IH55: 5 | II55: 2 | IJ55: 2 | IK55: 6 | IL55: 11 | IM55: 1 | IN55: 4 | IO55: 3 | IP55: 2 | IQ55: 5 | IR55: 9 | IT55: 1 | IU55: 3 | IV55: 5 | IW55: 2 | IX55: 6 | IY55: 1 | IZ55: 4 | JA55: 2 | JB55: 1 | JC55: 5 | JD55: 8 | JE55: 8 | JF55: 76 | JG55: 6 | JH55: 5 | JI55: 7 | JJ55: 2 | JK55: 3 | JL55: 1 | JM55: 6 | JN55: 3 | JO55: 4 | JP55: 4 | JQ55: 7 | JS55: 11 | JT55: 4 | JU55: 13 | JV55: 1 | JW55: 13 | JX55: 1 | JZ55: 10 | KA55: 5 | KB55: 4 | KC55: 5 | KD55: 2 | KE55: 2 | KF55: 1 | KG55: 3 | KI55: 6 | KJ55: 5 | KK55: 2 | KL55: 1 | KM55: 3 | KN55: 6 | KO55: 4 | KP55: 5 | KQ55: 3 | KR55: 1 | KT55: 3 | KU55: 11 | KV55: 2 | KX55: 5 | KY55: 3 | KZ55: 4 | LA55: 6 | LB55: 5 | LC55: 4 | LD55: 14 | LE55: 3 | LF55: 2 | LG55: 3 | LH55: 25 | LI55: 18 | LJ55: 15 | LK55: 5 | LL55: 32 | LM55: 1 | LN55: 8 | LO55: 14 | LP55: 8 | LQ55: 26 | LR55: 17 | LS55: 10 | LT55: 6 | LU55: 16 | LV55: 9 | LW55: 10 | LX55: 5 | LY55: 12 | LZ55: 34 | MA55: 14 | MB55: 15 | MC55: 10 | MD55: 16 | ME55: 19 | MF55: 3 | MG55: 13 | MH55: 18 | MI55: 6 | MJ55: 41 | MK55: 11 | ML55: 9 | MM55: 7 | MN55: 19 | MO55: 21 | MP55: 15 | MQ55: 8 | MR55: 10 | MS55: 4 | MT55: 39 | MU55: 7 | MV55: 13 | MW55: 11 | MX55: 26 | MY55: 15 | MZ55: 14 | NA55: 20 | NB55: 30 | NC55: 10 | ND55: 15 | NF55: 43 | NG55: 16 | NH55: 17 | NI55: 11 | NJ55: 43 | NK55: 19 | NL55: 13 | NM55: 16 | NN55: 14 | NO55: 46 | NP55: 5 | NQ55: 24 | NR55: 5 | NS55: 15 | NV55: 22 | NW55: 13 | NX55: 42 | NY55: 11 | NZ55: 11 | OA55: 13 | OB55: 14 | OC55: 41 | OD55: 29 | OE55: 14 | OF55: 15 | OG55: 17 | OH55: 18 | OI55: 6 | OJ55: 18 | OK55: 7 | OL55: 34 | OM55: 17 | ON55: 14 | OO55: 31 | OQ55: 49 | OR55: 61 | OS55: 22 | OT55: 11 | OU55: 27 | OV55: 31 | OX55: 28 | OY55: 16 | OZ55: 41 | PA55: 12 | PB55: 7 | PC55: 20 | PE55: 12 | PF55: 19 | PG55: 14 | PH55: 16 | PI55: 48 | PJ55: 31 | PK55: 24 | PL55: 14 | PM55: 17 | PN55: 39 | PO55: 23 | PP55: 22 | PQ55: 11 | PR55: 19 | PS55: 38 | PT55: 17 | PU55: 19 | PV55: 19 | PW55: 15 | PX55: 32 | PY55: 15 | PZ55: 11 | QB55: 41 | QC55: 25 | QD55: 26 | QE55: 13 | QF55: 18 | QG55: 48 | QH55: 19 | QI55: 15 | QJ55: 23 | QK55: 17 | QL55: 47 | QM55: 17 | QN55: 17 | QO55: 21 | QP55: 15 | QQ55: 50 | QR55: 29 | QS55: 20 | QT55: 23 | QU55: 23 | QV55: 44 | QW55: 25 | QX55: 22 | QY55: 24 | QZ55: 20 | RA55: 39
A56: NADRO | EM56: 36 | GG56: 6 | GN56: 6 | GW56: 6 | HM56: 6 | HX56: 6 | ID56: 258 | IK56: 396 | JF56: 54 | JI56: 96 | JO56: 102 | JP56: 354 | JT56: 426 | JW56: 474 | JZ56: 6 | KF56: 24 | KO56: 86 | LA56: 116 | LD56: 248 | LK56: 32 | LO56: 62 | LQ56: 212 | LW56: 6 | MB56: 84 | MG56: 28 | MP56: 68 | MU56: 502 | ND56: 200 | NG56: 14 | NN56: 1512 | OA56: 8 | OD56: 66 | OJ56: 208 | OP56: 268 | OT56: 242 | OY56: 68 | PA56: 20 | PL56: 26 | PP56: 26 | PT56: 72 | PZ56: 194 | QE56: 114 | QH56: 120 | QI56: 20 | QL56: 260
A57: OPERADORA DE NEGOCIOS VITPOW | JW57: 136 | JZ57: 30
A58: PHARMA PLUS | JO58: 204 | JT58: 252 | KI58: 305 | KK58: 425 | LA58: 333 | LD58: 94 | LK58: 169 | LN58: 128 | LT58: 119 | MI58: 12 | MX58: 6 | NB58: 18 | ND58: 24 | NZ58: 6 | OJ58: 12 | OS58: 18 | OX58: 12 | PA58: 63 | PJ58: 10 | PL58: 91 | PZ58: 110 | QH58: 37 | QL58: 14 | QP58: 31 | QZ58: 45
A59: PUBLICO EN GENERAL | JH59: 26 | KW59: 2 | LU59: 2 | LY59: 2 | MU59: 5 | NM59: 4 | NT59: 35 | NU59: 17 | PD59: 31 | PJ59: 1 | QA59: 33 | QF59: 1 | QR59: 1
A60: UNAM | OV60: 27 | QG60: 27
A61: WALMART | N61: 360 | O61: 960 | P61: 1920 | Q61: 252 | S61: 2316 | T61: 840 | U61: 600 | V61: 258 | W61: 30 | X61: 444 | Y61: 258 | Z61: 1296 | AA61: 522 | AB61: 12 | AD61: 546 | AF61: 1026 | AI61: 534 | AK61: 828 | AL61: 18 | AM61: 288 | AN61: 552 | AP61: 102 | AQ61: 132 | AR61: 318 | AT61: 48 | AU61: 36 | AV61: 102 | AW61: 222 | AX61: 30 | AZ61: 294 | BA61: 60 | BC61: 420 | BD61: 42 | BE61: 18 | BF61: 108 | BH61: 72 | BI61: 252 | BK61: 60 | BL61: 48 | BN61: 552 | BO61: 24 | BP61: 78 | BQ61: 180 | BR61: 60 | BS61: 36 | BT61: 126 | BU61: 192 | BX61: 48 | BY61: 342 | CA61: 222 | CB61: 132 | CD61: 60 | CE61: 654 | CF61: 168 | CG61: 180 | CH61: 108 | CI61: 36 | CJ61: 150 | CK61: 48 | CL61: 18 | CM61: 18 | CN61: 72 | CP61: 360 | CS61: 216 | CT61: 54 | CU61: 90 | CV61: 24 | CW61: 54 | CX61: 30 | CZ61: 102 | DA61: 174 | DB61: 157 | DC61: 180 | DD61: 120 | DE61: 36 | DH61: 192 | DI61: 84 | DK61: 66 | DL61: 294 | DN61: 198 | DO61: 36 | DP61: 216 | DQ61: 48 | DR61: 102 | DS61: 30 | DU61: 192 | DV61: 90 | DX61: 78 | DZ61: 1470 | EA61: 48 | EB61: 240 | EC61: 342 | EE61: 516 | EF61: 246 | EH61: 12 | EI61: 108 | EL61: 1092 | EN61: 1074 | EQ61: 522 | ET61: 288 | EV61: 42 | EX61: 804 | EY61: 300 | EZ61: 504 | FC61: 36 | FD61: 258 | FE61: 12 | FG61: 750 | FI61: 18 | FJ61: 240 | FO61: 306 | FR61: 18 | FS61: 48 | FT61: 18 | FW61: 1038 | GB61: 558 | GF61: 576 | GK61: 570 | GN61: 336 | GS61: 594 | GT61: 264 | GV61: 252 | GY61: 276 | HA61: 18 | HC61: 30 | HD61: 42 | HH61: 270 | HI61: 504 | HM61: 252 | HN61: 36 | HR61: 288 | HT61: 6 | HV61: 24 | HX61: 24 | IB61: 270 | IC61: 510 | IF61: 408 | IJ61: 270 | IK61: 336 | IN61: 372 | IO61: 774 | IS61: 792 | IV61: 24 | IY61: 720 | JB61: 600 | JC61: 660 | JD61: 24 | JE61: 12 | JF61: 102 | JG61: 534 | JI61: 54 | JJ61: 270 | JK61: 66 | JN61: 294 | JP61: 264 | JS61: 66 | JT61: 66 | JY61: 78 | JZ61: 60 | KC61: 84 | KE61: 54 | KH61: 324 | KI61: 162 | KM61: 468 | KN61: 480 | KP61: 720 | KQ61: 144 | KS61: 138 | KU61: 288 | KW61: 492 | KZ61: 138 | LA61: 342 | LE61: 750 | LI61: 180 | LJ61: 318 | LN61: 78 | LO61: 84 | LR61: 1338 | LW61: 132 | LX61: 924 | MB61: 402 | MG61: 354 | MK61: 66 | MM61: 354 | MQ61: 168 | MT61: 348 | MU61: 6 | MV61: 60 | MY61: 48 | MZ61: 30 | ND61: 582 | NG61: 72 | NK61: 270 | NM61: 36 | NQ61: 306 | NV61: 102 | NZ61: 24 | OA61: 6 | OD61: 66 | OH61: 24 | OI61: 42 | OO61: 618 | OT61: 66 | OY61: 318 | PA61: 492 | PB61: 336 | PE61: 42 | PG61: 534 | PJ61: 270 | PL61: 282 | PO61: 24 | PP61: 288 | PT61: 12 | PU61: 30 | PY61: 270 | PZ61: 28 | QC61: 30 | QE61: 42
A62: WALMART | B62: Nebulizador Adulto Walmart | QH62: 36 | QI62: 24 | QM62: 18 | QN62: 42 | QR62: 6 | QW62: 18 | QX62: 6
A63: WALMART | B63: Nebulizador Pediatrico Elefante Celeste | QH63: 12 | QM63: 12 | QN63: 18 | QR63: 12 | QT63: 12
A64: WALMART | B64: Termómetro Pediatrico Cute Animals Panda | QH64: 720 | QI64: 720 | QT64: 240 | QW64: 240
A65: WALMART MARKETPLACE | HP65: 1 | HU65: 2 | IH65: 1 | KE65: 1 | KI65: 1 | LS65: 1 | MO65: 1 | MY65: 1 | NA65: 1 | NG65: 1 | NM65: 1 | QB65: 1
A66: (en blanco) | B66: (en blanco)

Sheet TblProductos
A3: Suma de Cantidad Vendida | B3: Etiquetas de columna
B4: 2024 | C4: 2025 | D4: 2026
A5: Clientes | D5: ene | E5: feb | F5: mar | G5: abr | H5: may | I5: jun | J5: jul | K5: ago
A6: Báscula Digital de Vidrio Antideslizante | B6: 90 | C6: 209 | D6: 28 | E6: 7 | G6: 12 | H6: 32 | I6: 90 | J6: 57 | K6: 64
A7: Báscula Digital de Vidrio Marmol | B7: 18 | C7: 123 | D7: 24 | E7: 6 | F7: 14 | G7: 13 | H7: 5 | I7: 53 | J7: 31 | K7: 52
A8: Báscula Digital de Vidrio Transparente | B8: 12 | C8: 89 | D8: 20 | E8: 7 | F8: 14 | G8: 11 | H8: 5 | I8: 51 | J8: 70 | K8: 63
A9: Cojin Cuadrad Memory Foam | B9: 8 | C9: 16 | D9: 15 | E9: 2 | H9: 13 | J9: 6 | K9: 7
A10: Inodoro Portatil con tapa y brazo | B10: 9 | C10: 85 | D10: 10 | H10: 1 | J10: 1 | K10: 3
A11: Kit de Nebulización Adulto | I11: 105 | J11: 101 | K11: 5
A12: Kit de Nebulización Pediátrico | I12: 105 | J12: 3 | K12: 203
A13: Nebulizador Adulto Compacto | B13: 340 | C13: 2588 | D13: 594 | E13: 123 | F13: 287 | G13: 40 | H13: 139 | I13: 133 | J13: 269 | K13: 129
A14: Nebulizador Adulto Moderno NBA-10WA | E14: 5 | F14: 13 | G14: 1 | H14: 10 | J14: 5 | K14: 2
A15: Nebulizador Adulto Moderno Tapa Azul | B15: 77 | C15: 467 | D15: 226 | E15: 26 | F15: 188 | G15: 69 | H15: 40 | I15: 78 | J15: 66 | K15: 9
A16: Nebulizador Adulto Walmart | B16: 5184 | C16: 5443 | D16: 499 | E16: 608 | F16: 246 | G16: 257 | H16: 100 | I16: 312 | J16: 162 | K16: 150
A17: Nebulizador Pediatrico Buho Blanco | C17: 444 | D17: 314 | E17: 48 | F17: 24 | G17: 24 | H17: 18 | I17: 63 | J17: 6
A18: Nebulizador Pediatrico Buho Celeste | C18: 32 | D18: 57 | E18: 13 | F18: 2 | G18: 2 | J18: 21 | K18: 1
A19: Nebulizador Pediatrico Buho Rosado | C19: 19 | D19: 16 | E19: 15 | F19: 7 | G19: 2 | K19: 4
A20: Nebulizador Pediatrico Elefante Celeste | B20: 3622 | C20: 4755 | D20: 402 | E20: 456 | F20: 270 | G20: 228 | H20: 300 | I20: 332 | J20: 189 | K20: 76
A21: Nebulizador Pediatrico Elefante Rosa | C21: 227 | D21: 37 | E21: 72 | F21: 66 | G21: 72 | H21: 133 | I21: 26 | J21: 134 | K21: 35
A22: Pack Tarjetas Aromatizantes con Frases Motivacionales | C22: 31 | D22: 2
A23: Pack Tarjetas Aromatizantes con Frases Religiosas | C23: 31
A24: Pack Tarjetas Aromatizantes con Imagenes Religiosas | C24: 30
A25: Prueba de Embarazo Wellpro Response Tipo Lápiz | C25: 463 | D25: 141 | E25: 321 | F25: 22 | G25: 41 | H25: 517 | I25: 493 | J25: 295 | K25: 344
A26: Silla de Baño con Respaldo | B26: 6 | C26: 15 | D26: 1 | F26: 1 | H26: 7 | I26: 1 | J26: 1
A27: Silla de Ruedas STD | B27: 5 | C27: 18 | D27: 15 | E27: 2 | F27: 1 | H27: 13
A28: Tarjeta Aromatizante con Frases Motivacionales | C28: 7638 | D28: 165 | F28: 138 | H28: 120 | I28: 38
A29: Tarjeta Aromatizante con Frases Religiosas | C29: 7536 | D29: 27 | F29: 142 | H29: 120 | I29: 23 | K29: 85
A30: Tarjeta Aromatizante con Imágenes Religiosas | C30: 8259 | D30: 30 | F30: 2 | I30: 25
A31: Termómetro Pediatrico Cute Animals Cerdito | C31: 209 | D31: 89 | E31: 36 | F31: 70 | G31: 45 | H31: 76 | I31: 64 | J31: 111 | K31: 76
A32: Termómetro Pediatrico Cute Animals Koala | B32: 2679 | C32: 3747 | D32: 2375 | E32: 370 | F32: 239 | G32: 1055 | H32: 752 | I32: 329 | J32: 254 | K32: 402
A33: Termómetro Pediatrico Cute Animals Osito | B33: 1233 | C33: 2677 | D33: 2164 | E33: 366 | F33: 283 | G33: 866 | H33: 629 | I33: 602 | J33: 232 | K33: 569
A34: Termómetro Pediatrico Cute Animals Panda | B34: 10574 | C34: 19309 | D34: 1279 | E34: 2178 | F34: 504 | G34: 983 | H34: 767 | I34: 1469 | J34: 1019 | K34: 2657
A35: Termómetro Pediatrico Cute Animals Ranita | B35: 255 | C35: 419 | D35: 320 | E35: 31 | F35: 52 | G35: 42 | H35: 71 | I35: 292 | J35: 83 | K35: 43

Sheet Venta
A1: Indica | B1: Fecha | C1: Producto | D1: Cliente | E1: Precio de Venta | F1: Cantidad Vendida | G1: IVA | H1: Total de Venta sin IVA | I1: Total de Venta con IVA | J1: Año | K1: Mes | L1: Día
B2: 45321 | C2: Inodoro Portatil con tapa y brazo | D2: AMAZON | E2: 1068.94 | F2: 1 | G2: 171.03 | H2: 1068.94 | I2: 1239.97 | J2: =YEAR(Ventas_Wellpro[[#This Row],[Fecha]]) -> 2024 | K2: =TEXT(Ventas_Wellpro[[#This Row],[Fecha]],"MMMM") -> enero | L2: =DAY(Ventas_Wellpro[[#This Row],[Fecha]]) -> 30
B3: 45321 | C3: Inodoro Portatil con tapa y brazo | D3: AMAZON | E3: 1068.94 | F3: 3 | G3: 513.09 | H3: 3206.82 | I3: 3719.91 | J3: =YEAR(Ventas_Wellpro[[#This Row],[Fecha]]) -> 2024 | K3: =TEXT(Ventas_Wellpro[[#This Row],[Fecha]],"MMMM") -> enero | L3: =DAY(Ventas_Wellpro[[#This Row],[Fecha]]) -> 30
B4: 45321 | C4: Silla de Baño con Respaldo | D4: AMAZON | E4: 748.26 | F4: 1 | G4: 119.72 | H4: 748.26 | I4: 867.98 | J4: =YEAR(Ventas_Wellpro[[#This Row],[Fecha]]) -> 2024 | K4: =TEXT(Ventas_Wellpro[[#This Row],[Fecha]],"MMMM") -> enero | L4: =DAY(Ventas_Wellpro[[#This Row],[Fecha]]) -> 30
B5: 45321 | C5: Silla de Baño con Respaldo | D5: AMAZON | E5: 748.26 | F5: 3 | G5: 359.16 | H5: 2244.78 | I5: 2603.94 | J5: =YEAR(Ventas_Wellpro[[#This Row],[Fecha]]) -> 2024 | K5: =TEXT(Ventas_Wellpro[[#This Row],[Fecha]],"MMMM") -> enero | L5: =DAY(Ventas_Wellpro[[#This Row],[Fecha]]) -> 30
B6: 45321 | C6: Silla de Ruedas STD | D6: AMAZON | E6: 2419.7 | F6: 3 | G6: 1161.46 | H6: 7259.1 | I6: 8420.56 | J6: =YEAR(Ventas_Wellpro[[#This Row],[Fecha]]) -> 2024 | K6: =TEXT(Ventas_Wellpro[[#This Row],[Fecha]],"MMMM") -> enero | L6: =DAY(Ventas_Wellpro[[#This Row],[Fecha]]) -> 30
B7: 45324 | C7: Nebulizador Adulto Moderno Tapa Azul | D7: AMAZON | E7: 566.83 | F7: 6 | G7: 544.16 | H7: 3400.98 | I7: 3945.14 | J7: =YEAR(Ventas_Wellpro[[#This Row],[Fecha]]) -> 2024 | K7: =TEXT(Ventas_Wellpro[[#This Row],[Fecha]],"MMMM") -> febrero | L7: =DAY(Ventas_Wellpro[[#This Row],[Fecha]]) -> 2
B8: 45329 | C8: Cojin Cuadrad Memory Foam | D8: AMAZON | E8: 160.34 | F8: 5 | G8: 128.27 | H8: 801.7 | I8: 929.97 | J8: =YEAR(Ventas_Wellpro[[#This Row],[Fecha]]) -> 2024 | K8: =TEXT(Ventas_Wellpro[[#This Row],[Fecha]],"MMMM") -> febrero | L8: =DAY(Ventas_Wellpro[[#This Row],[Fecha]]) -> 7
B9: 45329 | C9: Inodoro Portatil con tapa y brazo | D9: AMAZON | E9: 1068.94 | F9: 1 | G9: 171.03 | H9: 1068.94 | I9: 1239.97 | J9: =YEAR(Ventas_Wellpro[[#This Row],[Fecha]]) -> 2024 | K9: =TEXT(Ventas_Wellpro[[#This Row],[Fecha]],"MMMM") -> febrero | L9: =DAY(Ventas_Wellpro[[#This Row],[Fecha]]) -> 7
B10: 45329 | C10: Silla de Baño con Respaldo | D10: AMAZON | E10: 748.26 | F10: 1 | G10: 119.72 | H10: 748.26 | I10: 867.98 | J10: =YEAR(Ventas_Wellpro[[#This Row],[Fecha]]) -> 2024 | K10: =TEXT(Ventas_Wellpro[[#This Row],[Fecha]],"MMMM") -> febrero | L10: =DAY(Ventas_Wellpro[[#This Row],[Fecha]]) -> 7
B11: 45329 | C11: Silla de Ruedas STD | D11: AMAZON | E11: 2419.7 | F11: 1 | G11: 387.15 | H11: 2419.7 | I11: 2806.85 | J11: =YEAR(Ventas_Wellpro[[#This Row],[Fecha]]) -> 2024 | K11: =TEXT(Ventas_Wellpro[[#This Row],[Fecha]],"MMMM") -> febrero | L11: =DAY(Ventas_Wellpro[[#This Row],[Fecha]]) -> 7
B12: 45329 | C12: Báscula Digital de Vidrio Marmol | D12: AMAZON | E12: 176.38 | F12: 6 | G12: 169.32 | H12: 1058.28 | I12: 1227.6 | J12: =YEAR(Ventas_Wellpro[[#This Row],[Fecha]]) -> 2024 | K12: =TEXT(Ventas_Wellpro[[#This Row],[Fecha]],"MMMM") -> febrero | L12: =DAY(Ventas_Wellpro[[#This Row],[Fecha]]) -> 7
B13: 45335 | C13: Báscula Digital de Vidrio Antideslizante | D13: AMAZON | E13: 176.38 | F13: 6 | G13: 169.32 | H13: 1058.28 | I13: 1227.6 | J13: =YEAR(Ventas_Wellpro[[#This Row],[Fecha]]) -> 2024 | K13: =TEXT(Ventas_Wellpro[[#This Row],[Fecha]],"MMMM") -> febrero | L13: =DAY(Ventas_Wellpro[[#This Row],[Fecha]]) -> 13
... B1812: 45901 | C1812: Termómetro Pediatrico Cute Animals Koala | D1812: AMAZON | E1812: 103.34 | F1812: 240 | G1812: 3968.256 | H1812: 24801.6 | I1812: 28769.856 | J1812: =YEAR(Ventas_Wellpro[[#This Row],[Fecha]]) -> 2025 | K1812: =TEXT(Ventas_Wellpro[[#This Row],[Fecha]],"MMMM") -> septiembre | L1812: =DAY(Ventas_Wellpro[[#This Row],[Fecha]]) -> 1
A1813: Aplicar aquí | B1813: 45901 | C1813: Silla de Ruedas STD | D1813: WALMART MARKETPLACE | E1813: 2585.34 | F1813: 1 | G1813: 413.6544 | H1813: 2585.34 | I1813: 2998.9944 | J1813: =YEAR(Ventas_Wellpro[[#This Row],[Fecha]]) -> 2025 | K1813: =TEXT(Ventas_Wellpro[[#This Row],[Fecha]],"MMMM") -> septiembre | L1813: =DAY(Ventas_Wellpro[[#This Row],[Fecha]]) -> 1
B1814: 45901 | C1814: Inodoro Portatil con tapa y brazo | D1814: MERCADO LIBRE | E1814: 1706.9 | F1814: 1 | G1814: 273.104 | H1814: 1706.9 | I1814: 1980.004 | J1814: =YEAR(Ventas_Wellpro[[#This Row],[Fecha]]) -> 2025 | K1814: =TEXT(Ventas_Wellpro[[#This Row],[Fecha]],"MMMM") -> septiembre | L1814: =DAY(Ventas_Wellpro[[#This Row],[Fecha]]) -> 1
B1815: 45901 | C1815: Cojin Cuadrad Memory Foam | D1815: WALMART MARKETPLACE | E1815: 0 | F1815: 1 | G1815: 0 | H1815: 0 | I1815: 0 | J1815: =YEAR(Ventas_Wellpro[[#This Row],[Fecha]]) -> 2025 | K1815: =TEXT(Ventas_Wellpro[[#This Row],[Fecha]],"MMMM") -> septiembre | L1815: =DAY(Ventas_Wellpro[[#This Row],[Fecha]]) -> 1
B1816: 45901 | C1816: Báscula Digital de Vidrio Marmol | D1816: MERCADO LIBRE | E1816: 343.97 | F1816: 1 | G1816: 55.0352 | H1816: 343.97 | I1816: 399.0052 | J1816: =YEAR(Ventas_Wellpro[[#This Row],[Fecha]]) -> 2025 | K1816: =TEXT(Ventas_Wellpro[[#This Row],[Fecha]],"MMMM") -> septiembre | L1816: =DAY(Ventas_Wellpro[[#This Row],[Fecha]]) -> 1
B1817: 45901 | C1817: Termómetro Pediatrico Cute Animals Osito | D1817: MERCADO LIBRE | E1817: 137.79 | F1817: 1 | G1817: 22.0464 | H1817: 137.79 | I1817: 159.8364 | J1817: =YEAR(Ventas_Wellpro[[#This Row],[Fecha]]) -> 2025 | K1817: =TEXT(Ventas_Wellpro[[#This Row],[Fecha]],"MMMM") -> septiembre | L1817: =DAY(Ventas_Wellpro[[#This Row],[Fecha]]) -> 1
B1818: 45901 | C1818: Termómetro Pediatrico Cute Animals Panda | D1818: MERCADO LIBRE | E1818: 136.55 | F1818: 1 | G1818: 21.848 | H1818: 136.55 | I1818: 158.398 | J1818: =YEAR(Ventas_Wellpro[[#This Row],[Fecha]]) -> 2025 | K1818: =TEXT(Ventas_Wellpro[[#This Row],[Fecha]],"MMMM") -> septiembre | L1818: =DAY(Ventas_Wellpro[[#This Row],[Fecha]]) -> 1
B1819: 45901 | C1819: Báscula Digital de Vidrio Transparente | D1819: MERCADO LIBRE | E1819: 340.86 | F1819: 1 | G1819: 54.5376 | H1819: 340.86 | I1819: 395.3976 | J1819: =YEAR(Ventas_Wellpro[[#This Row],[Fecha]]) -> 2025 | K1819: =TEXT(Ventas_Wellpro[[#This Row],[Fecha]],"MMMM") -> septiembre | L1819: =DAY(Ventas_Wellpro[[#This Row],[Fecha]]) -> 1
B1820: 45901 | C1820: Termómetro Pediatrico Cute Animals Ranita | D1820: MERCADO LIBRE | E1820: 137.79 | F1820: 1 | G1820: 22.0464 | H1820: 137.79 | I1820: 159.8364 | J1820: =YEAR(Ventas_Wellpro[[#This Row],[Fecha]]) -> 2025 | K1820: =TEXT(Ventas_Wellpro[[#This Row],[Fecha]],"MMMM") -> septiembre | L1820: =DAY(Ventas_Wellpro[[#This Row],[Fecha]]) -> 1
B1821: 45902 | C1821: Nebulizador Adulto Moderno Tapa Azul | D1821: MERCADO LIBRE | E1821: 905.16 | F1821: 1 | G1821: 144.8256 | H1821: 905.16 | I1821: 1049.9856 | J1821: =YEAR(Ventas_Wellpro[[#This Row],[Fecha]]) -> 2025 | K1821: =TEXT(Ventas_Wellpro[[#This Row],[Fecha]],"MMMM") -> septiembre | L1821: =DAY(Ventas_Wellpro[[#This Row],[Fecha]]) -> 2
B1822: 45902 | C1822: Nebulizador Adulto Walmart | D1822: WALMART | E1822: 498.66 | F1822: 6 | G1822: 478.7136 | H1822: 2991.96 | I1822: 3470.6736 | J1822: =YEAR(Ventas_Wellpro[[#This Row],[Fecha]]) -> 2025 | K1822: =TEXT(Ventas_Wellpro[[#This Row],[Fecha]],"MMMM") -> septiembre | L1822: =DAY(Ventas_Wellpro[[#This Row],[Fecha]]) -> 2
B1823: 45902 | C1823: Nebulizador Adulto Walmart | D1823: WALMART | E1823: 498.66 | F1823: 6 | G1823: 478.7136 | H1823: 2991.96 | I1823: 3470.6736 | J1823: =YEAR(Ventas_Wellpro[[#This Row],[Fecha]]) -> 2025 | K1823: =TEXT(Ventas_Wellpro[[#This Row],[Fecha]],"MMMM") -> septiembre | L1823: =DAY(Ventas_Wellpro[[#This Row],[Fecha]]) -> 2
B1824: 45902 | C1824: Nebulizador Adulto Walmart | D1824: WALMART | E1824: 498.66 | F1824: 6 | G1824: 478.7136 | H1824: 2991.96 | I1824: 3470.6736 | J1824: =YEAR(Ventas_Wellpro[[#This Row],[Fecha]]) -> 2025 | K1824: =TEXT(Ventas_Wellpro[[#This Row],[Fecha]],"MMMM") -> septiembre | L1824: =DAY(Ventas_Wellpro[[#This Row],[Fecha]]) -> 2
B1825: 45902 | C1825: Termómetro Pediatrico Cute Animals Cerdito | D1825: MERCADO LIBRE | E1825: 137.79 | F1825: 1 | G1825: 22.0464 | H1825: 137.79 | I1825: 159.8364 | J1825: =YEAR(Ventas_Wellpro[[#This Row],[Fecha]]) -> 2025 | K1825: =TEXT(Ventas_Wellpro[[#This Row],[Fecha]],"MMMM") -> septiembre | L1825: =DAY(Ventas_Wellpro[[#This Row],[Fecha]]) -> 2
... B1982: 45930 | C1982: Inodoro Portatil con tapa y brazo | D1982: MERCADO LIBRE | E1982: 1706.9 | F1982: 1 | G1982: 273.104 | H1982: 1706.9 | I1982: 1980.004 | J1982: =YEAR(Ventas_Wellpro[[#This Row],[Fecha]]) -> 2025 | K1982: =TEXT(Ventas_Wellpro[[#This Row],[Fecha]],"MMMM") -> septiembre | L1982: =DAY(Ventas_Wellpro[[#This Row],[Fecha]]) -> 30
B1983: 45931 | C1983: Nebulizador Adulto Walmart | D1983: WALMART | E1983: 498.66 | F1983: 6 | G1983: =+(Ventas_Wellpro[[#This Row],[Precio de Venta]]*0.16)*Ventas_Wellpro[[#This Row],[Cantidad Vendida]] -> 478.7136 | H1983: 2991.96 | I1983: =+Ventas_Wellpro[[#This Row],[Total de Venta sin IVA]]+Ventas_Wellpro[[#This Row],[IVA]] -> 3470.6736 | J1983: =YEAR(Ventas_Wellpro[[#This Row],[Fecha]]) -> 2025 | K1983: =TEXT(Ventas_Wellpro[[#This Row],[Fecha]],"MMMM") -> octubre | L1983: =DAY(Ventas_Wellpro[[#This Row],[Fecha]]) -> 1
B1984: 45931 | C1984: Nebulizador Adulto Walmart | D1984: WALMART | E1984: 498.66 | F1984: 36 | G1984: =+(Ventas_Wellpro[[#This Row],[Precio de Venta]]*0.16)*Ventas_Wellpro[[#This Row],[Cantidad Vendida]] -> 2872.2816 | H1984: 17951.76 | I1984: =+Ventas_Wellpro[[#This Row],[Total de Venta sin IVA]]+Ventas_Wellpro[[#This Row],[IVA]] -> 20824.042 | J1984: =YEAR(Ventas_Wellpro[[#This Row],[Fecha]]) -> 2025 | K1984: =TEXT(Ventas_Wellpro[[#This Row],[Fecha]],"MMMM") -> octubre | L1984: =DAY(Ventas_Wellpro[[#This Row],[Fecha]]) -> 1
B1985: 45931 | C1985: Nebulizador Adulto Walmart | D1985: WALMART | E1985: 498.66 | F1985: 12 | G1985: =+(Ventas_Wellpro[[#This Row],[Precio de Venta]]*0.16)*Ventas_Wellpro[[#This Row],[Cantidad Vendida]] -> 957.4272 | H1985: 5983.92 | I1985: =+Ventas_Wellpro[[#This Row],[Total de Venta sin IVA]]+Ventas_Wellpro[[#This Row],[IVA]] -> 6941.3472 | J1985: =YEAR(Ventas_Wellpro[[#This Row],[Fecha]]) -> 2025 | K1985: =TEXT(Ventas_Wellpro[[#This Row],[Fecha]],"MMMM") -> octubre | L1985: =DAY(Ventas_Wellpro[[#This Row],[Fecha]]) -> 1
B1986: 45931 | C1986: Nebulizador Adulto Walmart | D1986: WALMART | E1986: 498.66 | F1986: 6 | G1986: =+(Ventas_Wellpro[[#This Row],[Precio de Venta]]*0.16)*Ventas_Wellpro[[#This Row],[Cantidad Vendida]] -> 478.7136 | H1986: 2991.96 | I1986: =+Ventas_Wellpro[[#This Row],[Total de Venta sin IVA]]+Ventas_Wellpro[[#This Row],[IVA]] -> 3470.6736 | J1986: =YEAR(Ventas_Wellpro[[#This Row],[Fecha]]) -> 2025 | K1986: =TEXT(Ventas_Wellpro[[#This Row],[Fecha]],"MMMM") -> octubre | L1986: =DAY(Ventas_Wellpro[[#This Row],[Fecha]]) -> 1
B1987: 45931 | C1987: Nebulizador Adulto Walmart | D1987: WALMART | E1987: 498.66 | F1987: 6 | G1987: =+(Ventas_Wellpro[[#This Row],[Precio de Venta]]*0.16)*Ventas_Wellpro[[#This Row],[Cantidad Vendida]] -> 478.7136 | H1987: 2991.96 | I1987: =+Ventas_Wellpro[[#This Row],[Total de Venta sin IVA]]+Ventas_Wellpro[[#This Row],[IVA]] -> 3470.6736 | J1987: =YEAR(Ventas_Wellpro[[#This Row],[Fecha]]) -> 2025 | K1987: =TEXT(Ventas_Wellpro[[#This Row],[Fecha]],"MMMM") -> octubre | L1987: =DAY(Ventas_Wellpro[[#This Row],[Fecha]]) -> 1
B1988: 45931 | C1988: Termómetro Pediatrico Cute Animals Cerdito | D1988: MERCADO LIBRE | E1988: 137.79 | F1988: 1 | G1988: =+(Ventas_Wellpro[[#This Row],[Precio de Venta]]*0.16)*Ventas_Wellpro[[#This Row],[Cantidad Vendida]] -> 22.0464 | H1988: 137.79 | I1988: =+Ventas_Wellpro[[#This Row],[Total de Venta sin IVA]]+Ventas_Wellpro[[#This Row],[IVA]] -> 159.8364 | J1988: =YEAR(Ventas_Wellpro[[#This Row],[Fecha]]) -> 2025 | K1988: =TEXT(Ventas_Wellpro[[#This Row],[Fecha]],"MMMM") -> octubre | L1988: =DAY(Ventas_Wellpro[[#This Row],[Fecha]]) -> 1
B1989: 45931 | C1989: Termómetro Pediatrico Cute Animals Koala | D1989: MERCADO LIBRE | E1989: 137.79 | F1989: 1 | G1989: =+(Ventas_Wellpro[[#This Row],[Precio de Venta]]*0.16)*Ventas_Wellpro[[#This Row],[Cantidad Vendida]] -> 22.0464 | H1989: 137.79 | I1989: =+Ventas_Wellpro[[#This Row],[Total de Venta sin IVA]]+Ventas_Wellpro[[#This Row],[IVA]] -> 159.8364 | J1989: =YEAR(Ventas_Wellpro[[#This Row],[Fecha]]) -> 2025 | K1989: =TEXT(Ventas_Wellpro[[#This Row],[Fecha]],"MMMM") -> octubre | L1989: =DAY(Ventas_Wellpro[[#This Row],[Fecha]]) -> 1
B1990: 45931 | C1990: Inodoro Portatil con tapa y brazo | D1990: MERCADO LIBRE | E1990: 1706.9 | F1990: 1 | G1990: =+(Ventas_Wellpro[[#This Row],[Precio de Venta]]*0.16)*Ventas_Wellpro[[#This Row],[Cantidad Vendida]] -> 273.104 | H1990: 1706.9 | I1990: =+Ventas_Wellpro[[#This Row],[Total de Venta sin IVA]]+Ventas_Wellpro[[#This Row],[IVA]] -> 1980.004 | J1990: =YEAR(Ventas_Wellpro[[#This Row],[Fecha]]) -> 2025 | K1990: =TEXT(Ventas_Wellpro[[#This Row],[Fecha]],"MMMM") -> octubre | L1990: =DAY(Ventas_Wellpro[[#This Row],[Fecha]]) -> 1
B1991: 45931 | C1991: Nebulizador Pediatrico Elefante Celeste | D1991: WALMART | E1991: 525.59 | F1991: 24 | G1991: =+(Ventas_Wellpro[[#This Row],[Precio de Venta]]*0.16)*Ventas_Wellpro[[#This Row],[Cantidad Vendida]] -> 2018.2656 | H1991: 12614.16 | I1991: =+Ventas_Wellpro[[#This Row],[Total de Venta sin IVA]]+Ventas_Wellpro[[#This Row],[IVA]] -> 14632.426 | J1991: =YEAR(Ventas_Wellpro[[#This Row],[Fecha]]) -> 2025 | K1991: =TEXT(Ventas_Wellpro[[#This Row],[Fecha]],"MMMM") -> octubre | L1991: =DAY(Ventas_Wellpro[[#This Row],[Fecha]]) -> 1
B1992: 45931 | C1992: Nebulizador Pediatrico Elefante Celeste | D1992: WALMART | E1992: 525.59 | F1992: 102 | G1992: =+(Ventas_Wellpro[[#This Row],[Precio de Venta]]*0.16)*Ventas_Wellpro[[#This Row],[Cantidad Vendida]] -> 8577.6288 | H1992: 53610.18 | I1992: =+Ventas_Wellpro[[#This Row],[Total de Venta sin IVA]]+Ventas_Wellpro[[#This Row],[IVA]] -> 62187.809 | J1992: =YEAR(Ventas_Wellpro[[#This Row],[Fecha]]) -> 2025 | K1992: =TEXT(Ventas_Wellpro[[#This Row],[Fecha]],"MMMM") -> octubre | L1992: =DAY(Ventas_Wellpro[[#This Row],[Fecha]]) -> 1
B1993: 45931 | C1993: Nebulizador Pediatrico Elefante Celeste | D1993: WALMART | E1993: 525.59 | F1993: 54 | G1993: =+(Ventas_Wellpro[[#This Row],[Precio de Venta]]*0.16)*Ventas_Wellpro[[#This Row],[Cantidad Vendida]] -> 4541.0976 | H1993: 28381.86 | I1993: =+Ventas_Wellpro[[#This Row],[Total de Venta sin IVA]]+Ventas_Wellpro[[#This Row],[IVA]] -> 32922.958 | J1993: =YEAR(Ventas_Wellpro[[#This Row],[Fecha]]) -> 2025 | K1993: =TEXT(Ventas_Wellpro[[#This Row],[Fecha]],"MMMM") -> octubre | L1993: =DAY(Ventas_Wellpro[[#This Row],[Fecha]]) -> 1
B1994: 45931 | C1994: Nebulizador Pediatrico Elefante Celeste | D1994: WALMART | E1994: 525.59 | F1994: 66 | G1994: =+(Ventas_Wellpro[[#This Row],[Precio de Venta]]*0.16)*Ventas_Wellpro[[#This Row],[Cantidad Vendida]] -> 5550.2304 | H1994: 34688.94 | I1994: =+Ventas_Wellpro[[#This Row],[Total de Venta sin IVA]]+Ventas_Wellpro[[#This Row],[IVA]] -> 40239.17 | J1994: =YEAR(Ventas_Wellpro[[#This Row],[Fecha]]) -> 2025 | K1994: =TEXT(Ventas_Wellpro[[#This Row],[Fecha]],"MMMM") -> octubre | L1994: =DAY(Ventas_Wellpro[[#This Row],[Fecha]]) -> 1
... B7205: 46282 | C7205: Nebulizador Adulto Moderno NBA-10WA | D7205: MERCADO LIBRE | E7205: 905.16 | F7205: 1 | G7205: =+(Ventas_Wellpro[[#This Row],[Precio de Venta]]*0.16)*Ventas_Wellpro[[#This Row],[Cantidad Vendida]] -> 144.8256 | H7205: 905.16 | I7205: =+Ventas_Wellpro[[#This Row],[Total de Venta sin IVA]]+Ventas_Wellpro[[#This Row],[IVA]] -> 1049.9856 | J7205: =YEAR(Ventas_Wellpro[[#This Row],[Fecha]]) -> 2026 | K7205: =TEXT(Ventas_Wellpro[[#This Row],[Fecha]],"MMMM") -> septiembre | L7205: =DAY(Ventas_Wellpro[[#This Row],[Fecha]]) -> 17

Sheet Catalogo de Productos
A1: Nombre de Producto | B1: Modelo | C1: Costo CIF | D1: Lead Time (meses) | E1: Demanda Prom (mensual) | F1: Familias | G1: Stock Seguridad | H1: UPC | I1: ASIN
A2: Báscula Digital de Vidrio Antideslizante | B2: WP110 | C2: 147.58 | D2: 6 | E2: 18 | F2: DISP MÉDICOS | G2: 18 | H2: 7431009205975 | I2: B0CSKFXJMM
A3: Báscula Digital de Vidrio Marmol | B3: WP108 | C3: 147.58 | D3: 6 | E3: 8 | F3: DISP MÉDICOS | G3: 12 | H3: 7431009205968 | I3: B0CSKJ4BZ7
A4: Báscula Digital de Vidrio Transparente | B4: WP106 | C4: 147.58 | D4: 6 | E4: 8 | F4: DISP MÉDICOS | G4: 12 | H4: 7431009204879 | I4: B0CSKFZQVJ
A5: Cojin Cuadrad Memory Foam | B5: W | C5: 170.34 | D5: 6 | E5: 1 | F5: MEDIOS AUXILIARES + SOPORTE | G5: 1 | H5: 7431009206804 | I5: B0CR4WB3CX
A6: Inodoro Portatil con tapa y brazo | B6: WP813 | C6: 517.5 | D6: 6 | E6: 10 | F6: MEDIOS AUXILIARES + SOPORTE | G6: 10 | H6: 7431009204985 | I6: B0CR1X8V53
A7: Nebulizador Adulto Compacto | B7: NBA-00WA | C7: 441.31 | D7: 6 | E7: 325 | F7: NEBULIZADORES | G7: 325 | H7: 7434002550000 | I7: abcdefghi2
A8: Nebulizador Adulto Moderno NBA-10WA | F8: NEBULIZADORES | H8: 7431009209560 | I8: BOFPHCD4K3
A9: Nebulizador Adulto Moderno Tapa Azul | B9: NBA-01WA | C9: 465.81 | D9: 6 | E9: 11 | F9: NEBULIZADORES | G9: 11 | H9: 7431009204824 | I9: B0CR4H9TVR
A10: Nebulizador Adulto Walmart | B10: NBA-05WA | C10: 441.73 | D10: 6 | E10: 856 | F10: NEBULIZADORES | G10: 856 | H10: 7434002550028 | I10: abcdefghi1
A11: Nebulizador Adulto Moderno Tapa Verde | F11: NEBULIZADORES | H11: 7431009209318 | I11: B0FPHCD4K3
A12: Nebulizador Pediatrico Buho Blanco | F12: NEBULIZADORES | H12: 7431009209317 | I12: ABCDEFG910
A13: Nebulizador Pediatrico Buho Celeste | B13: NBA-01WB | C13: 465.81 | D13: 6 | E13: 1 | F13: NEBULIZADORES | G13: 500 | H13: 7431009209331 | I13: B0FPHYZCDY
A14: Nebulizador Pediatrico Buho Rosado | B14: NBA-01WB | C14: 465.81 | D14: 6 | E14: 1 | F14: NEBULIZADORES | G14: 500 | H14: 7431009209324 | I14: B0FPHSDZXF
A15: Nebulizador Pediatrico Elefante Celeste | B15: NBA-01WE | C15: 465.81 | D15: 6 | E15: 533 | F15: NEBULIZADORES | G15: 533 | H15: 7434002551490 | I15: abcdefghi3
A16: Nebulizador Pediatrico Elefante Rosa | B16: NBA-02WE | C16: 465.81 | D16: 6 | E16: 4 | F16: NEBULIZADORES | G16: 4 | H16: 7434002551506 | I16: B0DY2VFP2B
A17: Pack Tarjetas Aromatizantes con Frases Motivacionales | B17: JH0006 | C17: 184.56 | D17: 6 | E17: 10 | F17: AROMATIZANTES | G17: 10 | H17: 7431009209737 | I17: B0FCPGQJ9V
A18: Pack Tarjetas Aromatizantes con Frases Religiosas | B18: JH0005 | C18: 184.56 | D18: 6 | E18: 10 | F18: AROMATIZANTES | G18: 10 | H18: 7431009209713 | I18: B0FCQ2W6LT
A19: Pack Tarjetas Aromatizantes con Imagenes Religiosas | B19: JH0004 | C19: 184.56 | D19: 6 | E19: 10 | F19: AROMATIZANTES | G19: 10 | H19: 7431009207849 | I19: B0FCPW4XGX
A20: Prueba de Embarazo Wellpro Response Tipo Lápiz | C20: 17.9445 | D20: 5 | E20: 200 | F20: PRUEBAS EMBARAZO | G20: 400 | H20: 7431009209515 | I20: B0FKL74MN4
A21: Silla de Baño con Respaldo | B21: WP798L | C21: 349.31 | D21: 6 | E21: 3 | F21: MEDIOS AUXILIARES + SOPORTE | G21: 3 | H21: 7434002552640 | I21: B0CR1VKLK5
A22: Silla de Ruedas STD | C22: 1086.75 | D22: 6 | E22: 1 | F22: MEDIOS AUXILIARES + SOPORTE | G22: 1 | H22: 7431009205050 | I22: B0CR1W6KYT
A23: Tarjeta Aromatizante con Frases Motivacionales | B23: JH0002 | C23: 7.69 | D23: 6 | E23: 1 | F23: AROMATIZANTES | G23: 720 | H23: 7431009209706 | I23: B0FCPYRM2F
A24: Tarjeta Aromatizante con Frases Religiosas | B24: JH0003 | C24: 7.69 | D24: 6 | E24: 1 | F24: AROMATIZANTES | G24: 720 | H24: 7431009209690 | I24: B0FCP3CWBZ
A25: Tarjeta Aromatizante con Imágenes Religiosas | B25: JH0001 | C25: 7.69 | D25: 6 | E25: 1 | F25: AROMATIZANTES | G25: 720 | H25: 7431009207771 | I25: B0DJDV8ND4
A26: Termómetro Pediatrico Cute Animals Cerdito | B26: DMC-102 | C26: 60.76 | D26: 6 | E26: 20 | F26: TERMOMETROS | G26: 240 | H26: 7431009207467 | I26: B0F1F3YCRR
A27: Termómetro Pediatrico Cute Animals Koala | B27: DMC-102 | C27: 60.76 | D27: 6 | E27: 321 | F27: TERMOMETROS | G27: 480 | H27: 7431009207504 | I27: B0CSKGRXVD
A28: Termómetro Pediatrico Cute Animals Osito | B28: DMC-102 | C28: 60.76 | D28: 6 | E28: 140 | F28: TERMOMETROS | G28: 240 | H28: 7431009207481 | I28: B0CSKH3J51
A29: Termómetro Pediatrico Cute Animals Panda | B29: DMC-102 | C29: 60.76 | D29: 6 | E29: 2000 | F29: TERMOMETROS | G29: 2000 | H29: 7431009207498 | I29: B0CSKJ44LB
A30: Termómetro Pediatrico Cute Animals Ranita | B30: DMC-102 | C30: 60.76 | D30: 6 | E30: 10 | F30: TERMOMETROS | G30: 10 | H30: 7431009207474 | I30: B0CSKJ44KL
A31: Nebulizador Pediatrico Animalitos | F31: NEBULIZADORES | H31: 7770000000053 | I31: B0CSKJ4TT3
A32: Kit de Nebulización Adulto | F32: MRP | H32: 7770000000054 | I32: B0H34TFWGW
A33: Kit de Nebulización Pediátrico | F33: MRP | H33: 7770000000055 | I33: B0H356Y44V
A34: Nebulizador Pediátrico Penguin | F34: NEBULIZADORES | H34: 7743100920748 | I34: B0H356Y44X
A35: Termómetro Pediatrico Cute Animals Osito | F35: TERMOMETROS | H35: 743100920748 | I35: B0H356Y44Z

Sheet Productos_Sell_In
A1: Producto | B1: UPC
A2: Nebulizador Adulto Moderno NBA-01WA | B2: 7431009204824
A3: Nebulizador Adulto Moderno Tapa Azul | B3: 7431009204824
A4: Báscula Digital de Vidrio Transparente | B4: 7431009204879
A5: Bascula Digital de Vidrio Transparente | B5: 7431009204879
A6: Inodoro Portatil con tapa y brazo | B6: 7431009204985
A7: Inodoro Portatil | B7: 7431009204985
A8: Silla de Ruedas STD | B8: 7431009205050
A9: Silla de Ruedas Standar | B9: 7431009205050
A10: Báscula Digital de Vidrio Marmol | B10: 7431009205968
A11: Bascula Digital de Vidrio Marmol | B11: 7431009205968
A12: Báscula Digital de Vidrio Antideslizante | B12: 7431009205975
A13: Bascula Digital de Vidrio Antideslizante | B13: 7431009205975
... A20: Termómetro Pediatrico Cute Animals Osito | B20: 7431009207481
A21: Termómetro Pediatrico Cute Animals Osito | B21: 743100920748
A22: Termómetro Pediatrico Cute Animals Panda | B22: 7431009207498
A23: Termometro Pediatrico Panda | B23: 7431009207498
A24: Termómetro Pediatrico Cute Animals Koala | B24: 7431009207504
A25: Termometro Pediatrico Koala | B25: 7431009207504
A26: Tarjeta Aromatizante con Imágenes Religiosas | B26: 7431009207771
A27: Pack Tarjetas Aromatizantes con Imagenes Religiosas | B27: 7431009207849
A28: Tarjetas Aromatizantes con Imagenes Religiosas | B28: 7431009207849
A29: Nebulizador Pediatrico Buho Blanco | B29: 7431009209317
A30: Nebulizador Pediatrico Buho Rosado | B30: 7431009209324
A31: Nebulizador Pediatrico Buho Celeste | B31: 7431009209331
A32: Nebulizador Pediátrico Búho Celeste | B32: 7431009209331
A33: PRUEBA DE EMBARAZO RESPONSE TIPO LAPIZ | B33: 7431009209515
... A49: Nebulizador Pediátrico Penguin | B49: 7743100920748

Sheet Catalogo de Estados
A1: Codigo Estados
A2: MX-AGU
A3: MX-VER
A4: MX-NLE
A5: MX-DIF
A6: MX-GUA
A7: MX-TAM
A8: MX-SLP
A9: MX-SIN
A10: MX-MEX
A11: MX-ROO
A12: MX-COA
... A33: MX-BCS

Sheet Hoja1
F3: Suma de Cantidad Vendida | G3: Etiquetas de columna
G4: 2026 | S4: Total general
B5: FABRICANTE | C5: EXPORTADOR / DESPACHANTE | D5: COD ARTICULO | E5: DESCRIPCIÓN ARTICULO NICARAGUA | F5: ARTICULOS | G5: ene | H5: feb | I5: mar | J5: abr | K5: may | L5: jun | M5: jul | N5: ago | O5: sept | P5: oct | Q5: nov | R5: dic | T5: Prom = 6 | U5: Existencia 27.01.2026 | V5: COSTO PROM ($)
B6: =_xlfn.XLOOKUP(F6,'[1]Demanda MX'!$F:$F,'[1]Demanda MX'!$B:$B,0,0) -> ZHONGSHAN SILK | C6: =_xlfn.XLOOKUP(F6,'[1]Demanda MX'!$F:$F,'[1]Demanda MX'!$C:$C,0,0) -> FORTUS S.A. | D6: =_xlfn.XLOOKUP(F6,'[1]Demanda MX'!$F:$F,'[1]Demanda MX'!$E:$E,0,0) -> 13972 | E6: =_xlfn.XLOOKUP(F6,'[1]Demanda MX'!$F:$F,'[1]Demanda MX'!$G:$G,0,0) -> WP110 BALANZA DIGITAL DE VIDRIO ANTIDESLIZANTE (WELLPRO) | F6: Báscula Digital de Vidrio Antideslizante | G6: 66 | H6: 40 | I6: 36 | J6: 26 | K6: 26 | L6: 32 | M6: 52 | N6: 66 | O6: 26 | P6: 32 | Q6: 40 | R6: 72 | S6: 514 | T6: =AVERAGE(H6,I6,J6,K6,L6,M6) -> 35.333333 | U6: =_xlfn.XLOOKUP(F6,'[1]Demanda MX'!$F:$F,'[1]Demanda MX'!$I:$I,0,0) -> 536 | V6: =_xlfn.XLOOKUP(F6,'[1]Demanda MX'!$F:$F,'[1]Demanda MX'!$J:$J,0,0) -> 147.5766
B7: =_xlfn.XLOOKUP(F7,'[1]Demanda MX'!$F:$F,'[1]Demanda MX'!$B:$B,0,0) -> ZHONGSHAN SILK | C7: =_xlfn.XLOOKUP(F7,'[1]Demanda MX'!$F:$F,'[1]Demanda MX'!$C:$C,0,0) -> FORTUS S.A. | D7: =_xlfn.XLOOKUP(F7,'[1]Demanda MX'!$F:$F,'[1]Demanda MX'!$E:$E,0,0) -> 13971 | E7: =_xlfn.XLOOKUP(F7,'[1]Demanda MX'!$F:$F,'[1]Demanda MX'!$G:$G,0,0) -> WP108 BALANZA DIGITAL DE VIDRIO ACABADO MARMOL (WELLPRO) | F7: Báscula Digital de Vidrio Marmol | G7: 4 | H7: 4 | I7: 10 | J7: 2 | K7: 2 | L7: 14 | M7: 16 | N7: 4 | O7: 2 | P7: 8 | Q7: 4 | R7: 10 | S7: 80 | T7: =AVERAGE(H7,I7,J7,K7,L7,M7) -> 8 | U7: =_xlfn.XLOOKUP(F7,'[1]Demanda MX'!$F:$F,'[1]Demanda MX'!$I:$I,0,0) -> 702 | V7: =_xlfn.XLOOKUP(F7,'[1]Demanda MX'!$F:$F,'[1]Demanda MX'!$J:$J,0,0) -> 147.5766
B8: =_xlfn.XLOOKUP(F8,'[1]Demanda MX'!$F:$F,'[1]Demanda MX'!$B:$B,0,0) -> ZHONGSHAN SILK | C8: =_xlfn.XLOOKUP(F8,'[1]Demanda MX'!$F:$F,'[1]Demanda MX'!$C:$C,0,0) -> FORTUS S.A. | D8: =_xlfn.XLOOKUP(F8,'[1]Demanda MX'!$F:$F,'[1]Demanda MX'!$E:$E,0,0) -> 13667 | E8: =_xlfn.XLOOKUP(F8,'[1]Demanda MX'!$F:$F,'[1]Demanda MX'!$G:$G,0,0) -> BALANZA DIGITAL DE VIDRIO WP106 (WELLPRO) | F8: Báscula Digital de Vidrio Transparente | G8: 4 | H8: 4 | I8: 10 | J8: 2 | K8: 2 | L8: 14 | M8: 16 | N8: 4 | O8: 2 | P8: 8 | Q8: 4 | R8: 10 | S8: 80 | T8: =AVERAGE(H8,I8,J8,K8,L8,M8) -> 8 | U8: =_xlfn.XLOOKUP(F8,'[1]Demanda MX'!$F:$F,'[1]Demanda MX'!$I:$I,0,0) -> 868 | V8: =_xlfn.XLOOKUP(F8,'[1]Demanda MX'!$F:$F,'[1]Demanda MX'!$J:$J,0,0) -> 154.16365
B9: =_xlfn.XLOOKUP(F9,'[1]Demanda MX'!$F:$F,'[1]Demanda MX'!$B:$B,0,0) -> JIANLIAN HOMECARE | C9: =_xlfn.XLOOKUP(F9,'[1]Demanda MX'!$F:$F,'[1]Demanda MX'!$C:$C,0,0) -> FORTUS S.A. | D9: =_xlfn.XLOOKUP(F9,'[1]Demanda MX'!$F:$F,'[1]Demanda MX'!$E:$E,0,0) -> 13648 | E9: =_xlfn.XLOOKUP(F9,'[1]Demanda MX'!$F:$F,'[1]Demanda MX'!$G:$G,0,0) -> WP813 INODORO PORTATIL CON TAPA Y BRAZO (WELLPRO) | F9: Inodoro Portatil con tapa y brazo | G9: 3 | H9: 4 | I9: 4 | J9: 5 | K9: 6 | L9: 7 | M9: 9 | N9: 9 | O9: 10 | P9: 11 | Q9: 10 | R9: 10 | S9: 88 | T9: =AVERAGE(H9,I9,J9,K9,L9,M9) -> 5.8333333 | U9: =_xlfn.XLOOKUP(F9,'[1]Demanda MX'!$F:$F,'[1]Demanda MX'!$I:$I,0,0) -> 0 | V9: =_xlfn.XLOOKUP(F9,'[1]Demanda MX'!$F:$F,'[1]Demanda MX'!$J:$J,0,0) -> 0
B10: =_xlfn.XLOOKUP(F10,'[1]Demanda MX'!$F:$F,'[1]Demanda MX'!$B:$B,0,0) -> SHENZHEN FITCONN TECHNOLOGY CO., LTD | C10: =_xlfn.XLOOKUP(F10,'[1]Demanda MX'!$F:$F,'[1]Demanda MX'!$C:$C,0,0) -> FORTUS S.A. | D10: =_xlfn.XLOOKUP(F10,'[1]Demanda MX'!$F:$F,'[1]Demanda MX'!$E:$E,0,0) -> 14806 | E10: =_xlfn.XLOOKUP(F10,'[1]Demanda MX'!$F:$F,'[1]Demanda MX'!$G:$G,0,0) -> NBA-00WA NEBULIZADOR FAMILIAR (WELLPRO) | F10: Nebulizador Adulto Compacto | G10: 553 | H10: 557 | I10: 296 | J10: 296 | K10: 280 | L10: 220 | M10: 289 | N10: 262 | O10: 309 | P10: 554 | Q10: 412 | R10: 597 | S10: 4625 | T10: =AVERAGE(H10,I10,J10,K10,L10,M10) -> 323 | U10: =_xlfn.XLOOKUP(F10,'[1]Demanda MX'!$F:$F,'[1]Demanda MX'!$I:$I,0,0) -> 5943 | V10: =_xlfn.XLOOKUP(F10,'[1]Demanda MX'!$F:$F,'[1]Demanda MX'!$J:$J,0,0) -> 441.3131
B11: =_xlfn.XLOOKUP(F11,'[1]Demanda MX'!$F:$F,'[1]Demanda MX'!$B:$B,0,0) -> SHENZHEN FITCONN TECHNOLOGY CO., LTD | C11: =_xlfn.XLOOKUP(F11,'[1]Demanda MX'!$F:$F,'[1]Demanda MX'!$C:$C,0,0) -> FORTUS S.A. | D11: =_xlfn.XLOOKUP(F11,'[1]Demanda MX'!$F:$F,'[1]Demanda MX'!$E:$E,0,0) -> 13644 | E11: =_xlfn.XLOOKUP(F11,'[1]Demanda MX'!$F:$F,'[1]Demanda MX'!$G:$G,0,0) -> NBA-01WA NEBULIZADOR ADULTO MODERNO (WELLPRO) | F11: Nebulizador Adulto Moderno Tapa Azul | G11: 1040 | H11: 936 | I11: 719 | J11: 364 | K11: 370 | L11: 446 | M11: 452 | N11: 364 | O11: 527 | P11: 1090 | Q11: 1244 | R11: 1396 | S11: 8948 | T11: =AVERAGE(H11,I11,J11,K11,L11,M11) -> 547.83333 | U11: =_xlfn.XLOOKUP(F11,'[1]Demanda MX'!$F:$F,'[1]Demanda MX'!$I:$I,0,0) -> 5488 | V11: =_xlfn.XLOOKUP(F11,'[1]Demanda MX'!$F:$F,'[1]Demanda MX'!$J:$J,0,0) -> 465.8061
B12: =_xlfn.XLOOKUP(F12,'[1]Demanda MX'!$F:$F,'[1]Demanda MX'!$B:$B,0,0) -> SHENZHEN FITCONN TECHNOLOGY CO., LTD | C12: =_xlfn.XLOOKUP(F12,'[1]Demanda MX'!$F:$F,'[1]Demanda MX'!$C:$C,0,0) -> FORTUS S.A. | D12: =_xlfn.XLOOKUP(F12,'[1]Demanda MX'!$F:$F,'[1]Demanda MX'!$E:$E,0,0) -> 14660 | E12: =_xlfn.XLOOKUP(F12,'[1]Demanda MX'!$F:$F,'[1]Demanda MX'!$G:$G,0,0) -> NBA-05WA NEBULIZADOR ADULTO (WELLPRO) | F12: Nebulizador Adulto Walmart | G12: 1164 | H12: 1374 | I12: 576 | J12: 216 | K12: 192 | L12: 276 | M12: 264 | N12: 168 | O12: 306 | P12: 864 | Q12: 984 | R12: 1134 | S12: 7518 | T12: =AVERAGE(H12,I12,J12,K12,L12,M12) -> 483 | U12: =_xlfn.XLOOKUP(F12,'[1]Demanda MX'!$F:$F,'[1]Demanda MX'!$I:$I,0,0) -> 3589 | V12: =_xlfn.XLOOKUP(F12,'[1]Demanda MX'!$F:$F,'[1]Demanda MX'!$J:$J,0,0) -> 443.43104
B13: =_xlfn.XLOOKUP(F13,'[1]Demanda MX'!$F:$F,'[1]Demanda MX'!$B:$B,0,0) -> SHENZHEN FITCONN TECHNOLOGY CO., LTD | C13: =_xlfn.XLOOKUP(F13,'[1]Demanda MX'!$F:$F,'[1]Demanda MX'!$C:$C,0,0) -> FORTUS S.A. | D13: =_xlfn.XLOOKUP(F13,'[1]Demanda MX'!$F:$F,'[1]Demanda MX'!$E:$E,0,0) -> F13789 | E13: =_xlfn.XLOOKUP(F13,'[1]Demanda MX'!$F:$F,'[1]Demanda MX'!$G:$G,0,0) -> 0 | F13: Nebulizador Pediatrico Buho Blanco | G13: 0 | H13: 265 | I13: 28 | J13: 180 | K13: 0 | L13: 55 | M13: 51 | N13: 0 | O13: 0 | P13: 0 | Q13: 92 | R13: 57 | S13: 728 | T13: =AVERAGE(H13,I13,J13,K13,L13,M13) -> 96.5 | U13: =_xlfn.XLOOKUP(F13,'[1]Demanda MX'!$F:$F,'[1]Demanda MX'!$I:$I,0,0) -> 1714 | V13: =_xlfn.XLOOKUP(F13,'[1]Demanda MX'!$F:$F,'[1]Demanda MX'!$J:$J,0,0) -> 417.75261
B14: =_xlfn.XLOOKUP(F14,'[1]Demanda MX'!$F:$F,'[1]Demanda MX'!$B:$B,0,0) -> SHENZHEN FITCONN TECHNOLOGY CO., LTD | C14: =_xlfn.XLOOKUP(F14,'[1]Demanda MX'!$F:$F,'[1]Demanda MX'!$C:$C,0,0) -> FORTUS S.A. | D14: =_xlfn.XLOOKUP(F14,'[1]Demanda MX'!$F:$F,'[1]Demanda MX'!$E:$E,0,0) -> F13791 | E14: =_xlfn.XLOOKUP(F14,'[1]Demanda MX'!$F:$F,'[1]Demanda MX'!$G:$G,0,0) -> 0 | F14: Nebulizador Pediatrico Buho Celeste | G14: 166.5 | H14: 509 | I14: 262 | J14: 171 | K14: 129 | L14: 165 | M14: 162 | N14: 114 | O14: 159 | P14: 523 | Q14: 407 | R14: 567 | S14: 3334.5 | T14: =AVERAGE(H14,I14,J14,K14,L14,M14) -> 233 | U14: =_xlfn.XLOOKUP(F14,'[1]Demanda MX'!$F:$F,'[1]Demanda MX'!$I:$I,0,0) -> 1464 | V14: =_xlfn.XLOOKUP(F14,'[1]Demanda MX'!$F:$F,'[1]Demanda MX'!$J:$J,0,0) -> 417.7526
B15: =_xlfn.XLOOKUP(F15,'[1]Demanda MX'!$F:$F,'[1]Demanda MX'!$B:$B,0,0) -> SHENZHEN FITCONN TECHNOLOGY CO., LTD | C15: =_xlfn.XLOOKUP(F15,'[1]Demanda MX'!$F:$F,'[1]Demanda MX'!$C:$C,0,0) -> FORTUS S.A. | D15: =_xlfn.XLOOKUP(F15,'[1]Demanda MX'!$F:$F,'[1]Demanda MX'!$E:$E,0,0) -> F13790 | E15: =_xlfn.XLOOKUP(F15,'[1]Demanda MX'!$F:$F,'[1]Demanda MX'!$G:$G,0,0) -> CNB69026 NEBULIZADOR PED. BUHO ROSADO (WELLPRO) | F15: Nebulizador Pediatrico Buho Rosado | G15: 46.5 | H15: 48 | I15: 51 | J15: 54 | K15: 57 | L15: 60 | M15: 63 | N15: 66 | O15: 69 | P15: 72 | Q15: 75 | R15: 78 | S15: 739.5 | T15: =AVERAGE(H15,I15,J15,K15,L15,M15) -> 55.5 | U15: =_xlfn.XLOOKUP(F15,'[1]Demanda MX'!$F:$F,'[1]Demanda MX'!$I:$I,0,0) -> 1471 | V15: =_xlfn.XLOOKUP(F15,'[1]Demanda MX'!$F:$F,'[1]Demanda MX'!$J:$J,0,0) -> 417.7526
B16: =_xlfn.XLOOKUP(F16,'[1]Demanda MX'!$F:$F,'[1]Demanda MX'!$B:$B,0,0) -> SHENZHEN FITCONN TECHNOLOGY CO., LTD | C16: =_xlfn.XLOOKUP(F16,'[1]Demanda MX'!$F:$F,'[1]Demanda MX'!$C:$C,0,0) -> FORTUS S.A. | D16: =_xlfn.XLOOKUP(F16,'[1]Demanda MX'!$F:$F,'[1]Demanda MX'!$E:$E,0,0) -> 13471 | E16: =_xlfn.XLOOKUP(F16,'[1]Demanda MX'!$F:$F,'[1]Demanda MX'!$G:$G,0,0) -> NBA-02WE NEBULIZADOR ELEFANTE CELESTE (WELLPRO) | F16: Nebulizador Pediatrico Elefante Celeste | G16: 280.5 | H16: 954 | I16: 471 | J16: 288 | K16: 201 | L16: 258 | M16: 261 | N16: 162 | O16: 237 | P16: 972 | Q16: 735 | R16: 1038 | S16: 5857.5 | T16: =AVERAGE(H16,I16,J16,K16,L16,M16) -> 405.5 | U16: =_xlfn.XLOOKUP(F16,'[1]Demanda MX'!$F:$F,'[1]Demanda MX'!$I:$I,0,0) -> 2915 | V16: =_xlfn.XLOOKUP(F16,'[1]Demanda MX'!$F:$F,'[1]Demanda MX'!$J:$J,0,0) -> 462.35539
B17: =_xlfn.XLOOKUP(F17,'[1]Demanda MX'!$F:$F,'[1]Demanda MX'!$B:$B,0,0) -> SHENZHEN FITCONN TECHNOLOGY CO., LTD | C17: =_xlfn.XLOOKUP(F17,'[1]Demanda MX'!$F:$F,'[1]Demanda MX'!$C:$C,0,0) -> FORTUS S.A. | D17: =_xlfn.XLOOKUP(F17,'[1]Demanda MX'!$F:$F,'[1]Demanda MX'!$E:$E,0,0) -> 13470 | E17: =_xlfn.XLOOKUP(F17,'[1]Demanda MX'!$F:$F,'[1]Demanda MX'!$G:$G,0,0) -> NBA-01WE NEBULIZADOR ELEFANTE ROSADO (WELLPRO) | F17: Nebulizador Pediatrico Elefante Rosa | G17: 171.5 | H17: 503 | I17: 268 | J17: 207 | K17: 129 | L17: 165 | M17: 162 | N17: 114 | O17: 159 | P17: 523 | Q17: 407 | R17: 566 | S17: 3374.5 | T17: =AVERAGE(H17,I17,J17,K17,L17,M17) -> 239 | U17: =_xlfn.XLOOKUP(F17,'[1]Demanda MX'!$F:$F,'[1]Demanda MX'!$I:$I,0,0) -> 11324 | V17: =_xlfn.XLOOKUP(F17,'[1]Demanda MX'!$F:$F,'[1]Demanda MX'!$J:$J,0,0) -> 447.78175
... B27: =_xlfn.XLOOKUP(F27,'[1]Demanda MX'!$F:$F,'[1]Demanda MX'!$B:$B,0,0) -> GEON CORPORATION | C27: =_xlfn.XLOOKUP(F27,'[1]Demanda MX'!$F:$F,'[1]Demanda MX'!$C:$C,0,0) -> GEONIC | D27: =_xlfn.XLOOKUP(F27,'[1]Demanda MX'!$F:$F,'[1]Demanda MX'!$E:$E,0,0) -> 13597 | E27: =_xlfn.XLOOKUP(F27,'[1]Demanda MX'!$F:$F,'[1]Demanda MX'!$G:$G,0,0) -> DMC-102 TERMOMETRO DIGITAL PED "RANITA" (WELLPRO) | F27: Termómetro Pediatrico Cute Animals Ranita | G27: 40 | H27: 40 | I27: 40 | J27: 40 | K27: 40 | L27: 40 | M27: 40 | N27: 40 | O27: 40 | P27: 40 | Q27: 40 | R27: 40 | S27: 480 | T27: =AVERAGE(H27,I27,J27,K27,L27,M27) -> 40 | U27: =_xlfn.XLOOKUP(F27,'[1]Demanda MX'!$F:$F,'[1]Demanda MX'!$I:$I,0,0) -> 8493 | V27: =_xlfn.XLOOKUP(F27,'[1]Demanda MX'!$F:$F,'[1]Demanda MX'!$J:$J,0,0) -> 60.761
E28: MASCARA DE OXIGENO NEBULIZADORA PARA ADULTO | F28: MASCARA DE OXIGENO NEBULIZADORA PARA ADULTO
E29: MASCARA DE OXIGENO NEBULIZADORA PARA NIÑOS | F29: MASCARA DE OXIGENO NEBULIZADORA PARA NIÑOS

Sheet Hoja2
A1: Años (Fecha) | B1: 2026
A3: Suma de Total de Venta | B3: Etiquetas de columna
A4: Etiquetas de fila | B4: ene | C4: feb | D4: mar | E4: Total general
A5: AROMATIZANTES | B5: 299963.04 | C5: 1023.84 | D5: 1023.84 | E5: 302010.72 | F5: =E5/20 -> 15100.536
A6: DISP MÉDICOS | B6: 24804.6 | C6: 14430.6 | D6: 14242.74 | E6: 53477.94 | F6: =E6/20 -> 2673.897
A7: MEDIOS AUXILIARES + SOPORTE | B7: 10303.9 | C7: 7220.17 | D7: 11568 | E7: 29092.07 | F7: =E7/20 -> 1454.6035
A8: NEBULIZADORES | B8: 1801369.4 | C8: 2735258.5 | D8: 1434169.9 | E8: 5970797.8 | F8: =E8/20 -> 298539.89
A9: PRUEBAS EMBARAZO | B9: 13448 | C9: 6529.02 | D9: 59990.08 | E9: 79967.1 | F9: =E9/20 -> 3998.355
A10: TERMOMETROS | B10: 403043.63 | C10: 441551.8 | D10: 569478 | E10: 1414073.4 | F10: =E10/20 -> 70703.671
A11: Total general | B11: 2552932.5 | C11: 3206014 | D11: 2090472.5 | E11: 7849419 | F11: =SUM(F5:F10) -> 392470.95
A14: Años (Fecha) | B14: 2026
A16: Suma de Total de Venta | B16: Etiquetas de columna | I16: Clientes | J16: Categoría 2
A17: Etiquetas de fila | B17: ene | C17: feb | D17: mar | E17: Total general | F17: CATEGORÍA | G17: MONTO | I17: WALMART | J17: AUTOSERVICIO
A18: Amazon | B18: 47180.3 | C18: 38116.99 | D18: 67296.6 | E18: 152593.89 | F18: E-COMERCE | G18: =E18/20 -> 7629.6945 | I18: AMAZON | J18: E-COMERCE
A19: AP Distribucion | B19: 297000 | C19: 0 | D19: 0 | E19: 297000 | F19: DISTRIBUIDOR | G19: =E19/20 -> 14850 | I19: MARKET PLACE | J19: E-COMERCE
A20: Basilica de Guadalupe | B20: 0 | C20: 0 | D20: 0 | E20: 0 | F20: AUTOSERVICIO | G20: =E20/20 -> 0 | I20: CHEDRAUI | J20: AUTOSERVICIO
A21: FANASA | B21: 153561.95 | C21: 158166.8 | D21: 170169.96 | E21: 481898.71 | F21: DISTRIBUIDOR | G21: =E21/20 -> 24094.935 | I21: MEDICAL LIFE | J21: FARMACIA
A22: Farmacia Benavides | B22: 753837.3 | C22: 1101367.7 | D22: 807037.24 | E22: 2662242.2 | F22: FARMACIA | G22: =E22/20 -> 133112.11 | I22: NADRO | J22: DISTRIBUIDOR
A23: Farmacia San Pablo | B23: 210943.62 | C23: 360009.1 | D23: 92213.44 | E23: 663166.16 | F23: FARMACIA | G23: =E23/20 -> 33158.308 | I23: UNEFARM | J23: FARMACIA
A24: Farmacia Sana Sana | B24: 15886.74 | C24: 6938.48 | D24: 10817.78 | E24: 33643 | F24: FARMACIA | G24: =E24/20 -> 1682.15 | I24: FARMACIA SAN PABLO | J24: FARMACIA
A25: Mercado Libre | B25: 59263.58 | C25: 44845.1 | D25: 36613.75 | E25: 140722.43 | F25: E-COMERCE | G25: =E25/20 -> 7036.1215 | I25: FARMACIA SANA SANA | J25: FARMACIA
A26: Nadro | B26: 160522.75 | C26: 167106.42 | D26: 179791.78 | E26: 507420.95 | F26: DISTRIBUIDOR | G26: =E26/20 -> 25371.047 | I26: FORTUS | J26: INTERNO
A27: Walmart | B27: 854736.3 | C27: 1329463.4 | D27: 726531.96 | E27: 2910731.6 | F27: AUTOSERVICIO | G27: =E27/20 -> 145536.58 | I27: BASILICA DE GUADALUPE | J27: AUTOSERVICIO
A28: Total general | B28: 2552932.5 | C28: 3206014 | D28: 2090472.5 | E28: 7849419 | I28: MERCADO LIBRE | J28: E-COMERCE
I29: WALMART MARKETPLACE | J29: E-COMERCE
I30: COPPEL MARKETPLACE | J30: E-COMERCE
I31: Coppel | J31: AUTOSERVICIO
I32: LA GUADALUPANA | J32: AUTOSERVICIO
I33: AP DISTRIBUCION | J33: DISTRIBUIDOR
I34: DANIEL ZARCO SALINAS | J34: DOCTORES
I35: ANGELICA BENITEZ HERNANDEZ | J35: AUTOSERVICIO
I36: OPERADORA DE NEGOCIOS VITPOW | J36: AUTOSERVICIO
I37: PHARMA PLUS | J37: FARMACIA
C38: Etiquetas de fila | D38: Suma de MONTO | I38: PUBLICO EN GENERAL | J38: AUTOSERVICIO
C39: AUTOSERVICIO | D39: 145536.58 | I39: FARMACOS NACIONALES | J39: DISTRIBUIDOR
C40: DISTRIBUIDOR | D40: 64315.983 | I40: FARMACIA LA FE | J40: FARMACIA
C41: E-COMERCE | D41: 14665.816 | I41: CONAFAR | J41: FARMACIA
C42: FARMACIA | D42: 167952.57
C43: Total general | D43: 392470.95

Sheet Venta Objetivo
A1: Fecha | B1: Nombre Producto | C1: Cliente | D1: Cantidad Vendida | E1: Precio de Venta | F1: Total de Venta | G1: categoria
A2: 45321 | B2: Nebulizador Adulto Walmart | C2: Walmart | D2: 3000 | E2: 498.66 | F2: =D2*E2 -> 1495980 | G2: =_xlfn.XLOOKUP(Metas[[#This Row],[Nombre Producto]],'Catalogo de Productos'!A:A,'Catalogo de Productos'!F:F,0,0) -> NEBULIZADORES
A3: 45322 | B3: Nebulizador Pediatrico Elefante Celeste | C3: Walmart | D3: 1500 | E3: 525.59 | F3: =D3*E3 -> 788385 | G3: =_xlfn.XLOOKUP(Metas[[#This Row],[Nombre Producto]],'Catalogo de Productos'!A:A,'Catalogo de Productos'!F:F,0,0) -> NEBULIZADORES
A4: 45322 | B4: Nebulizador Pediatrico Elefante Rosa | C4: Walmart | D4: 1500 | E4: 525.59 | F4: =D4*E4 -> 788385 | G4: =_xlfn.XLOOKUP(Metas[[#This Row],[Nombre Producto]],'Catalogo de Productos'!A:A,'Catalogo de Productos'!F:F,0,0) -> NEBULIZADORES
A5: 45322 | B5: Silla de Ruedas STD | C5: Walmart | D5: 375 | E5: 2434.2 | F5: =D5*E5 -> 912825 | G5: =_xlfn.XLOOKUP(Metas[[#This Row],[Nombre Producto]],'Catalogo de Productos'!A:A,'Catalogo de Productos'!F:F,0,0) -> MEDIOS AUXILIARES + SOPORTE
A6: 45322 | B6: Nebulizador Adulto Moderno NBA-10WA | C6: Walmart | D6: 375 | E6: 1292.4 | F6: =D6*E6 -> 484650 | G6: =_xlfn.XLOOKUP(Metas[[#This Row],[Nombre Producto]],'Catalogo de Productos'!A:A,'Catalogo de Productos'!F:F,0,0) -> NEBULIZADORES
A7: 45322 | B7: Silla de Baño con Respaldo | C7: Walmart | D7: 375 | E7: 958.4 | F7: =D7*E7 -> 359400 | G7: =_xlfn.XLOOKUP(Metas[[#This Row],[Nombre Producto]],'Catalogo de Productos'!A:A,'Catalogo de Productos'!F:F,0,0) -> MEDIOS AUXILIARES + SOPORTE
A8: 45322 | B8: Báscula Digital de Vidrio Marmol | C8: Walmart | D8: 250 | E8: 226 | F8: =D8*E8 -> 56500 | G8: =_xlfn.XLOOKUP(Metas[[#This Row],[Nombre Producto]],'Catalogo de Productos'!A:A,'Catalogo de Productos'!F:F,0,0) -> DISP MÉDICOS
A9: 45322 | B9: Báscula Digital de Vidrio Transparente | C9: Walmart | D9: 250 | E9: 226 | F9: =D9*E9 -> 56500 | G9: =_xlfn.XLOOKUP(Metas[[#This Row],[Nombre Producto]],'Catalogo de Productos'!A:A,'Catalogo de Productos'!F:F,0,0) -> DISP MÉDICOS
A10: 45322 | B10: Báscula Digital de Vidrio Antideslizante | C10: Walmart | D10: 250 | E10: 226 | F10: =D10*E10 -> 56500 | G10: =_xlfn.XLOOKUP(Metas[[#This Row],[Nombre Producto]],'Catalogo de Productos'!A:A,'Catalogo de Productos'!F:F,0,0) -> DISP MÉDICOS
A11: 45322 | B11: Cojin Cuadrad Memory Foam | C11: Walmart | D11: 375 | E11: 0 | F11: =D11*E11 -> 0 | G11: =_xlfn.XLOOKUP(Metas[[#This Row],[Nombre Producto]],'Catalogo de Productos'!A:A,'Catalogo de Productos'!F:F,0,0) -> MEDIOS AUXILIARES + SOPORTE
A12: 45322 | B12: Termómetro Pediatrico Cute Animals Osito | C12: Walmart | D12: 1500 | E12: 70.05 | F12: =D12*E12 -> 105075 | G12: =_xlfn.XLOOKUP(Metas[[#This Row],[Nombre Producto]],'Catalogo de Productos'!A:A,'Catalogo de Productos'!F:F,0,0) -> TERMOMETROS
A13: 45322 | B13: Termómetro Pediatrico Cute Animals Koala | C13: Walmart | D13: 1500 | E13: 70.05 | F13: =D13*E13 -> 105075 | G13: =_xlfn.XLOOKUP(Metas[[#This Row],[Nombre Producto]],'Catalogo de Productos'!A:A,'Catalogo de Productos'!F:F,0,0) -> TERMOMETROS
... A388: 45777 | B388: Termómetro Pediatrico Cute Animals Koala | C388: Market Place | D388: 240 | E388: 103.34 | F388: =D388*E388 -> 24801.6 | G388: =_xlfn.XLOOKUP(Metas[[#This Row],[Nombre Producto]],'Catalogo de Productos'!A:A,'Catalogo de Productos'!F:F,0,0) -> TERMOMETROS
A389: 45808 | B389: Nebulizador Adulto Walmart | C389: Walmart | D389: =1001.154*1.1 -> 1101.2694 | E389: 498.66 | F389: =D389*E389 -> 549159 | G389: =_xlfn.XLOOKUP(Metas[[#This Row],[Nombre Producto]],'Catalogo de Productos'!A:A,'Catalogo de Productos'!F:F,0,0) -> NEBULIZADORES
A390: 45808 | B390: Nebulizador Pediatrico Elefante Celeste | C390: Walmart | D390: =643.236*1.1 -> 707.5596 | E390: 525.59 | F390: =D390*E390 -> 371886.25 | G390: =_xlfn.XLOOKUP(Metas[[#This Row],[Nombre Producto]],'Catalogo de Productos'!A:A,'Catalogo de Productos'!F:F,0,0) -> NEBULIZADORES
A391: 45808 | B391: Termómetro Pediatrico Cute Animals Panda | C391: Walmart | D391: =3194.4*1.1 -> 3513.84 | E391: 70.05 | F391: =D391*E391 -> 246144.49 | G391: =_xlfn.XLOOKUP(Metas[[#This Row],[Nombre Producto]],'Catalogo de Productos'!A:A,'Catalogo de Productos'!F:F,0,0) -> TERMOMETROS
A392: 45808 | B392: Nebulizador Adulto Moderno Tapa Azul | C392: Market Place | D392: 12.1 | E392: 905.16 | F392: =D392*E392 -> 10952.436 | G392: =_xlfn.XLOOKUP(Metas[[#This Row],[Nombre Producto]],'Catalogo de Productos'!A:A,'Catalogo de Productos'!F:F,0,0) -> NEBULIZADORES
A393: 45808 | B393: Termómetro Pediatrico Cute Animals Koala | C393: Market Place | D393: 6.05 | E393: 137.92 | F393: =D393*E393 -> 834.416 | G393: =_xlfn.XLOOKUP(Metas[[#This Row],[Nombre Producto]],'Catalogo de Productos'!A:A,'Catalogo de Productos'!F:F,0,0) -> TERMOMETROS
A394: 45808 | B394: Termómetro Pediatrico Cute Animals Osito | C394: Market Place | D394: 6.05 | E394: 137.92 | F394: =D394*E394 -> 834.416 | G394: =_xlfn.XLOOKUP(Metas[[#This Row],[Nombre Producto]],'Catalogo de Productos'!A:A,'Catalogo de Productos'!F:F,0,0) -> TERMOMETROS
A395: 45808 | B395: Termómetro Pediatrico Cute Animals Panda | C395: Market Place | D395: 6.05 | E395: 137.92 | F395: =D395*E395 -> 834.416 | G395: =_xlfn.XLOOKUP(Metas[[#This Row],[Nombre Producto]],'Catalogo de Productos'!A:A,'Catalogo de Productos'!F:F,0,0) -> TERMOMETROS
A396: 45808 | B396: Termómetro Pediatrico Cute Animals Ranita | C396: Market Place | D396: 6.05 | E396: 137.92 | F396: =D396*E396 -> 834.416 | G396: =_xlfn.XLOOKUP(Metas[[#This Row],[Nombre Producto]],'Catalogo de Productos'!A:A,'Catalogo de Productos'!F:F,0,0) -> TERMOMETROS
A397: 45808 | B397: Báscula Digital de Vidrio Antideslizante | C397: Amazon | D397: =7.26*1.1 -> 7.986 | E397: 211.23 | F397: =D397*E397 -> 1686.8828 | G397: =_xlfn.XLOOKUP(Metas[[#This Row],[Nombre Producto]],'Catalogo de Productos'!A:A,'Catalogo de Productos'!F:F,0,0) -> DISP MÉDICOS
A398: 45808 | B398: Báscula Digital de Vidrio Marmol | C398: Amazon | D398: =7.26*1.1 -> 7.986 | E398: 211.23 | F398: =D398*E398 -> 1686.8828 | G398: =_xlfn.XLOOKUP(Metas[[#This Row],[Nombre Producto]],'Catalogo de Productos'!A:A,'Catalogo de Productos'!F:F,0,0) -> DISP MÉDICOS
A399: 45808 | B399: Báscula Digital de Vidrio Transparente | C399: Amazon | D399: =7.26*1.1 -> 7.986 | E399: 211.23 | F399: =D399*E399 -> 1686.8828 | G399: =_xlfn.XLOOKUP(Metas[[#This Row],[Nombre Producto]],'Catalogo de Productos'!A:A,'Catalogo de Productos'!F:F,0,0) -> DISP MÉDICOS
A400: 45808 | B400: Termómetro Pediatrico Cute Animals Koala | C400: Amazon | D400: =290.4*1.1 -> 319.44 | E400: 103.34 | F400: =D400*E400 -> 33010.93 | G400: =_xlfn.XLOOKUP(Metas[[#This Row],[Nombre Producto]],'Catalogo de Productos'!A:A,'Catalogo de Productos'!F:F,0,0) -> TERMOMETROS
A401: 45808 | B401: Termómetro Pediatrico Cute Animals Osito | C401: Amazon | D401: =290.4*1.1 -> 319.44 | E401: 103.34 | F401: =D401*E401 -> 33010.93 | G401: =_xlfn.XLOOKUP(Metas[[#This Row],[Nombre Producto]],'Catalogo de Productos'!A:A,'Catalogo de Productos'!F:F,0,0) -> TERMOMETROS
A402: 45808 | B402: Nebulizador Adulto Moderno Tapa Azul | C402: Market Place | D402: 6 | E402: 664.66 | F402: =D402*E402 -> 3987.96 | G402: =_xlfn.XLOOKUP(Metas[[#This Row],[Nombre Producto]],'Catalogo de Productos'!A:A,'Catalogo de Productos'!F:F,0,0) -> NEBULIZADORES
A403: 45808 | B403: Nebulizador Pediatrico Elefante Celeste | C403: Market Place | D403: 3 | E403: 718.25 | F403: =D403*E403 -> 2154.75 | G403: =_xlfn.XLOOKUP(Metas[[#This Row],[Nombre Producto]],'Catalogo de Productos'!A:A,'Catalogo de Productos'!F:F,0,0) -> NEBULIZADORES
A404: 45808 | B404: Nebulizador Pediatrico Elefante Rosa | C404: Market Place | D404: 3 | E404: 718.25 | F404: =D404*E404 -> 2154.75 | G404: =_xlfn.XLOOKUP(Metas[[#This Row],[Nombre Producto]],'Catalogo de Productos'!A:A,'Catalogo de Productos'!F:F,0,0) -> NEBULIZADORES
A405: 45808 | B405: Silla de Ruedas STD | C405: Market Place | D405: 1 | E405: 2200 | F405: =D405*E405 -> 2200 | G405: =_xlfn.XLOOKUP(Metas[[#This Row],[Nombre Producto]],'Catalogo de Productos'!A:A,'Catalogo de Productos'!F:F,0,0) -> MEDIOS AUXILIARES + SOPORTE
A406: 45808 | B406: Inodoro Portatil con tapa y brazo | C406: Market Place | D406: 1 | E406: 1280 | F406: =D406*E406 -> 1280 | G406: =_xlfn.XLOOKUP(Metas[[#This Row],[Nombre Producto]],'Catalogo de Productos'!A:A,'Catalogo de Productos'!F:F,0,0) -> MEDIOS AUXILIARES + SOPORTE
A407: 45808 | B407: Silla de Baño con Respaldo | C407: Market Place | D407: 1 | E407: 896.12 | F407: =D407*E407 -> 896.12 | G407: =_xlfn.XLOOKUP(Metas[[#This Row],[Nombre Producto]],'Catalogo de Productos'!A:A,'Catalogo de Productos'!F:F,0,0) -> MEDIOS AUXILIARES + SOPORTE
A408: 45808 | B408: Báscula Digital de Vidrio Antideslizante | C408: Market Place | D408: 2 | E408: 211.23 | F408: =D408*E408 -> 422.46 | G408: =_xlfn.XLOOKUP(Metas[[#This Row],[Nombre Producto]],'Catalogo de Productos'!A:A,'Catalogo de Productos'!F:F,0,0) -> DISP MÉDICOS
A409: 45808 | B409: Báscula Digital de Vidrio Marmol | C409: Market Place | D409: 2 | E409: 211.23 | F409: =D409*E409 -> 422.46 | G409: =_xlfn.XLOOKUP(Metas[[#This Row],[Nombre Producto]],'Catalogo de Productos'!A:A,'Catalogo de Productos'!F:F,0,0) -> DISP MÉDICOS
A410: 45808 | B410: Báscula Digital de Vidrio Transparente | C410: Market Place | D410: 2 | E410: 211.23 | F410: =D410*E410 -> 422.46 | G410: =_xlfn.XLOOKUP(Metas[[#This Row],[Nombre Producto]],'Catalogo de Productos'!A:A,'Catalogo de Productos'!F:F,0,0) -> DISP MÉDICOS
A411: 45808 | B411: Termómetro Pediatrico Cute Animals Koala | C411: Market Place | D411: 240 | E411: 103.34 | F411: =D411*E411 -> 24801.6 | G411: =_xlfn.XLOOKUP(Metas[[#This Row],[Nombre Producto]],'Catalogo de Productos'!A:A,'Catalogo de Productos'!F:F,0,0) -> TERMOMETROS
A412: 45808 | B412: Nebulizador Adulto Compacto | C412: Farmacia San Pablo | D412: =186.624*0.8 -> 149.2992 | E412: 505.86 | F412: =D412*E412 -> 75524.493 | G412: =_xlfn.XLOOKUP(Metas[[#This Row],[Nombre Producto]],'Catalogo de Productos'!A:A,'Catalogo de Productos'!F:F,0,0) -> NEBULIZADORES
A413: 45808 | B413: Nebulizador Pediatrico Elefante Celeste | C413: Farmacia San Pablo | D413: =373.248*0.8 -> 298.5984 | E413: 547.24 | F413: =D413*E413 -> 163404.99 | G413: =_xlfn.XLOOKUP(Metas[[#This Row],[Nombre Producto]],'Catalogo de Productos'!A:A,'Catalogo de Productos'!F:F,0,0) -> NEBULIZADORES
A414: 45808 | B414: Termómetro Pediatrico Cute Animals Koala | C414: Farmacia San Pablo | D414: =279.936*0.8 -> 223.9488 | E414: 71.38 | F414: =D414*E414 -> 15985.465 | G414: =_xlfn.XLOOKUP(Metas[[#This Row],[Nombre Producto]],'Catalogo de Productos'!A:A,'Catalogo de Productos'!F:F,0,0) -> TERMOMETROS
A415: 45808 | B415: Tarjeta Aromatizante con Frases Religiosas | C415: Basilica de Guadalupe | D415: 720 | E415: 15.09 | F415: =D415*E415 -> 10864.8 | G415: =_xlfn.XLOOKUP(Metas[[#This Row],[Nombre Producto]],'Catalogo de Productos'!A:A,'Catalogo de Productos'!F:F,0,0) -> AROMATIZANTES
A416: 45808 | B416: Tarjeta Aromatizante con Imágenes Religiosas | C416: Basilica de Guadalupe | D416: 720 | E416: 15.09 | F416: =D416*E416 -> 10864.8 | G416: =_xlfn.XLOOKUP(Metas[[#This Row],[Nombre Producto]],'Catalogo de Productos'!A:A,'Catalogo de Productos'!F:F,0,0) -> AROMATIZANTES
A417: 45808 | B417: Nebulizador Adulto Moderno Tapa Azul | C417: Nadro | D417: =551.25*1.05 -> 578.8125 | E417: 599.94 | F417: =D417*E417 -> 347252.77 | G417: =_xlfn.XLOOKUP(Metas[[#This Row],[Nombre Producto]],'Catalogo de Productos'!A:A,'Catalogo de Productos'!F:F,0,0) -> NEBULIZADORES
A418: 45808 | B418: Nebulizador Adulto Compacto | C418: Nadro | D418: =551.25*1.05 -> 578.8125 | E418: 587.41 | F418: =D418*E418 -> 340000.25 | G418: =_xlfn.XLOOKUP(Metas[[#This Row],[Nombre Producto]],'Catalogo de Productos'!A:A,'Catalogo de Productos'!F:F,0,0) -> NEBULIZADORES
A419: 45808 | B419: Nebulizador Pediatrico Elefante Celeste | C419: Nadro | D419: =275.625*1.05 -> 289.40625 | E419: 646.81 | F419: =D419*E419 -> 187190.86 | G419: =_xlfn.XLOOKUP(Metas[[#This Row],[Nombre Producto]],'Catalogo de Productos'!A:A,'Catalogo de Productos'!F:F,0,0) -> NEBULIZADORES
A420: 45808 | B420: Nebulizador Pediatrico Elefante Rosa | C420: Nadro | D420: =275.625*1.05 -> 289.40625 | E420: 646.81 | F420: =D420*E420 -> 187190.86 | G420: =_xlfn.XLOOKUP(Metas[[#This Row],[Nombre Producto]],'Catalogo de Productos'!A:A,'Catalogo de Productos'!F:F,0,0) -> NEBULIZADORES
A421: 45808 | B421: Termómetro Pediatrico Cute Animals Koala | C421: Nadro | D421: =275.625*1.05 -> 289.40625 | E421: 84.02 | F421: =D421*E421 -> 24315.913 | G421: =_xlfn.XLOOKUP(Metas[[#This Row],[Nombre Producto]],'Catalogo de Productos'!A:A,'Catalogo de Productos'!F:F,0,0) -> TERMOMETROS
A422: 45808 | B422: Termómetro Pediatrico Cute Animals Osito | C422: Nadro | D422: =275.625*1.05 -> 289.40625 | E422: 84.02 | F422: =D422*E422 -> 24315.913 | G422: =_xlfn.XLOOKUP(Metas[[#This Row],[Nombre Producto]],'Catalogo de Productos'!A:A,'Catalogo de Productos'!F:F,0,0) -> TERMOMETROS
A423: 45838 | B423: Nebulizador Adulto Walmart | C423: Walmart | D423: =1101.2694*1.1 -> 1211.3963 | E423: 498.66 | F423: =D423*E423 -> 604074.9 | G423: =_xlfn.XLOOKUP(Metas[[#This Row],[Nombre Producto]],'Catalogo de Productos'!A:A,'Catalogo de Productos'!F:F,0,0) -> NEBULIZADORES
A424: 45838 | B424: Nebulizador Pediatrico Elefante Celeste | C424: Walmart | D424: =707.5596*1.1 -> 778.31556 | E424: 525.59 | F424: =D424*E424 -> 409074.88 | G424: =_xlfn.XLOOKUP(Metas[[#This Row],[Nombre Producto]],'Catalogo de Productos'!A:A,'Catalogo de Productos'!F:F,0,0) -> NEBULIZADORES
A425: 45838 | B425: Termómetro Pediatrico Cute Animals Panda | C425: Walmart | D425: =3513.84*1.1 -> 3865.224 | E425: 70.05 | F425: =D425*E425 -> 270758.94 | G425: =_xlfn.XLOOKUP(Metas[[#This Row],[Nombre Producto]],'Catalogo de Productos'!A:A,'Catalogo de Productos'!F:F,0,0) -> TERMOMETROS
A426: 45838 | B426: Nebulizador Adulto Moderno Tapa Azul | C426: Market Place | D426: =12.1*1.1 -> 13.31 | E426: 905.16 | F426: =D426*E426 -> 12047.68 | G426: =_xlfn.XLOOKUP(Metas[[#This Row],[Nombre Producto]],'Catalogo de Productos'!A:A,'Catalogo de Productos'!F:F,0,0) -> NEBULIZADORES
A427: 45838 | B427: Termómetro Pediatrico Cute Animals Koala | C427: Market Place | D427: =6.05*1.1 -> 6.655 | E427: 137.92 | F427: =D427*E427 -> 917.8576 | G427: =_xlfn.XLOOKUP(Metas[[#This Row],[Nombre Producto]],'Catalogo de Productos'!A:A,'Catalogo de Productos'!F:F,0,0) -> TERMOMETROS
A428: 45838 | B428: Termómetro Pediatrico Cute Animals Osito | C428: Market Place | D428: =1.1*6.05 -> 6.655 | E428: 137.92 | F428: =D428*E428 -> 917.8576 | G428: =_xlfn.XLOOKUP(Metas[[#This Row],[Nombre Producto]],'Catalogo de Productos'!A:A,'Catalogo de Productos'!F:F,0,0) -> TERMOMETROS
A429: 45838 | B429: Termómetro Pediatrico Cute Animals Panda | C429: Market Place | D429: =1.1*6.05 -> 6.655 | E429: 137.92 | F429: =D429*E429 -> 917.8576 | G429: =_xlfn.XLOOKUP(Metas[[#This Row],[Nombre Producto]],'Catalogo de Productos'!A:A,'Catalogo de Productos'!F:F,0,0) -> TERMOMETROS
A430: 45838 | B430: Termómetro Pediatrico Cute Animals Ranita | C430: Market Place | D430: =1.1*6.05 -> 6.655 | E430: 137.92 | F430: =D430*E430 -> 917.8576 | G430: =_xlfn.XLOOKUP(Metas[[#This Row],[Nombre Producto]],'Catalogo de Productos'!A:A,'Catalogo de Productos'!F:F,0,0) -> TERMOMETROS
A431: 45838 | B431: Báscula Digital de Vidrio Antideslizante | C431: Amazon | D431: =1.1*7.986 -> 8.7846 | E431: 211.23 | F431: =D431*E431 -> 1855.5711 | G431: =_xlfn.XLOOKUP(Metas[[#This Row],[Nombre Producto]],'Catalogo de Productos'!A:A,'Catalogo de Productos'!F:F,0,0) -> DISP MÉDICOS
A432: 45838 | B432: Báscula Digital de Vidrio Marmol | C432: Amazon | D432: =1.1*7.986 -> 8.7846 | E432: 211.23 | F432: =D432*E432 -> 1855.5711 | G432: =_xlfn.XLOOKUP(Metas[[#This Row],[Nombre Producto]],'Catalogo de Productos'!A:A,'Catalogo de Productos'!F:F,0,0) -> DISP MÉDICOS
A433: 45838 | B433: Báscula Digital de Vidrio Transparente | C433: Amazon | D433: =1.1*7.986 -> 8.7846 | E433: 211.23 | F433: =D433*E433 -> 1855.5711 | G433: =_xlfn.XLOOKUP(Metas[[#This Row],[Nombre Producto]],'Catalogo de Productos'!A:A,'Catalogo de Productos'!F:F,0,0) -> DISP MÉDICOS
A434: 45838 | B434: Termómetro Pediatrico Cute Animals Koala | C434: Amazon | D434: =1.1*319.44 -> 351.384 | E434: 103.34 | F434: =D434*E434 -> 36312.023 | G434: =_xlfn.XLOOKUP(Metas[[#This Row],[Nombre Producto]],'Catalogo de Productos'!A:A,'Catalogo de Productos'!F:F,0,0) -> TERMOMETROS
A435: 45838 | B435: Termómetro Pediatrico Cute Animals Osito | C435: Amazon | D435: =1.1*319.44 -> 351.384 | E435: 103.34 | F435: =D435*E435 -> 36312.023 | G435: =_xlfn.XLOOKUP(Metas[[#This Row],[Nombre Producto]],'Catalogo de Productos'!A:A,'Catalogo de Productos'!F:F,0,0) -> TERMOMETROS
A436: 45838 | B436: Nebulizador Adulto Moderno Tapa Azul | C436: Market Place | D436: =1.1*6 -> 6.6 | E436: 664.66 | F436: =D436*E436 -> 4386.756 | G436: =_xlfn.XLOOKUP(Metas[[#This Row],[Nombre Producto]],'Catalogo de Productos'!A:A,'Catalogo de Productos'!F:F,0,0) -> NEBULIZADORES
A437: 45838 | B437: Nebulizador Pediatrico Elefante Celeste | C437: Market Place | D437: =1.1*3 -> 3.3 | E437: 718.25 | F437: =D437*E437 -> 2370.225 | G437: =_xlfn.XLOOKUP(Metas[[#This Row],[Nombre Producto]],'Catalogo de Productos'!A:A,'Catalogo de Productos'!F:F,0,0) -> NEBULIZADORES
A438: 45838 | B438: Nebulizador Pediatrico Elefante Rosa | C438: Market Place | D438: =1.1*3 -> 3.3 | E438: 718.25 | F438: =D438*E438 -> 2370.225 | G438: =_xlfn.XLOOKUP(Metas[[#This Row],[Nombre Producto]],'Catalogo de Productos'!A:A,'Catalogo de Productos'!F:F,0,0) -> NEBULIZADORES
A439: 45838 | B439: Silla de Ruedas STD | C439: Market Place | D439: =1.1*1 -> 1.1 | E439: 2200 | F439: =D439*E439 -> 2420 | G439: =_xlfn.XLOOKUP(Metas[[#This Row],[Nombre Producto]],'Catalogo de Productos'!A:A,'Catalogo de Productos'!F:F,0,0) -> MEDIOS AUXILIARES + SOPORTE
A440: 45838 | B440: Inodoro Portatil con tapa y brazo | C440: Market Place | D440: =1.1*1 -> 1.1 | E440: 1280 | F440: =D440*E440 -> 1408 | G440: =_xlfn.XLOOKUP(Metas[[#This Row],[Nombre Producto]],'Catalogo de Productos'!A:A,'Catalogo de Productos'!F:F,0,0) -> MEDIOS AUXILIARES + SOPORTE
A441: 45838 | B441: Silla de Baño con Respaldo | C441: Market Place | D441: =1.1*1 -> 1.1 | E441: 896.12 | F441: =D441*E441 -> 985.732 | G441: =_xlfn.XLOOKUP(Metas[[#This Row],[Nombre Producto]],'Catalogo de Productos'!A:A,'Catalogo de Productos'!F:F,0,0) -> MEDIOS AUXILIARES + SOPORTE
A442: 45838 | B442: Báscula Digital de Vidrio Antideslizante | C442: Market Place | D442: =1.1*2 -> 2.2 | E442: 211.23 | F442: =D442*E442 -> 464.706 | G442: =_xlfn.XLOOKUP(Metas[[#This Row],[Nombre Producto]],'Catalogo de Productos'!A:A,'Catalogo de Productos'!F:F,0,0) -> DISP MÉDICOS
A443: 45838 | B443: Báscula Digital de Vidrio Marmol | C443: Market Place | D443: =1.1*2 -> 2.2 | E443: 211.23 | F443: =D443*E443 -> 464.706 | G443: =_xlfn.XLOOKUP(Metas[[#This Row],[Nombre Producto]],'Catalogo de Productos'!A:A,'Catalogo de Productos'!F:F,0,0) -> DISP MÉDICOS
A444: 45838 | B444: Báscula Digital de Vidrio Transparente | C444: Market Place | D444: =1.1*2 -> 2.2 | E444: 211.23 | F444: =D444*E444 -> 464.706 | G444: =_xlfn.XLOOKUP(Metas[[#This Row],[Nombre Producto]],'Catalogo de Productos'!A:A,'Catalogo de Productos'!F:F,0,0) -> DISP MÉDICOS
A445: 45838 | B445: Termómetro Pediatrico Cute Animals Koala | C445: Market Place | D445: =1.1*240 -> 264 | E445: 103.34 | F445: =D445*E445 -> 27281.76 | G445: =_xlfn.XLOOKUP(Metas[[#This Row],[Nombre Producto]],'Catalogo de Productos'!A:A,'Catalogo de Productos'!F:F,0,0) -> TERMOMETROS
A446: 45838 | B446: Nebulizador Adulto Compacto | C446: Farmacia San Pablo | D446: =1.08*149.2992 -> 161.24314 | E446: 505.86 | F446: =D446*E446 -> 81566.453 | G446: =_xlfn.XLOOKUP(Metas[[#This Row],[Nombre Producto]],'Catalogo de Productos'!A:A,'Catalogo de Productos'!F:F,0,0) -> NEBULIZADORES
A447: 45838 | B447: Nebulizador Pediatrico Elefante Celeste | C447: Farmacia San Pablo | D447: =1.08*298.5984 -> 322.48627 | E447: 547.24 | F447: =D447*E447 -> 176477.39 | G447: =_xlfn.XLOOKUP(Metas[[#This Row],[Nombre Producto]],'Catalogo de Productos'!A:A,'Catalogo de Productos'!F:F,0,0) -> NEBULIZADORES
A448: 45838 | B448: Termómetro Pediatrico Cute Animals Koala | C448: Farmacia San Pablo | D448: =1.08*223.9488 -> 241.8647 | E448: 71.38 | F448: =D448*E448 -> 17264.303 | G448: =_xlfn.XLOOKUP(Metas[[#This Row],[Nombre Producto]],'Catalogo de Productos'!A:A,'Catalogo de Productos'!F:F,0,0) -> TERMOMETROS
A449: 45838 | B449: Tarjeta Aromatizante con Frases Religiosas | C449: Basilica de Guadalupe | D449: 720 | E449: 15.09 | F449: =D449*E449 -> 10864.8 | G449: =_xlfn.XLOOKUP(Metas[[#This Row],[Nombre Producto]],'Catalogo de Productos'!A:A,'Catalogo de Productos'!F:F,0,0) -> AROMATIZANTES
A450: 45838 | B450: Tarjeta Aromatizante con Imágenes Religiosas | C450: Basilica de Guadalupe | D450: 720 | E450: 15.09 | F450: =D450*E450 -> 10864.8 | G450: =_xlfn.XLOOKUP(Metas[[#This Row],[Nombre Producto]],'Catalogo de Productos'!A:A,'Catalogo de Productos'!F:F,0,0) -> AROMATIZANTES
A451: 45838 | B451: Nebulizador Adulto Moderno Tapa Azul | C451: Nadro | D451: =1.05*578.8125 -> 607.75313 | E451: 599.94 | F451: =D451*E451 -> 364615.41 | G451: =_xlfn.XLOOKUP(Metas[[#This Row],[Nombre Producto]],'Catalogo de Productos'!A:A,'Catalogo de Productos'!F:F,0,0) -> NEBULIZADORES
A452: 45838 | B452: Nebulizador Adulto Compacto | C452: Nadro | D452: =1.05*578.8125 -> 607.75313 | E452: 587.41 | F452: =D452*E452 -> 357000.26 | G452: =_xlfn.XLOOKUP(Metas[[#This Row],[Nombre Producto]],'Catalogo de Productos'!A:A,'Catalogo de Productos'!F:F,0,0) -> NEBULIZADORES
A453: 45838 | B453: Nebulizador Pediatrico Elefante Celeste | C453: Nadro | D453: =1.05*289.40625 -> 303.87656 | E453: 646.81 | F453: =D453*E453 -> 196550.4 | G453: =_xlfn.XLOOKUP(Metas[[#This Row],[Nombre Producto]],'Catalogo de Productos'!A:A,'Catalogo de Productos'!F:F,0,0) -> NEBULIZADORES
A454: 45838 | B454: Nebulizador Pediatrico Elefante Rosa | C454: Nadro | D454: =1.05*289.40625 -> 303.87656 | E454: 646.81 | F454: =D454*E454 -> 196550.4 | G454: =_xlfn.XLOOKUP(Metas[[#This Row],[Nombre Producto]],'Catalogo de Productos'!A:A,'Catalogo de Productos'!F:F,0,0) -> NEBULIZADORES
A455: 45838 | B455: Termómetro Pediatrico Cute Animals Koala | C455: Nadro | D455: =1.05*289.40625 -> 303.87656 | E455: 84.02 | F455: =D455*E455 -> 25531.709 | G455: =_xlfn.XLOOKUP(Metas[[#This Row],[Nombre Producto]],'Catalogo de Productos'!A:A,'Catalogo de Productos'!F:F,0,0) -> TERMOMETROS
A456: 45838 | B456: Termómetro Pediatrico Cute Animals Osito | C456: Nadro | D456: =1.05*289.40625 -> 303.87656 | E456: 84.02 | F456: =D456*E456 -> 25531.709 | G456: =_xlfn.XLOOKUP(Metas[[#This Row],[Nombre Producto]],'Catalogo de Productos'!A:A,'Catalogo de Productos'!F:F,0,0) -> TERMOMETROS
A457: 45869 | B457: Nebulizador Adulto Walmart | C457: Walmart | D457: =D423*1.1 -> 1332.536 | E457: 498.66 | F457: =D457*E457 -> 664482.39 | G457: =_xlfn.XLOOKUP(Metas[[#This Row],[Nombre Producto]],'Catalogo de Productos'!A:A,'Catalogo de Productos'!F:F,0,0) -> NEBULIZADORES
A458: 45869 | B458: Nebulizador Pediatrico Elefante Celeste | C458: Walmart | D458: =D424*1.1 -> 856.14712 | E458: 525.59 | F458: =D458*E458 -> 449982.36 | G458: =_xlfn.XLOOKUP(Metas[[#This Row],[Nombre Producto]],'Catalogo de Productos'!A:A,'Catalogo de Productos'!F:F,0,0) -> NEBULIZADORES
A459: 45869 | B459: Termómetro Pediatrico Cute Animals Panda | C459: Walmart | D459: =D425*1.1 -> 4251.7464 | E459: 70.05 | F459: =D459*E459 -> 297834.84 | G459: =_xlfn.XLOOKUP(Metas[[#This Row],[Nombre Producto]],'Catalogo de Productos'!A:A,'Catalogo de Productos'!F:F,0,0) -> TERMOMETROS
A460: 45869 | B460: Báscula Digital de Vidrio Antideslizante | C460: Amazon | D460: =D431*1.1 -> 9.66306 | E460: 211.23 | F460: =D460*E460 -> 2041.1282 | G460: =_xlfn.XLOOKUP(Metas[[#This Row],[Nombre Producto]],'Catalogo de Productos'!A:A,'Catalogo de Productos'!F:F,0,0) -> DISP MÉDICOS
A461: 45869 | B461: Báscula Digital de Vidrio Marmol | C461: Amazon | D461: =D432*1.1 -> 9.66306 | E461: 211.23 | F461: =D461*E461 -> 2041.1282 | G461: =_xlfn.XLOOKUP(Metas[[#This Row],[Nombre Producto]],'Catalogo de Productos'!A:A,'Catalogo de Productos'!F:F,0,0) -> DISP MÉDICOS
A462: 45869 | B462: Báscula Digital de Vidrio Transparente | C462: Amazon | D462: =D433*1.1 -> 9.66306 | E462: 211.23 | F462: =D462*E462 -> 2041.1282 | G462: =_xlfn.XLOOKUP(Metas[[#This Row],[Nombre Producto]],'Catalogo de Productos'!A:A,'Catalogo de Productos'!F:F,0,0) -> DISP MÉDICOS
A463: 45869 | B463: Termómetro Pediatrico Cute Animals Koala | C463: Amazon | D463: =D434*1.1 -> 386.5224 | E463: 103.34 | F463: =D463*E463 -> 39943.225 | G463: =_xlfn.XLOOKUP(Metas[[#This Row],[Nombre Producto]],'Catalogo de Productos'!A:A,'Catalogo de Productos'!F:F,0,0) -> TERMOMETROS
A464: 45869 | B464: Termómetro Pediatrico Cute Animals Osito | C464: Amazon | D464: =D435*1.1 -> 386.5224 | E464: 103.34 | F464: =D464*E464 -> 39943.225 | G464: =_xlfn.XLOOKUP(Metas[[#This Row],[Nombre Producto]],'Catalogo de Productos'!A:A,'Catalogo de Productos'!F:F,0,0) -> TERMOMETROS
A465: 45869 | B465: Tarjeta Aromatizante con Imágenes Religiosas | C465: Basilica de Guadalupe | D465: 720 | E465: 15.09 | F465: =D465*E465 -> 10864.8 | G465: =_xlfn.XLOOKUP(Metas[[#This Row],[Nombre Producto]],'Catalogo de Productos'!A:A,'Catalogo de Productos'!F:F,0,0) -> AROMATIZANTES
A466: 45869 | B466: Tarjeta Aromatizante con Frases Religiosas | C466: Basilica de Guadalupe | D466: 720 | E466: 15.09 | F466: =D466*E466 -> 10864.8 | G466: =_xlfn.XLOOKUP(Metas[[#This Row],[Nombre Producto]],'Catalogo de Productos'!A:A,'Catalogo de Productos'!F:F,0,0) -> AROMATIZANTES
A467: 45869 | B467: Nebulizador Adulto Compacto | C467: Farmacia San Pablo | D467: =D446*1.08 -> 174.14259 | E467: 505.86 | F467: =D467*E467 -> 88091.769 | G467: =_xlfn.XLOOKUP(Metas[[#This Row],[Nombre Producto]],'Catalogo de Productos'!A:A,'Catalogo de Productos'!F:F,0,0) -> NEBULIZADORES
A468: 45869 | B468: Nebulizador Pediatrico Elefante Celeste | C468: Farmacia San Pablo | D468: =D447*1.08 -> 348.28517 | E468: 547.24 | F468: =D468*E468 -> 190595.58 | G468: =_xlfn.XLOOKUP(Metas[[#This Row],[Nombre Producto]],'Catalogo de Productos'!A:A,'Catalogo de Productos'!F:F,0,0) -> NEBULIZADORES
A469: 45869 | B469: Termómetro Pediatrico Cute Animals Koala | C469: Farmacia San Pablo | D469: =D448*1.08 -> 261.21388 | E469: 71.38 | F469: =D469*E469 -> 18645.447 | G469: =_xlfn.XLOOKUP(Metas[[#This Row],[Nombre Producto]],'Catalogo de Productos'!A:A,'Catalogo de Productos'!F:F,0,0) -> TERMOMETROS
A470: 45869 | B470: Nebulizador Adulto Moderno Tapa Azul | C470: Nadro | D470: =D451*1.05 -> 638.14078 | E470: 599.94 | F470: =D470*E470 -> 382846.18 | G470: =_xlfn.XLOOKUP(Metas[[#This Row],[Nombre Producto]],'Catalogo de Productos'!A:A,'Catalogo de Productos'!F:F,0,0) -> NEBULIZADORES
A471: 45869 | B471: Nebulizador Adulto Compacto | C471: Nadro | D471: =D452*1.05 -> 638.14078 | E471: 587.41 | F471: =D471*E471 -> 374850.28 | G471: =_xlfn.XLOOKUP(Metas[[#This Row],[Nombre Producto]],'Catalogo de Productos'!A:A,'Catalogo de Productos'!F:F,0,0) -> NEBULIZADORES
A472: 45869 | B472: Nebulizador Pediatrico Elefante Celeste | C472: Nadro | D472: =D453*1.05 -> 319.07039 | E472: 646.81 | F472: =D472*E472 -> 206377.92 | G472: =_xlfn.XLOOKUP(Metas[[#This Row],[Nombre Producto]],'Catalogo de Productos'!A:A,'Catalogo de Productos'!F:F,0,0) -> NEBULIZADORES
A473: 45869 | B473: Nebulizador Pediatrico Elefante Rosa | C473: Nadro | D473: =D454*1.05 -> 319.07039 | E473: 646.81 | F473: =D473*E473 -> 206377.92 | G473: =_xlfn.XLOOKUP(Metas[[#This Row],[Nombre Producto]],'Catalogo de Productos'!A:A,'Catalogo de Productos'!F:F,0,0) -> NEBULIZADORES
A474: 45869 | B474: Termómetro Pediatrico Cute Animals Koala | C474: Nadro | D474: =D455*1.05 -> 319.07039 | E474: 84.02 | F474: =D474*E474 -> 26808.294 | G474: =_xlfn.XLOOKUP(Metas[[#This Row],[Nombre Producto]],'Catalogo de Productos'!A:A,'Catalogo de Productos'!F:F,0,0) -> TERMOMETROS
...

Sheet Inventario
A1: Fecha | B1: UPC | C1: Producto | D1: InventarioInicial | E1: Compras | F1: Ventas | G1: Devoluciones | H1: Ajustes | I1: Muestras | J1: Consignación | K1: Mermas | L1: InventarioFinal
A2: 45292 | B2: 7431009205975 | C2: Báscula Digital de Vidrio Antideslizante | D2: 0 | E2: 1002 | F2: 0 | G2: 0 | H2: 0 | I2: -2 | J2: 0 | K2: 0 | L2: 1000
A3: 45292 | B3: 7431009205968 | C3: Báscula Digital de Vidrio Marmol | D3: 0 | E3: 1002 | F3: 0 | G3: 0 | H3: 0 | I3: 0 | J3: 0 | K3: 0 | L3: 1002
A4: 45292 | B4: 7431009204879 | C4: Báscula Digital de Vidrio Transparente | D4: 0 | E4: 1002 | F4: 0 | G4: 0 | H4: 0 | I4: 0 | J4: 0 | K4: 0 | L4: 1002
A5: 45292 | B5: 7431009206804 | C5: Cojin Cuadrad Memory Foam | D5: 1500 | E5: 0 | F5: 0 | G5: 0 | H5: 0 | I5: 0 | J5: 0 | K5: 0 | L5: 1500
A6: 45292 | B6: N/A | C6: Ganchos de Plastico | D6: 0 | E6: 0 | F6: 0 | G6: 0 | H6: 0 | I6: 0 | J6: 0 | K6: 0 | L6: 0
A7: 45292 | B7: 7431009204985 | C7: Inodoro Portatil con tapa y brazo | D7: 450 | E7: 0 | F7: -4 | G7: 0 | H7: 0 | I7: 0 | J7: 0 | K7: 0 | L7: 446
A8: 45292 | B8: 7434002550000 | C8: Nebulizador Adulto Compacto | D8: 9120 | E8: 0 | F8: 0 | G8: 0 | H8: 0 | I8: 0 | J8: 0 | K8: 0 | L8: 9120
A9: 45292 | B9: 7431009204824 | C9: Nebulizador Adulto Moderno Tapa Azul | D9: 6270 | E9: 0 | F9: 0 | G9: 0 | H9: 0 | I9: 0 | J9: 0 | K9: 0 | L9: 6270
A10: 45292 | B10: 7434002550028 | C10: Nebulizador Adulto Walmart | D10: 7380 | E10: 0 | F10: 0 | G10: 0 | H10: 0 | I10: 0 | J10: 0 | K10: 0 | L10: 7380
A11: 45292 | B11: 7434002551490 | C11: Nebulizador Pediatrico Elefante Celeste | D11: 3882 | E11: 0 | F11: 0 | G11: 0 | H11: 0 | I11: -1 | J11: 0 | K11: 0 | L11: 3881
A12: 45292 | B12: 7434002551506 | C12: Nebulizador Pediatrico Elefante Rosa | D12: 3882 | E12: 0 | F12: 0 | G12: 0 | H12: 0 | I12: -1 | J12: 0 | K12: 0 | L12: 3881
A13: 45292 | B13: 7434002552640 | C13: Silla de Baño con Respaldo | D13: 850 | E13: 0 | F13: -4 | G13: 0 | H13: 0 | I13: 0 | J13: 0 | K13: 0 | L13: 846
A14: 45292 | B14: 7431009205050 | C14: Silla de Ruedas STD | D14: 354 | E14: 0 | F14: -3 | G14: 0 | H14: 0 | I14: 0 | J14: 0 | K14: 0 | L14: 351
A15: 45292 | B15: N/A | C15: Tablero de Papel | D15: 0 | E15: 0 | F15: 0 | G15: 0 | H15: 0 | I15: 0 | J15: 0 | K15: 0 | L15: 0
A16: 45292 | B16: 9999999999991 | C16: Tarjeta Aromatizante con Frases Religiosas | D16: 0 | E16: 0 | F16: 0 | G16: 0 | H16: 0 | I16: 0 | J16: 0 | K16: 0 | L16: 0
A17: 45292 | B17: 9999999999992 | C17: Tarjeta Aromatizante con Imágenes Religiosas | D17: 0 | E17: 0 | F17: 0 | G17: 0 | H17: 0 | I17: 0 | J17: 0 | K17: 0 | L17: 0
A18: 45292 | B18: 7431009207467 | C18: Termómetro Pediatrico Cute Animals Cerdito | D18: 0 | E18: 0 | F18: 0 | G18: 0 | H18: 0 | I18: 0 | J18: 0 | K18: 0 | L18: 0
A19: 45292 | B19: 7431009207504 | C19: Termómetro Pediatrico Cute Animals Koala | D19: 0 | E19: 10000 | F19: 0 | G19: 0 | H19: 0 | I19: 0 | J19: 0 | K19: 0 | L19: 10000
A20: 45292 | B20: 7431009207481 | C20: Termómetro Pediatrico Cute Animals Osito | D20: 0 | E20: 10000 | F20: 0 | G20: 0 | H20: 0 | I20: 0 | J20: 0 | K20: 0 | L20: 10000
A21: 45292 | B21: 7431009207498 | C21: Termómetro Pediatrico Cute Animals Panda | D21: 0 | E21: 10000 | F21: 0 | G21: 0 | H21: 0 | I21: 0 | J21: 0 | K21: 0 | L21: 10000
A22: 45292 | B22: 7431009207474 | C22: Termómetro Pediatrico Cute Animals Ranita | D22: 0 | E22: 10000 | F22: 0 | G22: 0 | H22: 0 | I22: 0 | J22: 0 | K22: 0 | L22: 10000
A23: 45323 | B23: 7431009205975 | C23: Báscula Digital de Vidrio Antideslizante | D23: 1000 | E23: 0 | F23: -18 | G23: 0 | H23: 0 | I23: -1 | J23: -6 | K23: 0 | L23: 975
A24: 45323 | B24: 7431009205968 | C24: Báscula Digital de Vidrio Marmol | D24: 1002 | E24: 0 | F24: -12 | G24: 0 | H24: 0 | I24: 0 | J24: 0 | K24: 0 | L24: 990
A25: 45323 | B25: 7431009204879 | C25: Báscula Digital de Vidrio Transparente | D25: 1002 | E25: 0 | F25: -12 | G25: 0 | H25: 0 | I25: 0 | J25: 0 | K25: 0 | L25: 990
A26: 45323 | B26: 7431009206804 | C26: Cojin Cuadrad Memory Foam | D26: 1500 | E26: 0 | F26: -6 | G26: 0 | H26: 0 | I26: 0 | J26: 0 | K26: 0 | L26: 1494
A27: 45323 | B27: N/A | C27: Ganchos de Plastico | D27: 0 | E27: 0 | F27: 0 | G27: 0 | H27: 0 | I27: 0 | J27: 0 | K27: 0 | L27: 0
A28: 45323 | B28: 7431009204985 | C28: Inodoro Portatil con tapa y brazo | D28: 446 | E28: 0 | F28: -2 | G28: 0 | H28: 0 | I28: 0 | J28: 0 | K28: 0 | L28: 444
A29: 45323 | B29: 7434002550000 | C29: Nebulizador Adulto Compacto | D29: 9120 | E29: 0 | F29: 0 | G29: 0 | H29: 0 | I29: 0 | J29: 0 | K29: 0 | L29: 9120
A30: 45323 | B30: 7431009204824 | C30: Nebulizador Adulto Moderno Tapa Azul | D30: 6270 | E30: 0 | F30: -18 | G30: 0 | H30: 0 | I30: -2 | J30: -5 | K30: 0 | L30: 6245
A31: 45323 | B31: 7434002550028 | C31: Nebulizador Adulto Walmart | D31: 7380 | E31: 0 | F31: 0 | G31: 0 | H31: 0 | I31: 0 | J31: 0 | K31: 0 | L31: 7380
A32: 45323 | B32: 7434002551490 | C32: Nebulizador Pediatrico Elefante Celeste | D32: 3881 | E32: 0 | F32: -6 | G32: 0 | H32: 0 | I32: -2 | J32: -6 | K32: 0 | L32: 3867
A33: 45323 | B33: 7434002551506 | C33: Nebulizador Pediatrico Elefante Rosa | D33: 3881 | E33: 0 | F33: -6 | G33: 0 | H33: 0 | I33: -2 | J33: -6 | K33: 0 | L33: 3867
A34: 45323 | B34: 7434002552640 | C34: Silla de Baño con Respaldo | D34: 846 | E34: 0 | F34: -2 | G34: 0 | H34: 0 | I34: 0 | J34: 0 | K34: 0 | L34: 844
A35: 45323 | B35: 7431009205050 | C35: Silla de Ruedas STD | D35: 351 | E35: 0 | F35: -1 | G35: 0 | H35: 0 | I35: 0 | J35: 0 | K35: 0 | L35: 350
A36: 45323 | B36: N/A | C36: Tablero de Papel | D36: 0 | E36: 0 | F36: 0 | G36: 0 | H36: 0 | I36: 0 | J36: 0 | K36: 0 | L36: 0
A37: 45323 | B37: 9999999999991 | C37: Tarjeta Aromatizante con Frases Religiosas | D37: 0 | E37: 0 | F37: 0 | G37: 0 | H37: 0 | I37: 0 | J37: 0 | K37: 0 | L37: 0
A38: 45323 | B38: 9999999999992 | C38: Tarjeta Aromatizante con Imágenes Religiosas | D38: 0 | E38: 0 | F38: 0 | G38: 0 | H38: 0 | I38: 0 | J38: 0 | K38: 0 | L38: 0
A39: 45323 | B39: 7431009207467 | C39: Termómetro Pediatrico Cute Animals Cerdito | D39: 0 | E39: 0 | F39: 0 | G39: 0 | H39: 0 | I39: 0 | J39: 0 | K39: 0 | L39: 0
A40: 45323 | B40: 7431009207504 | C40: Termómetro Pediatrico Cute Animals Koala | D40: 10000 | E40: 0 | F40: -260 | G40: 0 | H40: 0 | I40: -2 | J40: -14 | K40: 0 | L40: 9724
A41: 45323 | B41: 7431009207481 | C41: Termómetro Pediatrico Cute Animals Osito | D41: 10000 | E41: 0 | F41: -260 | G41: 0 | H41: 0 | I41: -2 | J41: -11 | K41: 0 | L41: 9727
A42: 45323 | B42: 7431009207498 | C42: Termómetro Pediatrico Cute Animals Panda | D42: 10000 | E42: 0 | F42: -260 | G42: 0 | H42: 0 | I42: -2 | J42: -16 | K42: 0 | L42: 9722
A43: 45323 | B43: 7431009207474 | C43: Termómetro Pediatrico Cute Animals Ranita | D43: 10000 | E43: 0 | F43: -260 | G43: 0 | H43: 0 | I43: -2 | J43: -15 | K43: 0 | L43: 9723
A44: 45352 | B44: 7431009205975 | C44: Báscula Digital de Vidrio Antideslizante | D44: 975 | E44: 0 | F44: 0 | G44: 0 | H44: 0 | I44: 0 | J44: 0 | K44: 0 | L44: 975
A45: 45352 | B45: 7431009205968 | C45: Báscula Digital de Vidrio Marmol | D45: 990 | E45: 0 | F45: 0 | G45: 0 | H45: 0 | I45: 0 | J45: 0 | K45: 0 | L45: 990
A46: 45352 | B46: 7431009204879 | C46: Báscula Digital de Vidrio Transparente | D46: 990 | E46: 0 | F46: 0 | G46: 0 | H46: 0 | I46: 0 | J46: 0 | K46: 0 | L46: 990
A47: 45352 | B47: 7431009206804 | C47: Cojin Cuadrad Memory Foam | D47: 1494 | E47: 0 | F47: 0 | G47: 0 | H47: 0 | I47: 0 | J47: 0 | K47: 0 | L47: 1494
A48: 45352 | B48: N/A | C48: Ganchos de Plastico | D48: 0 | E48: 0 | F48: 0 | G48: 0 | H48: 0 | I48: 0 | J48: 0 | K48: 0 | L48: 0
A49: 45352 | B49: 7431009204985 | C49: Inodoro Portatil con tapa y brazo | D49: 444 | E49: 0 | F49: 0 | G49: 0 | H49: 0 | I49: 0 | J49: 0 | K49: 0 | L49: 444
A50: 45352 | B50: 7434002550000 | C50: Nebulizador Adulto Compacto | D50: 9120 | E50: 0 | F50: 0 | G50: 0 | H50: 0 | I50: 0 | J50: 0 | K50: 0 | L50: 9120
A51: 45352 | B51: 7431009204824 | C51: Nebulizador Adulto Moderno Tapa Azul | D51: 6245 | E51: 0 | F51: 0 | G51: 0 | H51: 0 | I51: 0 | J51: 0 | K51: 0 | L51: 6245
A52: 45352 | B52: 7434002550028 | C52: Nebulizador Adulto Walmart | D52: 7380 | E52: 0 | F52: 0 | G52: 0 | H52: 0 | I52: 0 | J52: 0 | K52: 0 | L52: 7380
A53: 45352 | B53: 7434002551490 | C53: Nebulizador Pediatrico Elefante Celeste | D53: 3867 | E53: 0 | F53: 0 | G53: 0 | H53: 0 | I53: 0 | J53: 0 | K53: 0 | L53: 3867
A54: 45352 | B54: 7434002551506 | C54: Nebulizador Pediatrico Elefante Rosa | D54: 3867 | E54: 0 | F54: 0 | G54: 0 | H54: 0 | I54: 0 | J54: 0 | K54: 0 | L54: 3867
A55: 45352 | B55: 7434002552640 | C55: Silla de Baño con Respaldo | D55: 844 | E55: 0 | F55: 0 | G55: 0 | H55: 0 | I55: 0 | J55: 0 | K55: 0 | L55: 844
A56: 45352 | B56: 7431009205050 | C56: Silla de Ruedas STD | D56: 350 | E56: 0 | F56: 0 | G56: 0 | H56: 0 | I56: 0 | J56: 0 | K56: 0 | L56: 350
A57: 45352 | B57: N/A | C57: Tablero de Papel | D57: 0 | E57: 0 | F57: 0 | G57: 0 | H57: 0 | I57: 0 | J57: 0 | K57: 0 | L57: 0
A58: 45352 | B58: 9999999999991 | C58: Tarjeta Aromatizante con Frases Religiosas | D58: 0 | E58: 0 | F58: 0 | G58: 0 | H58: 0 | I58: 0 | J58: 0 | K58: 0 | L58: 0
A59: 45352 | B59: 9999999999992 | C59: Tarjeta Aromatizante con Imágenes Religiosas | D59: 0 | E59: 0 | F59: 0 | G59: 0 | H59: 0 | I59: 0 | J59: 0 | K59: 0 | L59: 0
A60: 45352 | B60: 7431009207467 | C60: Termómetro Pediatrico Cute Animals Cerdito | D60: 0 | E60: 0 | F60: 0 | G60: 0 | H60: 0 | I60: 0 | J60: 0 | K60: 0 | L60: 0
A61: 45352 | B61: 7431009207504 | C61: Termómetro Pediatrico Cute Animals Koala | D61: 9724 | E61: 0 | F61: 0 | G61: 0 | H61: 0 | I61: 0 | J61: 0 | K61: 0 | L61: 9724
A62: 45352 | B62: 7431009207481 | C62: Termómetro Pediatrico Cute Animals Osito | D62: 9727 | E62: 0 | F62: 0 | G62: 0 | H62: 0 | I62: 0 | J62: 0 | K62: 0 | L62: 9727
A63: 45352 | B63: 7431009207498 | C63: Termómetro Pediatrico Cute Animals Panda | D63: 9722 | E63: 0 | F63: 0 | G63: 0 | H63: 0 | I63: 0 | J63: 0 | K63: 0 | L63: 9722
A64: 45352 | B64: 7431009207474 | C64: Termómetro Pediatrico Cute Animals Ranita | D64: 9723 | E64: 0 | F64: 0 | G64: 0 | H64: 0 | I64: 0 | J64: 0 | K64: 0 | L64: 9723
A65: 45383 | B65: 7431009205975 | C65: Báscula Digital de Vidrio Antideslizante | D65: 975 | E65: 0 | F65: 0 | G65: 0 | H65: 0 | I65: -2 | J65: 0 | K65: 0 | L65: 973
A66: 45383 | B66: 7431009205968 | C66: Báscula Digital de Vidrio Marmol | D66: 990 | E66: 0 | F66: 0 | G66: 0 | H66: 0 | I66: -2 | J66: 0 | K66: 0 | L66: 988
A67: 45383 | B67: 7431009204879 | C67: Báscula Digital de Vidrio Transparente | D67: 990 | E67: 0 | F67: 0 | G67: 0 | H67: 0 | I67: -2 | J67: 0 | K67: 0 | L67: 988
A68: 45383 | B68: 7431009206804 | C68: Cojin Cuadrad Memory Foam | D68: 1494 | E68: 0 | F68: 0 | G68: 0 | H68: 0 | I68: 0 | J68: 0 | K68: 0 | L68: 1494
A69: 45383 | B69: N/A | C69: Ganchos de Plastico | D69: 0 | E69: 0 | F69: 0 | G69: 0 | H69: 0 | I69: 0 | J69: 0 | K69: 0 | L69: 0
A70: 45383 | B70: 7431009204985 | C70: Inodoro Portatil con tapa y brazo | D70: 444 | E70: 0 | F70: 0 | G70: 0 | H70: 0 | I70: 0 | J70: 0 | K70: 0 | L70: 444
A71: 45383 | B71: 7434002550000 | C71: Nebulizador Adulto Compacto | D71: 9120 | E71: 0 | F71: 0 | G71: 0 | H71: 0 | I71: -2 | J71: 0 | K71: 0 | L71: 9118
A72: 45383 | B72: 7431009204824 | C72: Nebulizador Adulto Moderno Tapa Azul | D72: 6245 | E72: 0 | F72: 0 | G72: 0 | H72: 0 | I72: -2 | J72: 0 | K72: 0 | L72: 6243
A73: 45383 | B73: 7434002550028 | C73: Nebulizador Adulto Walmart | D73: 7380 | E73: 0 | F73: 0 | G73: 0 | H73: 0 | I73: 0 | J73: 0 | K73: 0 | L73: 7380
A74: 45383 | B74: 7434002551490 | C74: Nebulizador Pediatrico Elefante Celeste | D74: 3867 | E74: 0 | F74: 0 | G74: 0 | H74: 0 | I74: -2 | J74: 0 | K74: 0 | L74: 3865
A75: 45383 | B75: 7434002551506 | C75: Nebulizador Pediatrico Elefante Rosa | D75: 3867 | E75: 0 | F75: 0 | G75: 0 | H75: 0 | I75: -2 | J75: 0 | K75: 0 | L75: 3865
A76: 45383 | B76: 7434002552640 | C76: Silla de Baño con Respaldo | D76: 844 | E76: 0 | F76: 0 | G76: 0 | H76: 0 | I76: 0 | J76: 0 | K76: 0 | L76: 844
A77: 45383 | B77: 7431009205050 | C77: Silla de Ruedas STD | D77: 350 | E77: 0 | F77: 0 | G77: 0 | H77: 0 | I77: 0 | J77: 0 | K77: 0 | L77: 350
A78: 45383 | B78: N/A | C78: Tablero de Papel | D78: 0 | E78: 0 | F78: 0 | G78: 0 | H78: 0 | I78: 0 | J78: 0 | K78: 0 | L78: 0
A79: 45383 | B79: 9999999999991 | C79: Tarjeta Aromatizante con Frases Religiosas | D79: 0 | E79: 0 | F79: 0 | G79: 0 | H79: 0 | I79: 0 | J79: 0 | K79: 0 | L79: 0
A80: 45383 | B80: 9999999999992 | C80: Tarjeta Aromatizante con Imágenes Religiosas | D80: 0 | E80: 0 | F80: 0 | G80: 0 | H80: 0 | I80: 0 | J80: 0 | K80: 0 | L80: 0
A81: 45383 | B81: 7431009207467 | C81: Termómetro Pediatrico Cute Animals Cerdito | D81: 0 | E81: 0 | F81: 0 | G81: 0 | H81: 0 | I81: 0 | J81: 0 | K81: 0 | L81: 0
A82: 45383 | B82: 7431009207504 | C82: Termómetro Pediatrico Cute Animals Koala | D82: 9724 | E82: 0 | F82: 0 | G82: 0 | H82: 0 | I82: -2 | J82: 0 | K82: 0 | L82: 9722
A83: 45383 | B83: 7431009207481 | C83: Termómetro Pediatrico Cute Animals Osito | D83: 9727 | E83: 0 | F83: 0 | G83: 0 | H83: 0 | I83: -2 | J83: 0 | K83: 0 | L83: 9725
A84: 45383 | B84: 7431009207498 | C84: Termómetro Pediatrico Cute Animals Panda | D84: 9722 | E84: 0 | F84: 0 | G84: 0 | H84: 0 | I84: -2 | J84: 0 | K84: 0 | L84: 9720
A85: 45383 | B85: 7431009207474 | C85: Termómetro Pediatrico Cute Animals Ranita | D85: 9723 | E85: 0 | F85: 0 | G85: 0 | H85: 0 | I85: -2 | J85: 0 | K85: 0 | L85: 9721
A86: 45413 | B86: 7431009205975 | C86: Báscula Digital de Vidrio Antideslizante | D86: 973 | E86: 0 | F86: 0 | G86: 0 | H86: 0 | I86: 0 | J86: 0 | K86: 0 | L86: 973
A87: 45413 | B87: 7431009205968 | C87: Báscula Digital de Vidrio Marmol | D87: 988 | E87: 0 | F87: 0 | G87: 0 | H87: 0 | I87: 0 | J87: 0 | K87: 0 | L87: 988
A88: 45413 | B88: 7431009204879 | C88: Báscula Digital de Vidrio Transparente | D88: 988 | E88: 0 | F88: 0 | G88: 0 | H88: 0 | I88: 0 | J88: 0 | K88: 0 | L88: 988
A89: 45413 | B89: 7431009206804 | C89: Cojin Cuadrad Memory Foam | D89: 1494 | E89: 0 | F89: 0 | G89: 0 | H89: 0 | I89: 0 | J89: 0 | K89: 0 | L89: 1494
A90: 45413 | B90: N/A | C90: Ganchos de Plastico | D90: 0 | E90: 0 | F90: 0 | G90: 0 | H90: 0 | I90: 0 | J90: 0 | K90: 0 | L90: 0
A91: 45413 | B91: 7431009204985 | C91: Inodoro Portatil con tapa y brazo | D91: 444 | E91: 0 | F91: 0 | G91: 0 | H91: 0 | I91: 0 | J91: 0 | K91: 0 | L91: 444
A92: 45413 | B92: 7434002550000 | C92: Nebulizador Adulto Compacto | D92: 9118 | E92: 0 | F92: 0 | G92: 0 | H92: 0 | I92: 0 | J92: 0 | K92: 0 | L92: 9118
A93: 45413 | B93: 7431009204824 | C93: Nebulizador Adulto Moderno Tapa Azul | D93: 6243 | E93: 0 | F93: -2 | G93: 0 | H93: 0 | I93: 0 | J93: 0 | K93: 0 | L93: 6241
A94: 45413 | B94: 7434002550028 | C94: Nebulizador Adulto Walmart | D94: 7380 | E94: 0 | F94: 0 | G94: 0 | H94: 0 | I94: 0 | J94: 0 | K94: 0 | L94: 7380
A95: 45413 | B95: 7434002551490 | C95: Nebulizador Pediatrico Elefante Celeste | D95: 3865 | E95: 0 | F95: 0 | G95: 0 | H95: 0 | I95: 0 | J95: 0 | K95: 0 | L95: 3865
A96: 45413 | B96: 7434002551506 | C96: Nebulizador Pediatrico Elefante Rosa | D96: 3865 | E96: 0 | F96: 0 | G96: 0 | H96: 0 | I96: 0 | J96: 0 | K96: 0 | L96: 3865
A97: 45413 | B97: 7434002552640 | C97: Silla de Baño con Respaldo | D97: 844 | E97: 0 | F97: 0 | G97: 0 | H97: 0 | I97: 0 | J97: 0 | K97: 0 | L97: 844
A98: 45413 | B98: 7431009205050 | C98: Silla de Ruedas STD | D98: 350 | E98: 0 | F98: 0 | G98: 0 | H98: 0 | I98: 0 | J98: 0 | K98: 0 | L98: 350
A99: 45413 | B99: N/A | C99: Tablero de Papel | D99: 0 | E99: 0 | F99: 0 | G99: 0 | H99: 0 | I99: 0 | J99: 0 | K99: 0 | L99: 0
A100: 45413 | B100: 9999999999991 | C100: Tarjeta Aromatizante con Frases Religiosas | D100: 0 | E100: 0 | F100: 0 | G100: 0 | H100: 0 | I100: 0 | J100: 0 | K100: 0 | L100: 0
...
